Workbook
Name Criterio1: 'Empresas y UTE'!$AG$1:$AG$35
Name Criterio2: 'Empresas y UTE'!$AF$1:$AF$81
Name CriterioGrupo: 'Empresas y UTE'!$BW$1:$BW$68

Sheet Consulta de contratos
A1: CONSULTA DE CONTRATOS MUNICIPALES | K1: =IF(OR(B4="",B4="Sin filtro"),"",B4)
A2: Seleccione uno o varios criterios. Para retirar un criterio, elija «Sin filtro» en su lista. | K2: =IF(OR(B8="",B8="Sin filtro"),"",B8)
K3: =IF(OR(B10="",B10="Sin filtro"),"",B10)
A4: Distrito | B4: Sin filtro | E4: ▾ | K4: =IF(OR(B12="",B12="Sin filtro"),"",B12)
K5: =IF(OR(B14="",B14="Sin filtro"),"",B14)
A6: Grupo empresarial | B6: Sin filtro | E6: ▾ | K6: =IF(OR(B6="",B6="Sin filtro"),"",B6)
A8: Empresa / UTE | B8: Sin filtro | E8: ▾
A10: Área de Gobierno | B10: Sin filtro | E10: ▾
A12: Dirección General | B12: Sin filtro | E12: ▾
A14: Subdirección General | B14: Sin filtro | E14: ▾
A16: =IF(AND(K3<>"",K4<>"",COUNTIFS(Datos!$C$2:$C$1000,K3,Datos!$D$2:$D$1000,K4)=0),"Revise filtros: Área y Dirección General no son compatibles",IF(AND(K4<>"",K5<>"",COUNTIFS(Datos!$D$2:$D$1000,K4,Datos!$E$2:$E$1000,K5)=0),"Revise filtros: Dirección y Subdirección no son compatibles",IF(SUM(IF(K1="",0,1),IF(K2="",0,1),IF(K3="",0,1),IF(K4="",0,1),IF(K5="",0,1),IF(K6="",0,1))=0,"Seleccione un criterio para iniciar la consulta",IF(SUM(Datos!V2:V1000)=0,"Sin coincidencias. Retire o cambie un criterio.",SUM(Datos!V2:V1000)&" prestaciones encontradas")))) -> Seleccione un criterio para iniciar la consulta
A17: Distrito | B17: Subdirección General | C17: Empresa / UTE | D17: Denominación del contrato | E17: Lote | F17: Titular de la Dirección General | G17: Fin de vigencia registrado | H17: Prestación y particularidades
A18: =IF($J18=0,"",IF(INDEX(Datos!$A$2:$A$1000,$J18)="","",INDEX(Datos!$A$2:$A$1000,$J18))) | B18: =IF($J18=0,"",IF(INDEX(Datos!$E$2:$E$1000,$J18)="","",INDEX(Datos!$E$2:$E$1000,$J18))) | C18: =IF($J18=0,"",IF(INDEX(Datos!$I$2:$I$1000,$J18)="","",INDEX(Datos!$I$2:$I$1000,$J18))) | D18: =IF($J18=0,"",IF(INDEX(Datos!$F$2:$F$1000,$J18)="","",INDEX(Datos!$F$2:$F$1000,$J18))) | E18: =IF($J18=0,"",IF(INDEX(Datos!$H$2:$H$1000,$J18)="","",INDEX(Datos!$H$2:$H$1000,$J18))) | F18: =IF($J18=0,"",IF(INDEX(Datos!$N$2:$N$1000,$J18)="","",INDEX(Datos!$N$2:$N$1000,$J18))) | G18: =IF($J18=0,"",IF(INDEX(Datos!$M$2:$M$1000,$J18)="","",INDEX(Datos!$M$2:$M$1000,$J18))) | H18: =IF($J18=0,"",INDEX(Datos!$J$2:$J$1000,$J18)&IF(INDEX(Datos!$Q$2:$Q$1000,$J18)="",""," | "&INDEX(Datos!$Q$2:$Q$1000,$J18))) | J18: =IFERROR(MATCH(ROW()-17,Datos!$W$2:$W$1000,0),0) -> 0
A19: =IF($J19=0,"",IF(INDEX(Datos!$A$2:$A$1000,$J19)="","",INDEX(Datos!$A$2:$A$1000,$J19))) | B19: =IF($J19=0,"",IF(INDEX(Datos!$E$2:$E$1000,$J19)="","",INDEX(Datos!$E$2:$E$1000,$J19))) | C19: =IF($J19=0,"",IF(INDEX(Datos!$I$2:$I$1000,$J19)="","",INDEX(Datos!$I$2:$I$1000,$J19))) | D19: =IF($J19=0,"",IF(INDEX(Datos!$F$2:$F$1000,$J19)="","",INDEX(Datos!$F$2:$F$1000,$J19))) | E19: =IF($J19=0,"",IF(INDEX(Datos!$H$2:$H$1000,$J19)="","",INDEX(Datos!$H$2:$H$1000,$J19))) | F19: =IF($J19=0,"",IF(INDEX(Datos!$N$2:$N$1000,$J19)="","",INDEX(Datos!$N$2:$N$1000,$J19))) | G19: =IF($J19=0,"",IF(INDEX(Datos!$M$2:$M$1000,$J19)="","",INDEX(Datos!$M$2:$M$1000,$J19))) | H19: =IF($J19=0,"",INDEX(Datos!$J$2:$J$1000,$J19)&IF(INDEX(Datos!$Q$2:$Q$1000,$J19)="",""," | "&INDEX(Datos!$Q$2:$Q$1000,$J19))) | J19: =IFERROR(MATCH(ROW()-17,Datos!$W$2:$W$1000,0),0) -> 0
A20: =IF($J20=0,"",IF(INDEX(Datos!$A$2:$A$1000,$J20)="","",INDEX(Datos!$A$2:$A$1000,$J20))) | B20: =IF($J20=0,"",IF(INDEX(Datos!$E$2:$E$1000,$J20)="","",INDEX(Datos!$E$2:$E$1000,$J20))) | C20: =IF($J20=0,"",IF(INDEX(Datos!$I$2:$I$1000,$J20)="","",INDEX(Datos!$I$2:$I$1000,$J20))) | D20: =IF($J20=0,"",IF(INDEX(Datos!$F$2:$F$1000,$J20)="","",INDEX(Datos!$F$2:$F$1000,$J20))) | E20: =IF($J20=0,"",IF(INDEX(Datos!$H$2:$H$1000,$J20)="","",INDEX(Datos!$H$2:$H$1000,$J20))) | F20: =IF($J20=0,"",IF(INDEX(Datos!$N$2:$N$1000,$J20)="","",INDEX(Datos!$N$2:$N$1000,$J20))) | G20: =IF($J20=0,"",IF(INDEX(Datos!$M$2:$M$1000,$J20)="","",INDEX(Datos!$M$2:$M$1000,$J20))) | H20: =IF($J20=0,"",INDEX(Datos!$J$2:$J$1000,$J20)&IF(INDEX(Datos!$Q$2:$Q$1000,$J20)="",""," | "&INDEX(Datos!$Q$2:$Q$1000,$J20))) | J20: =IFERROR(MATCH(ROW()-17,Datos!$W$2:$W$1000,0),0) -> 0
A21: =IF($J21=0,"",IF(INDEX(Datos!$A$2:$A$1000,$J21)="","",INDEX(Datos!$A$2:$A$1000,$J21))) | B21: =IF($J21=0,"",IF(INDEX(Datos!$E$2:$E$1000,$J21)="","",INDEX(Datos!$E$2:$E$1000,$J21))) | C21: =IF($J21=0,"",IF(INDEX(Datos!$I$2:$I$1000,$J21)="","",INDEX(Datos!$I$2:$I$1000,$J21))) | D21: =IF($J21=0,"",IF(INDEX(Datos!$F$2:$F$1000,$J21)="","",INDEX(Datos!$F$2:$F$1000,$J21))) | E21: =IF($J21=0,"",IF(INDEX(Datos!$H$2:$H$1000,$J21)="","",INDEX(Datos!$H$2:$H$1000,$J21))) | F21: =IF($J21=0,"",IF(INDEX(Datos!$N$2:$N$1000,$J21)="","",INDEX(Datos!$N$2:$N$1000,$J21))) | G21: =IF($J21=0,"",IF(INDEX(Datos!$M$2:$M$1000,$J21)="","",INDEX(Datos!$M$2:$M$1000,$J21))) | H21: =IF($J21=0,"",INDEX(Datos!$J$2:$J$1000,$J21)&IF(INDEX(Datos!$Q$2:$Q$1000,$J21)="",""," | "&INDEX(Datos!$Q$2:$Q$1000,$J21))) | J21: =IFERROR(MATCH(ROW()-17,Datos!$W$2:$W$1000,0),0) -> 0
A22: =IF($J22=0,"",IF(INDEX(Datos!$A$2:$A$1000,$J22)="","",INDEX(Datos!$A$2:$A$1000,$J22))) | B22: =IF($J22=0,"",IF(INDEX(Datos!$E$2:$E$1000,$J22)="","",INDEX(Datos!$E$2:$E$1000,$J22))) | C22: =IF($J22=0,"",IF(INDEX(Datos!$I$2:$I$1000,$J22)="","",INDEX(Datos!$I$2:$I$1000,$J22))) | D22: =IF($J22=0,"",IF(INDEX(Datos!$F$2:$F$1000,$J22)="","",INDEX(Datos!$F$2:$F$1000,$J22))) | E22: =IF($J22=0,"",IF(INDEX(Datos!$H$2:$H$1000,$J22)="","",INDEX(Datos!$H$2:$H$1000,$J22))) | F22: =IF($J22=0,"",IF(INDEX(Datos!$N$2:$N$1000,$J22)="","",INDEX(Datos!$N$2:$N$1000,$J22))) | G22: =IF($J22=0,"",IF(INDEX(Datos!$M$2:$M$1000,$J22)="","",INDEX(Datos!$M$2:$M$1000,$J22))) | H22: =IF($J22=0,"",INDEX(Datos!$J$2:$J$1000,$J22)&IF(INDEX(Datos!$Q$2:$Q$1000,$J22)="",""," | "&INDEX(Datos!$Q$2:$Q$1000,$J22))) | J22: =IFERROR(MATCH(ROW()-17,Datos!$W$2:$W$1000,0),0) -> 0
A23: =IF($J23=0,"",IF(INDEX(Datos!$A$2:$A$1000,$J23)="","",INDEX(Datos!$A$2:$A$1000,$J23))) | B23: =IF($J23=0,"",IF(INDEX(Datos!$E$2:$E$1000,$J23)="","",INDEX(Datos!$E$2:$E$1000,$J23))) | C23: =IF($J23=0,"",IF(INDEX(Datos!$I$2:$I$1000,$J23)="","",INDEX(Datos!$I$2:$I$1000,$J23))) | D23: =IF($J23=0,"",IF(INDEX(Datos!$F$2:$F$1000,$J23)="","",INDEX(Datos!$F$2:$F$1000,$J23))) | E23: =IF($J23=0,"",IF(INDEX(Datos!$H$2:$H$1000,$J23)="","",INDEX(Datos!$H$2:$H$1000,$J23))) | F23: =IF($J23=0,"",IF(INDEX(Datos!$N$2:$N$1000,$J23)="","",INDEX(Datos!$N$2:$N$1000,$J23))) | G23: =IF($J23=0,"",IF(INDEX(Datos!$M$2:$M$1000,$J23)="","",INDEX(Datos!$M$2:$M$1000,$J23))) | H23: =IF($J23=0,"",INDEX(Datos!$J$2:$J$1000,$J23)&IF(INDEX(Datos!$Q$2:$Q$1000,$J23)="",""," | "&INDEX(Datos!$Q$2:$Q$1000,$J23))) | J23: =IFERROR(MATCH(ROW()-17,Datos!$W$2:$W$1000,0),0) -> 0
A24: =IF($J24=0,"",IF(INDEX(Datos!$A$2:$A$1000,$J24)="","",INDEX(Datos!$A$2:$A$1000,$J24))) | B24: =IF($J24=0,"",IF(INDEX(Datos!$E$2:$E$1000,$J24)="","",INDEX(Datos!$E$2:$E$1000,$J24))) | C24: =IF($J24=0,"",IF(INDEX(Datos!$I$2:$I$1000,$J24)="","",INDEX(Datos!$I$2:$I$1000,$J24))) | D24: =IF($J24=0,"",IF(INDEX(Datos!$F$2:$F$1000,$J24)="","",INDEX(Datos!$F$2:$F$1000,$J24))) | E24: =IF($J24=0,"",IF(INDEX(Datos!$H$2:$H$1000,$J24)="","",INDEX(Datos!$H$2:$H$1000,$J24))) | F24: =IF($J24=0,"",IF(INDEX(Datos!$N$2:$N$1000,$J24)="","",INDEX(Datos!$N$2:$N$1000,$J24))) | G24: =IF($J24=0,"",IF(INDEX(Datos!$M$2:$M$1000,$J24)="","",INDEX(Datos!$M$2:$M$1000,$J24))) | H24: =IF($J24=0,"",INDEX(Datos!$J$2:$J$1000,$J24)&IF(INDEX(Datos!$Q$2:$Q$1000,$J24)="",""," | "&INDEX(Datos!$Q$2:$Q$1000,$J24))) | J24: =IFERROR(MATCH(ROW()-17,Datos!$W$2:$W$1000,0),0) -> 0
A25: =IF($J25=0,"",IF(INDEX(Datos!$A$2:$A$1000,$J25)="","",INDEX(Datos!$A$2:$A$1000,$J25))) | B25: =IF($J25=0,"",IF(INDEX(Datos!$E$2:$E$1000,$J25)="","",INDEX(Datos!$E$2:$E$1000,$J25))) | C25: =IF($J25=0,"",IF(INDEX(Datos!$I$2:$I$1000,$J25)="","",INDEX(Datos!$I$2:$I$1000,$J25))) | D25: =IF($J25=0,"",IF(INDEX(Datos!$F$2:$F$1000,$J25)="","",INDEX(Datos!$F$2:$F$1000,$J25))) | E25: =IF($J25=0,"",IF(INDEX(Datos!$H$2:$H$1000,$J25)="","",INDEX(Datos!$H$2:$H$1000,$J25))) | F25: =IF($J25=0,"",IF(INDEX(Datos!$N$2:$N$1000,$J25)="","",INDEX(Datos!$N$2:$N$1000,$J25))) | G25: =IF($J25=0,"",IF(INDEX(Datos!$M$2:$M$1000,$J25)="","",INDEX(Datos!$M$2:$M$1000,$J25))) | H25: =IF($J25=0,"",INDEX(Datos!$J$2:$J$1000,$J25)&IF(INDEX(Datos!$Q$2:$Q$1000,$J25)="",""," | "&INDEX(Datos!$Q$2:$Q$1000,$J25))) | J25: =IFERROR(MATCH(ROW()-17,Datos!$W$2:$W$1000,0),0) -> 0
A26: =IF($J26=0,"",IF(INDEX(Datos!$A$2:$A$1000,$J26)="","",INDEX(Datos!$A$2:$A$1000,$J26))) | B26: =IF($J26=0,"",IF(INDEX(Datos!$E$2:$E$1000,$J26)="","",INDEX(Datos!$E$2:$E$1000,$J26))) | C26: =IF($J26=0,"",IF(INDEX(Datos!$I$2:$I$1000,$J26)="","",INDEX(Datos!$I$2:$I$1000,$J26))) | D26: =IF($J26=0,"",IF(INDEX(Datos!$F$2:$F$1000,$J26)="","",INDEX(Datos!$F$2:$F$1000,$J26))) | E26: =IF($J26=0,"",IF(INDEX(Datos!$H$2:$H$1000,$J26)="","",INDEX(Datos!$H$2:$H$1000,$J26))) | F26: =IF($J26=0,"",IF(INDEX(Datos!$N$2:$N$1000,$J26)="","",INDEX(Datos!$N$2:$N$1000,$J26))) | G26: =IF($J26=0,"",IF(INDEX(Datos!$M$2:$M$1000,$J26)="","",INDEX(Datos!$M$2:$M$1000,$J26))) | H26: =IF($J26=0,"",INDEX(Datos!$J$2:$J$1000,$J26)&IF(INDEX(Datos!$Q$2:$Q$1000,$J26)="",""," | "&INDEX(Datos!$Q$2:$Q$1000,$J26))) | J26: =IFERROR(MATCH(ROW()-17,Datos!$W$2:$W$1000,0),0) -> 0
A27: =IF($J27=0,"",IF(INDEX(Datos!$A$2:$A$1000,$J27)="","",INDEX(Datos!$A$2:$A$1000,$J27))) | B27: =IF($J27=0,"",IF(INDEX(Datos!$E$2:$E$1000,$J27)="","",INDEX(Datos!$E$2:$E$1000,$J27))) | C27: =IF($J27=0,"",IF(INDEX(Datos!$I$2:$I$1000,$J27)="","",INDEX(Datos!$I$2:$I$1000,$J27))) | D27: =IF($J27=0,"",IF(INDEX(Datos!$F$2:$F$1000,$J27)="","",INDEX(Datos!$F$2:$F$1000,$J27))) | E27: =IF($J27=0,"",IF(INDEX(Datos!$H$2:$H$1000,$J27)="","",INDEX(Datos!$H$2:$H$1000,$J27))) | F27: =IF($J27=0,"",IF(INDEX(Datos!$N$2:$N$1000,$J27)="","",INDEX(Datos!$N$2:$N$1000,$J27))) | G27: =IF($J27=0,"",IF(INDEX(Datos!$M$2:$M$1000,$J27)="","",INDEX(Datos!$M$2:$M$1000,$J27))) | H27: =IF($J27=0,"",INDEX(Datos!$J$2:$J$1000,$J27)&IF(INDEX(Datos!$Q$2:$Q$1000,$J27)="",""," | "&INDEX(Datos!$Q$2:$Q$1000,$J27))) | J27: =IFERROR(MATCH(ROW()-17,Datos!$W$2:$W$1000,0),0) -> 0
A28: =IF($J28=0,"",IF(INDEX(Datos!$A$2:$A$1000,$J28)="","",INDEX(Datos!$A$2:$A$1000,$J28))) | B28: =IF($J28=0,"",IF(INDEX(Datos!$E$2:$E$1000,$J28)="","",INDEX(Datos!$E$2:$E$1000,$J28))) | C28: =IF($J28=0,"",IF(INDEX(Datos!$I$2:$I$1000,$J28)="","",INDEX(Datos!$I$2:$I$1000,$J28))) | D28: =IF($J28=0,"",IF(INDEX(Datos!$F$2:$F$1000,$J28)="","",INDEX(Datos!$F$2:$F$1000,$J28))) | E28: =IF($J28=0,"",IF(INDEX(Datos!$H$2:$H$1000,$J28)="","",INDEX(Datos!$H$2:$H$1000,$J28))) | F28: =IF($J28=0,"",IF(INDEX(Datos!$N$2:$N$1000,$J28)="","",INDEX(Datos!$N$2:$N$1000,$J28))) | G28: =IF($J28=0,"",IF(INDEX(Datos!$M$2:$M$1000,$J28)="","",INDEX(Datos!$M$2:$M$1000,$J28))) | H28: =IF($J28=0,"",INDEX(Datos!$J$2:$J$1000,$J28)&IF(INDEX(Datos!$Q$2:$Q$1000,$J28)="",""," | "&INDEX(Datos!$Q$2:$Q$1000,$J28))) | J28: =IFERROR(MATCH(ROW()-17,Datos!$W$2:$W$1000,0),0) -> 0
A29: =IF($J29=0,"",IF(INDEX(Datos!$A$2:$A$1000,$J29)="","",INDEX(Datos!$A$2:$A$1000,$J29))) | B29: =IF($J29=0,"",IF(INDEX(Datos!$E$2:$E$1000,$J29)="","",INDEX(Datos!$E$2:$E$1000,$J29))) | C29: =IF($J29=0,"",IF(INDEX(Datos!$I$2:$I$1000,$J29)="","",INDEX(Datos!$I$2:$I$1000,$J29))) | D29: =IF($J29=0,"",IF(INDEX(Datos!$F$2:$F$1000,$J29)="","",INDEX(Datos!$F$2:$F$1000,$J29))) | E29: =IF($J29=0,"",IF(INDEX(Datos!$H$2:$H$1000,$J29)="","",INDEX(Datos!$H$2:$H$1000,$J29))) | F29: =IF($J29=0,"",IF(INDEX(Datos!$N$2:$N$1000,$J29)="","",INDEX(Datos!$N$2:$N$1000,$J29))) | G29: =IF($J29=0,"",IF(INDEX(Datos!$M$2:$M$1000,$J29)="","",INDEX(Datos!$M$2:$M$1000,$J29))) | H29: =IF($J29=0,"",INDEX(Datos!$J$2:$J$1000,$J29)&IF(INDEX(Datos!$Q$2:$Q$1000,$J29)="",""," | "&INDEX(Datos!$Q$2:$Q$1000,$J29))) | J29: =IFERROR(MATCH(ROW()-17,Datos!$W$2:$W$1000,0),0) -> 0
... A517: =IF($J517=0,"",IF(INDEX(Datos!$A$2:$A$1000,$J517)="","",INDEX(Datos!$A$2:$A$1000,$J517))) | B517: =IF($J517=0,"",IF(INDEX(Datos!$E$2:$E$1000,$J517)="","",INDEX(Datos!$E$2:$E$1000,$J517))) | C517: =IF($J517=0,"",IF(INDEX(Datos!$I$2:$I$1000,$J517)="","",INDEX(Datos!$I$2:$I$1000,$J517))) | D517: =IF($J517=0,"",IF(INDEX(Datos!$F$2:$F$1000,$J517)="","",INDEX(Datos!$F$2:$F$1000,$J517))) | E517: =IF($J517=0,"",IF(INDEX(Datos!$H$2:$H$1000,$J517)="","",INDEX(Datos!$H$2:$H$1000,$J517))) | F517: =IF($J517=0,"",IF(INDEX(Datos!$N$2:$N$1000,$J517)="","",INDEX(Datos!$N$2:$N$1000,$J517))) | G517: =IF($J517=0,"",IF(INDEX(Datos!$M$2:$M$1000,$J517)="","",INDEX(Datos!$M$2:$M$1000,$J517))) | H517: =IF($J517=0,"",INDEX(Datos!$J$2:$J$1000,$J517)&IF(INDEX(Datos!$Q$2:$Q$1000,$J517)="",""," | "&INDEX(Datos!$Q$2:$Q$1000,$J517))) | J517: =IFERROR(MATCH(ROW()-17,Datos!$W$2:$W$1000,0),0) -> 0

Sheet Datos
A1: Distrito | B1: Servicio | C1: Area de gobierno | D1: Direccion general | E1: Subdireccion / unidad | F1: Contrato | G1: Expediente | H1: Lote | I1: Empresa / UTE | J1: Prestacion | K1: Cobertura | L1: Inicio registrado (ver criterio) | M1: Fin registrado (ver criterio) | N1: Responsable DG | O1: Gestor del contrato | P1: Contacto publicado | Q1: Excepciones / limites | R1: Estado / pendientes | S1: Fuente | T1: ID relacion (PK propuesta) | U1: ID lote (FK propuesta) | X1: ESTADO DE VIGENCIA · 16/10/2026 | Y1: GRUPO/FAMILIA PARA BÚSQUEDA | Z1: CRITERIO VÍNCULO CORPORATIVO | AA1: REVISIÓN | AB1: ESTADO CONTRACTUAL | AC1: COBERTURA DEL LOTE | AD1: FECHAS: CRITERIO | AE1: REVISADO EL | AF1: CLAVES DE GRUPO
A2: Centro | B2: Residuos | C2: Área de Gobierno de Urbanismo, Medio Ambiente y Movilidad | D2: Dirección General de Servicios de Limpieza y Residuos | E2: Subdirección General de Recogida de Residuos | F2: Contenerización, recogida y transporte de residuos | G2: 131/2021/06296 | H2: 1 | I2: FCC MEDIO AMBIENTE, SA | J2: Recogida y transporte habitual | K2: Zona territorial del lote | L2: 44866 | M2: 47057 | N2: Víctor Manuel Sarabia Herrero | O2: No acreditado | P2: 010 / 914 800 010 (atencion municipal, no gestor directo) | Q2: Lote 1: eventos eje Castellana-Prado-Recoletos | R2: Concesión vigente; adjudicataria y fin 31/10/2028 contrastados en registro de concesiones municipal (15/10/2026). | FECHAS REVISADAS: Inicio 01/11/2022 acreditado por formalización de los cuatro lotes. | CONTROL DOCUMENTAL 21/10/2026: Adjudicación y fin publicados. Los cuatro lotes se pueden contrastar en el registro municipal de concesiones. Fin publicado: 31/10/2028. No generalizar ámbito de cada lote. [Base de evidencia: Portal municipal / resolución o resultado oficial consultado] | CONTRASTE ADICIONAL 21/10/2026: FUENTE MUNICIPAL: la concesión registra adjudicación diferenciada en los 4 lotes (FCC, UTE VAO, UTE Sur, CONTENUR) y fin contractual 31/10/2028. | S2: https://contratacion.madrid.es/concesiones/ https://contrataciondelestado.es/FileSystem/servlet/GetDocumentByIdServlet?DocumentIdParam=I52CDqtLbsdgHyWk6Tjc%2BH2t2QGKU1Ro9lcaZmb7V5J4T4CLRYtO18fD2fcADXQg90aL83OqQbUADSXvNu02Vt6kOzxNccJdTRf8umMgorI%3D&cifrado=QUC1GjXXSiLkydRHJBmbpw%3D%3D | T2: REL-0001 | U2: 131/2021/06296|1 | V2: =IF(AND(SUM(IF('Consulta de contratos'!$K$1="",0,1),IF('Consulta de contratos'!$K$2="",0,1),IF('Consulta de contratos'!$K$3="",0,1),IF('Consulta de contratos'!$K$4="",0,1),IF('Consulta de contratos'!$K$5="",0,1),IF('Consulta de contratos'!$K$6="",0,1))>0,OR('Consulta de contratos'!$K$1="",A2='Consulta de contratos'!$K$1),OR('Consulta de contratos'!$K$2="",I2='Consulta de contratos'!$K$2),OR('Consulta de contratos'!$K$3="",C2='Consulta de contratos'!$K$3),OR('Consulta de contratos'!$K$4="",D2='Consulta de contratos'!$K$4),OR('Consulta de contratos'!$K$5="",E2='Consulta de contratos'!$K$5),OR('Consulta de contratos'!$K$6="",IFERROR(ISNUMBER(SEARCH("|"&'Consulta de contratos'!$K$6&"|",AF2)),FALSE))),1,0) -> 0 | W2: =IF(V2=1,SUM($V$2:V2),0) -> 0 | X2: FIN REGISTRADO POSTERIOR · EJECUCIÓN A CONFIRMAR | Y2: FCC | Z2: Grupo/familia pendiente de confirmar legalmente | AA2: 16/10/2026 | AF2: |FCC|
A3: Centro | B3: Residuos | C3: Área de Gobierno de Urbanismo, Medio Ambiente y Movilidad | D3: Dirección General de Servicios de Limpieza y Residuos | E3: Subdirección General de Recogida de Residuos | F3: Contenerización, recogida y transporte de residuos | G3: 131/2021/06296 | H3: 4 | I3: CONTENUR SL | J3: Suministro, mantenimiento y limpieza de contenedores | K3: Toda la ciudad | L3: 44866 | M3: 47057 | N3: Víctor Manuel Sarabia Herrero | O3: No acreditado | P3: 010 / 914 800 010 (atencion municipal, no gestor directo) | Q3: No es vaciado ni recogida habitual | R3: Concesión vigente; adjudicataria y fin 31/10/2028 contrastados en registro de concesiones municipal (15/10/2026). | FECHAS REVISADAS: Inicio 01/11/2022 acreditado por formalización de los cuatro lotes. | CONTROL DOCUMENTAL 21/10/2026: Adjudicación y fin publicados. Los cuatro lotes se pueden contrastar en el registro municipal de concesiones. Fin publicado: 31/10/2028. No generalizar ámbito de cada lote. [Base de evidencia: Portal municipal / resolución o resultado oficial consultado] | CONTRASTE ADICIONAL 21/10/2026: FUENTE MUNICIPAL: la concesión registra adjudicación diferenciada en los 4 lotes (FCC, UTE VAO, UTE Sur, CONTENUR) y fin contractual 31/10/2028. | S3: https://contratacion.madrid.es/concesiones/ https://contrataciondelestado.es/FileSystem/servlet/GetDocumentByIdServlet?DocumentIdParam=I52CDqtLbsdgHyWk6Tjc%2BH2t2QGKU1Ro9lcaZmb7V5J4T4CLRYtO18fD2fcADXQg90aL83OqQbUADSXvNu02Vt6kOzxNccJdTRf8umMgorI%3D&cifrado=QUC1GjXXSiLkydRHJBmbpw%3D%3D | T3: REL-0002 | U3: 131/2021/06296|4 | V3: =IF(AND(SUM(IF('Consulta de contratos'!$K$1="",0,1),IF('Consulta de contratos'!$K$2="",0,1),IF('Consulta de contratos'!$K$3="",0,1),IF('Consulta de contratos'!$K$4="",0,1),IF('Consulta de contratos'!$K$5="",0,1),IF('Consulta de contratos'!$K$6="",0,1))>0,OR('Consulta de contratos'!$K$1="",A3='Consulta de contratos'!$K$1),OR('Consulta de contratos'!$K$2="",I3='Consulta de contratos'!$K$2),OR('Consulta de contratos'!$K$3="",C3='Consulta de contratos'!$K$3),OR('Consulta de contratos'!$K$4="",D3='Consulta de contratos'!$K$4),OR('Consulta de contratos'!$K$5="",E3='Consulta de contratos'!$K$5),OR('Consulta de contratos'!$K$6="",IFERROR(ISNUMBER(SEARCH("|"&'Consulta de contratos'!$K$6&"|",AF3)),FALSE))),1,0) -> 0 | W3: =IF(V3=1,SUM($V$2:V3),0) -> 0 | X3: FIN REGISTRADO POSTERIOR · EJECUCIÓN A CONFIRMAR | Y3: CONTENUR SL | Z3: Agrupación de consulta por nombre de adjudicataria; no consta matriz contrastada. | AA3: 16/10/2026 | AF3: |CONTENUR SL|
A4: Centro | B4: Residuos | C4: Área de Gobierno de Urbanismo, Medio Ambiente y Movilidad | D4: Dirección General de Servicios de Limpieza y Residuos | E4: Subdirección General de Recogida de Residuos | F4: Contenerización, recogida y transporte de residuos | G4: 131/2021/06296 | H4: 3 | I4: UTE 2022 Recogida Madrid Sur | J4: Recogida de pilas y baterias usadas | K4: Toda la ciudad | L4: 44866 | M4: 47057 | N4: Víctor Manuel Sarabia Herrero | O4: No acreditado | P4: 010 / 914 800 010 (atencion municipal, no gestor directo) | Q4: Tarea especial del lote 3 fuera de su zona habitual | R4: Concesión vigente; adjudicataria y fin 31/10/2028 contrastados en registro de concesiones municipal (15/10/2026). | FECHAS REVISADAS: Inicio 01/11/2022 acreditado por formalización de los cuatro lotes. | CONTROL DOCUMENTAL 21/10/2026: Adjudicación y fin publicados. Los cuatro lotes se pueden contrastar en el registro municipal de concesiones. Fin publicado: 31/10/2028. No generalizar ámbito de cada lote. [Base de evidencia: Portal municipal / resolución o resultado oficial consultado] | CONTRASTE ADICIONAL 21/10/2026: FUENTE MUNICIPAL: la concesión registra adjudicación diferenciada en los 4 lotes (FCC, UTE VAO, UTE Sur, CONTENUR) y fin contractual 31/10/2028. | S4: https://contratacion.madrid.es/concesiones/ https://contrataciondelestado.es/FileSystem/servlet/GetDocumentByIdServlet?DocumentIdParam=I52CDqtLbsdgHyWk6Tjc%2BH2t2QGKU1Ro9lcaZmb7V5J4T4CLRYtO18fD2fcADXQg90aL83OqQbUADSXvNu02Vt6kOzxNccJdTRf8umMgorI%3D&cifrado=QUC1GjXXSiLkydRHJBmbpw%3D%3D | T4: REL-0003 | U4: 131/2021/06296|3 | V4: =IF(AND(SUM(IF('Consulta de contratos'!$K$1="",0,1),IF('Consulta de contratos'!$K$2="",0,1),IF('Consulta de contratos'!$K$3="",0,1),IF('Consulta de contratos'!$K$4="",0,1),IF('Consulta de contratos'!$K$5="",0,1),IF('Consulta de contratos'!$K$6="",0,1))>0,OR('Consulta de contratos'!$K$1="",A4='Consulta de contratos'!$K$1),OR('Consulta de contratos'!$K$2="",I4='Consulta de contratos'!$K$2),OR('Consulta de contratos'!$K$3="",C4='Consulta de contratos'!$K$3),OR('Consulta de contratos'!$K$4="",D4='Consulta de contratos'!$K$4),OR('Consulta de contratos'!$K$5="",E4='Consulta de contratos'!$K$5),OR('Consulta de contratos'!$K$6="",IFERROR(ISNUMBER(SEARCH("|"&'Consulta de contratos'!$K$6&"|",AF4)),FALSE))),1,0) -> 0 | W4: =IF(V4=1,SUM($V$2:V4),0) -> 0 | X4: FIN REGISTRADO POSTERIOR · EJECUCIÓN A CONFIRMAR | Y4: PREZERO | URBASER | Z4: UTE: vínculo comercial; no implica propiedad | AA4: 16/10/2026 | AF4: |PREZERO|URBASER|
A5: Centro | B5: Residuos | C5: Área de Gobierno de Urbanismo, Medio Ambiente y Movilidad | D5: Dirección General de Servicios de Limpieza y Residuos | E5: Subdirección General de Recogida de Residuos | F5: Asistencia técnica para el mantenimiento, ampliación y mejora continua del sistema de gestión de la información de limpieza urbana, recogida de residuos y equipamientos urbanos | G5: 300/2025/00411 | H5: Sin lotes | I5: APORTA PLATAFORMA COOPERATIVA SCCL | J5: Mantenimiento y mejora del sistema de informacion | K5: Ambito municipal; no contrato propio del distrito | M5: 46850 | N5: Víctor Manuel Sarabia Herrero | O5: No acreditado | P5: 010 / 914 800 010 (atencion municipal, no gestor directo) | R5: Adjudicado 27/01/2026 y formalizado 08/04/2026. Fin publicado 07/04/2028 (posible prórroga 12 meses). Inicio de prestación no acreditado. | FECHAS SIN ACREDITAR: Formalización 08/04/2026 y fin en agregador 07/04/2028; no consta fecha independiente de inicio de prestación. La formalización no se convierte en inicio automático. | FUENTES REVISADAS 21/10/2026: Ayuntamiento publica objeto y pliegos; registro TED del contrato identifica formalización el 08/04/2026 y adjudicataria Aporta. No equivale a fecha de inicio operativo. | CONTROL DOCUMENTAL 21/10/2026: Adjudicataria identificada. APORTA PLATAFORMA COOPERATIVA figura en la base y en fichas de licitación; comprobar firma e hitos en el expediente. [Base de evidencia: Datos confrontados con referencias aportadas; no hay resolución individual corroborada] | CONTRASTE ADICIONAL 21/10/2026: ADJUDICACIÓN: APORTA PLATAFORMA COOPERATIVA SCCL, resolución de 27/01/2026, contrastada con publicación de licitación. | S5: https://contratos.gobierto.es/adjudicatarios/aporta-plataforma-cooperativa-sccl?locale=es https://www.madrid.es/portales/munimadrid/es/Inicio/Medio-ambiente/Limpieza-urbana/Contrato-de-servicio-de-asistencia-tecnica/?vgnextchannel=ddd2a694fde40910VgnVCM2000001f4a900aRCRD&vgnextfmt=default&vgnextoid=7c07475398a4e910VgnVCM200000f921e388RCRD https://contratos.gobierto.es/licitaciones/4668721?locale=es | T5: REL-0004 | U5: 300/2025/00411|Sin lotes | V5: =IF(AND(SUM(IF('Consulta de contratos'!$K$1="",0,1),IF('Consulta de contratos'!$K$2="",0,1),IF('Consulta de contratos'!$K$3="",0,1),IF('Consulta de contratos'!$K$4="",0,1),IF('Consulta de contratos'!$K$5="",0,1),IF('Consulta de contratos'!$K$6="",0,1))>0,OR('Consulta de contratos'!$K$1="",A5='Consulta de contratos'!$K$1),OR('Consulta de contratos'!$K$2="",I5='Consulta de contratos'!$K$2),OR('Consulta de contratos'!$K$3="",C5='Consulta de contratos'!$K$3),OR('Consulta de contratos'!$K$4="",D5='Consulta de contratos'!$K$4),OR('Consulta de contratos'!$K$5="",E5='Consulta de contratos'!$K$5),OR('Consulta de contratos'!$K$6="",IFERROR(ISNUMBER(SEARCH("|"&'Consulta de contratos'!$K$6&"|",AF5)),FALSE))),1,0) -> 0 | W5: =IF(V5=1,SUM($V$2:V5),0) -> 0 | X5: FIN REGISTRADO POSTERIOR · EJECUCIÓN A CONFIRMAR | Y5: APORTA PLATAFORMA COOPERATIVA SCCL | Z5: Agrupación de consulta por nombre de adjudicataria; no consta matriz contrastada. | AA5: 16/10/2026 | AF5: |APORTA PLATAFORMA COOPERATIVA SCCL|
A6: Centro | B6: Residuos | C6: Área de Gobierno de Urbanismo, Medio Ambiente y Movilidad | D6: Dirección General de Servicios de Limpieza y Residuos | E6: Subdirección General de Recogida de Residuos | F6: Gestión del servicio de explotación de puntos limpios, centros de reutilización de residuos y saneamiento de viviendas | G6: 300/2023/00593 | H6: Sin lotes | I6: PREZERO ESPAÑA SAU | J6: Gestión de puntos limpios y centros de reutilización; saneamientos por requerimiento. | K6: Ambito municipal; ubicaciones concretas no incluidas | L6: 45622 | M6: 47447 | N6: Víctor Manuel Sarabia Herrero | O6: No acreditado | P6: 010 / 914 800 010 (atencion municipal, no gestor directo) | Q6: Saneamiento no es limpieza domestica ordinaria | R6: Vigente según Ayuntamiento; adjudicataria PREZERO acreditada (24/10/2024). Inicio contractual y fecha fin exacta sin acreditar. | FECHAS REVISADAS: Vigencia: 26/11/2024–25/11/2029. Inicio oficial; fin ordinario calculado por cinco años contractuales sin prórroga. | CONTROL DOCUMENTAL 21/10/2026: Adjudicataria identificada. PREZERO ESPAÑA figura adjudicataria de puntos limpios. El contrato es municipal; no son 21 concesiones independientes. [Base de evidencia: Datos confrontados con referencias aportadas; no hay resolución individual corroborada] | CONTRASTE ADICIONAL 21/10/2026: ADJUDICACIÓN: PREZERO ESPAÑA SA, 24/10/2024. El Ayuntamiento dispone de ficha oficial del contrato; compruébese formalización para fechas exactas. | S6: https://contratos.gobierto.es/licitaciones/4336157 https://contrataciondelestado.es/FileSystem/servlet/GetDocumentByIdServlet?DocumentIdParam=DX1ZAvwzaIUStPoibgXBVeTGIJOgffe86rdC19dt4dT5lTaSGg5Vq9cT4fT6Jv75jYAipcFv6g1zHenSv4lINo4IQyA7QON0MW%2BNRBCDa6cZyAJWGsSt0OzTSTyw9JAs&cifrado=QUC1GjXXSiLkydRHJBmbpw%3D%3D https://www.madrid.es/UnidadesDescentralizadas/LimpiezaUrbanaYResiduos/CONTRATOS_DG/CONTRATO-RES_PuntosLimpios/DocumentoPliegos_ContratoPuntosLimpios.pdf https://www.madrid.es/portales/munimadrid/es/Inicio/Medio-ambiente/Recogida-de-residuos/Contrato-de-servicios-de-explotacion-de-puntos-limpios-centros-de-reutilizacion-de-residuos-y-saneamiento-de-viviendas-en-la-ciudad-de-Madrid/?vgnextchannel=f81379ed268fe410VgnVCM1000000b205a0aRCRD&vgnextfmt=default&vgnextoid=8177150aabc46710VgnVCM2000001f4a900aRCRD | T6: REL-0005 | U6: 300/2023/00593|Sin lotes | V6: =IF(AND(SUM(IF('Consulta de contratos'!$K$1="",0,1),IF('Consulta de contratos'!$K$2="",0,1),IF('Consulta de contratos'!$K$3="",0,1),IF('Consulta de contratos'!$K$4="",0,1),IF('Consulta de contratos'!$K$5="",0,1),IF('Consulta de contratos'!$K$6="",0,1))>0,OR('Consulta de contratos'!$K$1="",A6='Consulta de contratos'!$K$1),OR('Consulta de contratos'!$K$2="",I6='Consulta de contratos'!$K$2),OR('Consulta de contratos'!$K$3="",C6='Consulta de contratos'!$K$3),OR('Consulta de contratos'!$K$4="",D6='Consulta de contratos'!$K$4),OR('Consulta de contratos'!$K$5="",E6='Consulta de contratos'!$K$5),OR('Consulta de contratos'!$K$6="",IFERROR(ISNUMBER(SEARCH("|"&'Consulta de contratos'!$K$6&"|",AF6)),FALSE))),1,0) -> 0 | W6: =IF(V6=1,SUM($V$2:V6),0) -> 0 | X6: FIN REGISTRADO POSTERIOR · EJECUCIÓN A CONFIRMAR | Y6: PREZERO | Z6: Grupo/familia pendiente de confirmar legalmente | AA6: 16/10/2026 | AF6: |PREZERO|
A7: Centro | B7: Residuos | C7: Área de Gobierno de Urbanismo, Medio Ambiente y Movilidad | D7: Dirección General de Servicios de Limpieza y Residuos | E7: Subdirección General de Recogida de Residuos | F7: Programa de actividades de sensibilización sobre separación de residuos y limpieza del espacio público | G7: 300/2026/00024 | H7: Sin lotes | I7: TALHER, S.A. | J7: Actividades educativas y de sensibilizacion | K7: Ambito municipal; no acredita actividad en cada distrito | N7: Víctor Manuel Sarabia Herrero | O7: No acreditado | P7: 010 / 914 800 010 (atencion municipal, no gestor directo) | Q7: Adjudicación publicada en datos de PLACSP; formalización e inicio efectivos sin contrastar. | ATENCIÓN · CONTRASTE 23/10/2026: el portal municipal incluye este expediente entre los contratos en vigor, mientras un agregador lo presenta como «Desistida». La resolución de adjudicación, la formalización y el inicio efectivo requieren comprobación directa. | R7: ADJUDICACIÓN 30/09/2026 A TALHER, S.A. (1.432.107 € sin IVA) recogida en LicitaLens a partir de PLACSP. Pendiente de verificar resolución y fecha de formalización en documento oficial; no certificar inicio efectivo. | CONTROL DOCUMENTAL 21/10/2026: Adjudicación localizada. Adjudicación a TALHER encontrada en plataformas que reproducen PLACSP; la resolución y la fecha de ejecución requieren lectura directa. [Base de evidencia: Ficha individual de publicación / agregador contrastada] | CONTRASTE DE FUENTES 23/10/2026: ficha municipal lo relaciona entre contratos en vigor; Gobierto muestra estado «Desistida», pese a reflejar datos de adjudicación del 30/09/2026. No tratar la formalización, la entrada en servicio ni la vigencia como acreditadas sin resolución. | S7: https://www.madrid.es/portales/munimadrid/es/Inicio/El-Ayuntamiento/Publicaciones/Listado-de-Publicaciones/Contratos-de-Recogida-de-Residuos/?vgnextchannel=f1aebadb6b997010VgnVCM100000dc0ca8c0RCRD&vgnextfmt=default&vgnextoid=429f71adf3d56910VgnVCM2000001f4a900aRCRD https://contratos.gobierto.es/licitaciones/5108890 https://licitalens.com/empresa/A08602815 https://www.madrid.es/portales/munimadrid/es/Inicio/Medio-ambiente/Recogida-de-residuos/Actividades-y-eventos/Contrato-de-servicio-de-actividades-de-sensibilizacion/?vgnextchannel=d04bbb21278fe410VgnVCM1000000b205a0aRCRD&vgnextfmt=default&vgnextoid=1d1f49ec5caef910VgnVCM200000f921e388RCRD | T7: REL-0006 | U7: 300/2026/00024|Sin lotes | V7: =IF(AND(SUM(IF('Consulta de contratos'!$K$1="",0,1),IF('Consulta de contratos'!$K$2="",0,1),IF('Consulta de contratos'!$K$3="",0,1),IF('Consulta de contratos'!$K$4="",0,1),IF('Consulta de contratos'!$K$5="",0,1),IF('Consulta de contratos'!$K$6="",0,1))>0,OR('Consulta de contratos'!$K$1="",A7='Consulta de contratos'!$K$1),OR('Consulta de contratos'!$K$2="",I7='Consulta de contratos'!$K$2),OR('Consulta de contratos'!$K$3="",C7='Consulta de contratos'!$K$3),OR('Consulta de contratos'!$K$4="",D7='Consulta de contratos'!$K$4),OR('Consulta de contratos'!$K$5="",E7='Consulta de contratos'!$K$5),OR('Consulta de contratos'!$K$6="",IFERROR(ISNUMBER(SEARCH("|"&'Consulta de contratos'!$K$6&"|",AF7)),FALSE))),1,0) -> 0 | W7: =IF(V7=1,SUM($V$2:V7),0) -> 0 | X7: ADJUDICACIÓN PUBLICADA EN DATOS PLACSP · FORMALIZACIÓN POR CONTRASTAR | Y7: CLECE | Z7: Grupo de empresa contrastado en fuente corporativa: https://clece.es/es/listado-clece-filiales/ | AA7: 16/10/2026 | AF7: |CLECE|
A8: Arganzuela | B8: Residuos | C8: Área de Gobierno de Urbanismo, Medio Ambiente y Movilidad | D8: Dirección General de Servicios de Limpieza y Residuos | E8: Subdirección General de Recogida de Residuos | F8: Contenerización, recogida y transporte de residuos | G8: 131/2021/06296 | H8: 3 | I8: UTE 2022 Recogida Madrid Sur | J8: Recogida y transporte habitual | K8: Zona territorial del lote | L8: 44866 | M8: 47057 | N8: Víctor Manuel Sarabia Herrero | O8: No acreditado | P8: 010 / 914 800 010 (atencion municipal, no gestor directo) | R8: Concesión vigente; adjudicataria y fin 31/10/2028 contrastados en registro de concesiones municipal (15/10/2026). | FECHAS REVISADAS: Inicio 01/11/2022 acreditado por formalización de los cuatro lotes. | CONTROL DOCUMENTAL 21/10/2026: Adjudicación y fin publicados. Los cuatro lotes se pueden contrastar en el registro municipal de concesiones. Fin publicado: 31/10/2028. No generalizar ámbito de cada lote. [Base de evidencia: Portal municipal / resolución o resultado oficial consultado] | CONTRASTE ADICIONAL 21/10/2026: FUENTE MUNICIPAL: la concesión registra adjudicación diferenciada en los 4 lotes (FCC, UTE VAO, UTE Sur, CONTENUR) y fin contractual 31/10/2028. | S8: https://contratacion.madrid.es/concesiones/ https://contrataciondelestado.es/FileSystem/servlet/GetDocumentByIdServlet?DocumentIdParam=I52CDqtLbsdgHyWk6Tjc%2BH2t2QGKU1Ro9lcaZmb7V5J4T4CLRYtO18fD2fcADXQg90aL83OqQbUADSXvNu02Vt6kOzxNccJdTRf8umMgorI%3D&cifrado=QUC1GjXXSiLkydRHJBmbpw%3D%3D | T8: REL-0007 | U8: 131/2021/06296|3 | V8: =IF(AND(SUM(IF('Consulta de contratos'!$K$1="",0,1),IF('Consulta de contratos'!$K$2="",0,1),IF('Consulta de contratos'!$K$3="",0,1),IF('Consulta de contratos'!$K$4="",0,1),IF('Consulta de contratos'!$K$5="",0,1),IF('Consulta de contratos'!$K$6="",0,1))>0,OR('Consulta de contratos'!$K$1="",A8='Consulta de contratos'!$K$1),OR('Consulta de contratos'!$K$2="",I8='Consulta de contratos'!$K$2),OR('Consulta de contratos'!$K$3="",C8='Consulta de contratos'!$K$3),OR('Consulta de contratos'!$K$4="",D8='Consulta de contratos'!$K$4),OR('Consulta de contratos'!$K$5="",E8='Consulta de contratos'!$K$5),OR('Consulta de contratos'!$K$6="",IFERROR(ISNUMBER(SEARCH("|"&'Consulta de contratos'!$K$6&"|",AF8)),FALSE))),1,0) -> 0 | W8: =IF(V8=1,SUM($V$2:V8),0) -> 0 | X8: FIN REGISTRADO POSTERIOR · EJECUCIÓN A CONFIRMAR | Y8: PREZERO | URBASER | Z8: UTE: vínculo comercial; no implica propiedad | AA8: 16/10/2026 | AF8: |PREZERO|URBASER|
A9: Arganzuela | B9: Residuos | C9: Área de Gobierno de Urbanismo, Medio Ambiente y Movilidad | D9: Dirección General de Servicios de Limpieza y Residuos | E9: Subdirección General de Recogida de Residuos | F9: Contenerización, recogida y transporte de residuos | G9: 131/2021/06296 | H9: 4 | I9: CONTENUR SL | J9: Suministro, mantenimiento y limpieza de contenedores | K9: Toda la ciudad | L9: 44866 | M9: 47057 | N9: Víctor Manuel Sarabia Herrero | O9: No acreditado | P9: 010 / 914 800 010 (atencion municipal, no gestor directo) | Q9: No es vaciado ni recogida habitual | R9: Concesión vigente; adjudicataria y fin 31/10/2028 contrastados en registro de concesiones municipal (15/10/2026). | FECHAS REVISADAS: Inicio 01/11/2022 acreditado por formalización de los cuatro lotes. | CONTROL DOCUMENTAL 21/10/2026: Adjudicación y fin publicados. Los cuatro lotes se pueden contrastar en el registro municipal de concesiones. Fin publicado: 31/10/2028. No generalizar ámbito de cada lote. [Base de evidencia: Portal municipal / resolución o resultado oficial consultado] | CONTRASTE ADICIONAL 21/10/2026: FUENTE MUNICIPAL: la concesión registra adjudicación diferenciada en los 4 lotes (FCC, UTE VAO, UTE Sur, CONTENUR) y fin contractual 31/10/2028. | S9: https://contratacion.madrid.es/concesiones/ https://contrataciondelestado.es/FileSystem/servlet/GetDocumentByIdServlet?DocumentIdParam=I52CDqtLbsdgHyWk6Tjc%2BH2t2QGKU1Ro9lcaZmb7V5J4T4CLRYtO18fD2fcADXQg90aL83OqQbUADSXvNu02Vt6kOzxNccJdTRf8umMgorI%3D&cifrado=QUC1GjXXSiLkydRHJBmbpw%3D%3D | T9: REL-0008 | U9: 131/2021/06296|4 | V9: =IF(AND(SUM(IF('Consulta de contratos'!$K$1="",0,1),IF('Consulta de contratos'!$K$2="",0,1),IF('Consulta de contratos'!$K$3="",0,1),IF('Consulta de contratos'!$K$4="",0,1),IF('Consulta de contratos'!$K$5="",0,1),IF('Consulta de contratos'!$K$6="",0,1))>0,OR('Consulta de contratos'!$K$1="",A9='Consulta de contratos'!$K$1),OR('Consulta de contratos'!$K$2="",I9='Consulta de contratos'!$K$2),OR('Consulta de contratos'!$K$3="",C9='Consulta de contratos'!$K$3),OR('Consulta de contratos'!$K$4="",D9='Consulta de contratos'!$K$4),OR('Consulta de contratos'!$K$5="",E9='Consulta de contratos'!$K$5),OR('Consulta de contratos'!$K$6="",IFERROR(ISNUMBER(SEARCH("|"&'Consulta de contratos'!$K$6&"|",AF9)),FALSE))),1,0) -> 0 | W9: =IF(V9=1,SUM($V$2:V9),0) -> 0 | X9: FIN REGISTRADO POSTERIOR · EJECUCIÓN A CONFIRMAR | Y9: CONTENUR SL | Z9: Agrupación de consulta por nombre de adjudicataria; no consta matriz contrastada. | AA9: 16/10/2026 | AF9: |CONTENUR SL|
A10: Arganzuela | B10: Residuos | C10: Área de Gobierno de Urbanismo, Medio Ambiente y Movilidad | D10: Dirección General de Servicios de Limpieza y Residuos | E10: Subdirección General de Recogida de Residuos | F10: Contenerización, recogida y transporte de residuos | G10: 131/2021/06296 | H10: 3 | I10: UTE 2022 Recogida Madrid Sur | J10: Recogida de pilas y baterias usadas | K10: Toda la ciudad | L10: 44866 | M10: 47057 | N10: Víctor Manuel Sarabia Herrero | O10: No acreditado | P10: 010 / 914 800 010 (atencion municipal, no gestor directo) | Q10: Tarea especial del lote 3 fuera de su zona habitual | R10: Concesión vigente; adjudicataria y fin 31/10/2028 contrastados en registro de concesiones municipal (15/10/2026). | FECHAS REVISADAS: Inicio 01/11/2022 acreditado por formalización de los cuatro lotes. | CONTROL DOCUMENTAL 21/10/2026: Adjudicación y fin publicados. Los cuatro lotes se pueden contrastar en el registro municipal de concesiones. Fin publicado: 31/10/2028. No generalizar ámbito de cada lote. [Base de evidencia: Portal municipal / resolución o resultado oficial consultado] | CONTRASTE ADICIONAL 21/10/2026: FUENTE MUNICIPAL: la concesión registra adjudicación diferenciada en los 4 lotes (FCC, UTE VAO, UTE Sur, CONTENUR) y fin contractual 31/10/2028. | S10: https://contratacion.madrid.es/concesiones/ https://contrataciondelestado.es/FileSystem/servlet/GetDocumentByIdServlet?DocumentIdParam=I52CDqtLbsdgHyWk6Tjc%2BH2t2QGKU1Ro9lcaZmb7V5J4T4CLRYtO18fD2fcADXQg90aL83OqQbUADSXvNu02Vt6kOzxNccJdTRf8umMgorI%3D&cifrado=QUC1GjXXSiLkydRHJBmbpw%3D%3D | T10: REL-0009 | U10: 131/2021/06296|3 | V10: =IF(AND(SUM(IF('Consulta de contratos'!$K$1="",0,1),IF('Consulta de contratos'!$K$2="",0,1),IF('Consulta de contratos'!$K$3="",0,1),IF('Consulta de contratos'!$K$4="",0,1),IF('Consulta de contratos'!$K$5="",0,1),IF('Consulta de contratos'!$K$6="",0,1))>0,OR('Consulta de contratos'!$K$1="",A10='Consulta de contratos'!$K$1),OR('Consulta de contratos'!$K$2="",I10='Consulta de contratos'!$K$2),OR('Consulta de contratos'!$K$3="",C10='Consulta de contratos'!$K$3),OR('Consulta de contratos'!$K$4="",D10='Consulta de contratos'!$K$4),OR('Consulta de contratos'!$K$5="",E10='Consulta de contratos'!$K$5),OR('Consulta de contratos'!$K$6="",IFERROR(ISNUMBER(SEARCH("|"&'Consulta de contratos'!$K$6&"|",AF10)),FALSE))),1,0) -> 0 | W10: =IF(V10=1,SUM($V$2:V10),0) -> 0 | X10: FIN REGISTRADO POSTERIOR · EJECUCIÓN A CONFIRMAR | Y10: PREZERO | URBASER | Z10: UTE: vínculo comercial; no implica propiedad | AA10: 16/10/2026 | AF10: |PREZERO|URBASER|
A11: Arganzuela | B11: Residuos | C11: Área de Gobierno de Urbanismo, Medio Ambiente y Movilidad | D11: Dirección General de Servicios de Limpieza y Residuos | E11: Subdirección General de Recogida de Residuos | F11: Asistencia técnica para el mantenimiento, ampliación y mejora continua del sistema de gestión de la información de limpieza urbana, recogida de residuos y equipamientos urbanos | G11: 300/2025/00411 | H11: Sin lotes | I11: APORTA PLATAFORMA COOPERATIVA SCCL | J11: Mantenimiento y mejora del sistema de informacion | K11: Ambito municipal; no contrato propio del distrito | M11: 46850 | N11: Víctor Manuel Sarabia Herrero | O11: No acreditado | P11: 010 / 914 800 010 (atencion municipal, no gestor directo) | R11: Adjudicado 27/01/2026 y formalizado 08/04/2026. Fin publicado 07/04/2028 (posible prórroga 12 meses). Inicio de prestación no acreditado. | FECHAS SIN ACREDITAR: Formalización 08/04/2026 y fin en agregador 07/04/2028; no consta fecha independiente de inicio de prestación. La formalización no se convierte en inicio automático. | FUENTES REVISADAS 21/10/2026: Ayuntamiento publica objeto y pliegos; registro TED del contrato identifica formalización el 08/04/2026 y adjudicataria Aporta. No equivale a fecha de inicio operativo. | CONTROL DOCUMENTAL 21/10/2026: Adjudicataria identificada. APORTA PLATAFORMA COOPERATIVA figura en la base y en fichas de licitación; comprobar firma e hitos en el expediente. [Base de evidencia: Datos confrontados con referencias aportadas; no hay resolución individual corroborada] | CONTRASTE ADICIONAL 21/10/2026: ADJUDICACIÓN: APORTA PLATAFORMA COOPERATIVA SCCL, resolución de 27/01/2026, contrastada con publicación de licitación. | S11: https://contratos.gobierto.es/adjudicatarios/aporta-plataforma-cooperativa-sccl?locale=es https://www.madrid.es/portales/munimadrid/es/Inicio/Medio-ambiente/Limpieza-urbana/Contrato-de-servicio-de-asistencia-tecnica/?vgnextchannel=ddd2a694fde40910VgnVCM2000001f4a900aRCRD&vgnextfmt=default&vgnextoid=7c07475398a4e910VgnVCM200000f921e388RCRD https://contratos.gobierto.es/licitaciones/4668721?locale=es | T11: REL-0010 | U11: 300/2025/00411|Sin lotes | V11: =IF(AND(SUM(IF('Consulta de contratos'!$K$1="",0,1),IF('Consulta de contratos'!$K$2="",0,1),IF('Consulta de contratos'!$K$3="",0,1),IF('Consulta de contratos'!$K$4="",0,1),IF('Consulta de contratos'!$K$5="",0,1),IF('Consulta de contratos'!$K$6="",0,1))>0,OR('Consulta de contratos'!$K$1="",A11='Consulta de contratos'!$K$1),OR('Consulta de contratos'!$K$2="",I11='Consulta de contratos'!$K$2),OR('Consulta de contratos'!$K$3="",C11='Consulta de contratos'!$K$3),OR('Consulta de contratos'!$K$4="",D11='Consulta de contratos'!$K$4),OR('Consulta de contratos'!$K$5="",E11='Consulta de contratos'!$K$5),OR('Consulta de contratos'!$K$6="",IFERROR(ISNUMBER(SEARCH("|"&'Consulta de contratos'!$K$6&"|",AF11)),FALSE))),1,0) -> 0 | W11: =IF(V11=1,SUM($V$2:V11),0) -> 0 | X11: FIN REGISTRADO POSTERIOR · EJECUCIÓN A CONFIRMAR | Y11: APORTA PLATAFORMA COOPERATIVA SCCL | Z11: Agrupación de consulta por nombre de adjudicataria; no consta matriz contrastada. | AA11: 16/10/2026 | AF11: |APORTA PLATAFORMA COOPERATIVA SCCL|
A12: Arganzuela | B12: Residuos | C12: Área de Gobierno de Urbanismo, Medio Ambiente y Movilidad | D12: Dirección General de Servicios de Limpieza y Residuos | E12: Subdirección General de Recogida de Residuos | F12: Gestión del servicio de explotación de puntos limpios, centros de reutilización de residuos y saneamiento de viviendas | G12: 300/2023/00593 | H12: Sin lotes | I12: PREZERO ESPAÑA SAU | J12: Gestión de puntos limpios y centros de reutilización; saneamientos por requerimiento. | K12: Ambito municipal; ubicaciones concretas no incluidas | L12: 45622 | M12: 47447 | N12: Víctor Manuel Sarabia Herrero | O12: No acreditado | P12: 010 / 914 800 010 (atencion municipal, no gestor directo) | Q12: Saneamiento no es limpieza domestica ordinaria | R12: Vigente según Ayuntamiento; adjudicataria PREZERO acreditada (24/10/2024). Inicio contractual y fecha fin exacta sin acreditar. | FECHAS REVISADAS: Vigencia: 26/11/2024–25/11/2029. Inicio oficial; fin ordinario calculado por cinco años contractuales sin prórroga. | CONTROL DOCUMENTAL 21/10/2026: Adjudicataria identificada. PREZERO ESPAÑA figura adjudicataria de puntos limpios. El contrato es municipal; no son 21 concesiones independientes. [Base de evidencia: Datos confrontados con referencias aportadas; no hay resolución individual corroborada] | CONTRASTE ADICIONAL 21/10/2026: ADJUDICACIÓN: PREZERO ESPAÑA SA, 24/10/2024. El Ayuntamiento dispone de ficha oficial del contrato; compruébese formalización para fechas exactas. | S12: https://contratos.gobierto.es/licitaciones/4336157 https://contrataciondelestado.es/FileSystem/servlet/GetDocumentByIdServlet?DocumentIdParam=DX1ZAvwzaIUStPoibgXBVeTGIJOgffe86rdC19dt4dT5lTaSGg5Vq9cT4fT6Jv75jYAipcFv6g1zHenSv4lINo4IQyA7QON0MW%2BNRBCDa6cZyAJWGsSt0OzTSTyw9JAs&cifrado=QUC1GjXXSiLkydRHJBmbpw%3D%3D https://www.madrid.es/UnidadesDescentralizadas/LimpiezaUrbanaYResiduos/CONTRATOS_DG/CONTRATO-RES_PuntosLimpios/DocumentoPliegos_ContratoPuntosLimpios.pdf https://www.madrid.es/portales/munimadrid/es/Inicio/Medio-ambiente/Recogida-de-residuos/Contrato-de-servicios-de-explotacion-de-puntos-limpios-centros-de-reutilizacion-de-residuos-y-saneamiento-de-viviendas-en-la-ciudad-de-Madrid/?vgnextchannel=f81379ed268fe410VgnVCM1000000b205a0aRCRD&vgnextfmt=default&vgnextoid=8177150aabc46710VgnVCM2000001f4a900aRCRD | T12: REL-0011 | U12: 300/2023/00593|Sin lotes | V12: =IF(AND(SUM(IF('Consulta de contratos'!$K$1="",0,1),IF('Consulta de contratos'!$K$2="",0,1),IF('Consulta de contratos'!$K$3="",0,1),IF('Consulta de contratos'!$K$4="",0,1),IF('Consulta de contratos'!$K$5="",0,1),IF('Consulta de contratos'!$K$6="",0,1))>0,OR('Consulta de contratos'!$K$1="",A12='Consulta de contratos'!$K$1),OR('Consulta de contratos'!$K$2="",I12='Consulta de contratos'!$K$2),OR('Consulta de contratos'!$K$3="",C12='Consulta de contratos'!$K$3),OR('Consulta de contratos'!$K$4="",D12='Consulta de contratos'!$K$4),OR('Consulta de contratos'!$K$5="",E12='Consulta de contratos'!$K$5),OR('Consulta de contratos'!$K$6="",IFERROR(ISNUMBER(SEARCH("|"&'Consulta de contratos'!$K$6&"|",AF12)),FALSE))),1,0) -> 0 | W12: =IF(V12=1,SUM($V$2:V12),0) -> 0 | X12: FIN REGISTRADO POSTERIOR · EJECUCIÓN A CONFIRMAR | Y12: PREZERO | Z12: Grupo/familia pendiente de confirmar legalmente | AA12: 16/10/2026 | AF12: |PREZERO|
A13: Arganzuela | B13: Residuos | C13: Área de Gobierno de Urbanismo, Medio Ambiente y Movilidad | D13: Dirección General de Servicios de Limpieza y Residuos | E13: Subdirección General de Recogida de Residuos | F13: Programa de actividades de sensibilización sobre separación de residuos y limpieza del espacio público | G13: 300/2026/00024 | H13: Sin lotes | I13: TALHER, S.A. | J13: Actividades educativas y de sensibilizacion | K13: Ambito municipal; no acredita actividad en cada distrito | N13: Víctor Manuel Sarabia Herrero | O13: No acreditado | P13: 010 / 914 800 010 (atencion municipal, no gestor directo) | Q13: Adjudicación publicada en datos de PLACSP; formalización e inicio efectivos sin contrastar. | ATENCIÓN · CONTRASTE 23/10/2026: el portal municipal incluye este expediente entre los contratos en vigor, mientras un agregador lo presenta como «Desistida». La resolución de adjudicación, la formalización y el inicio efectivo requieren comprobación directa. | R13: ADJUDICACIÓN 30/09/2026 A TALHER, S.A. (1.432.107 € sin IVA) recogida en LicitaLens a partir de PLACSP. Pendiente de verificar resolución y fecha de formalización en documento oficial; no certificar inicio efectivo. | CONTROL DOCUMENTAL 21/10/2026: Adjudicación localizada. Adjudicación a TALHER encontrada en plataformas que reproducen PLACSP; la resolución y la fecha de ejecución requieren lectura directa. [Base de evidencia: Ficha individual de publicación / agregador contrastada] | CONTRASTE DE FUENTES 23/10/2026: ficha municipal lo relaciona entre contratos en vigor; Gobierto muestra estado «Desistida», pese a reflejar datos de adjudicación del 30/09/2026. No tratar la formalización, la entrada en servicio ni la vigencia como acreditadas sin resolución. | S13: https://www.madrid.es/portales/munimadrid/es/Inicio/El-Ayuntamiento/Publicaciones/Listado-de-Publicaciones/Contratos-de-Recogida-de-Residuos/?vgnextchannel=f1aebadb6b997010VgnVCM100000dc0ca8c0RCRD&vgnextfmt=default&vgnextoid=429f71adf3d56910VgnVCM2000001f4a900aRCRD https://contratos.gobierto.es/licitaciones/5108890 https://licitalens.com/empresa/A08602815 https://www.madrid.es/portales/munimadrid/es/Inicio/Medio-ambiente/Recogida-de-residuos/Actividades-y-eventos/Contrato-de-servicio-de-actividades-de-sensibilizacion/?vgnextchannel=d04bbb21278fe410VgnVCM1000000b205a0aRCRD&vgnextfmt=default&vgnextoid=1d1f49ec5caef910VgnVCM200000f921e388RCRD | T13: REL-0012 | U13: 300/2026/00024|Sin lotes | V13: =IF(AND(SUM(IF('Consulta de contratos'!$K$1="",0,1),IF('Consulta de contratos'!$K$2="",0,1),IF('Consulta de contratos'!$K$3="",0,1),IF('Consulta de contratos'!$K$4="",0,1),IF('Consulta de contratos'!$K$5="",0,1),IF('Consulta de contratos'!$K$6="",0,1))>0,OR('Consulta de contratos'!$K$1="",A13='Consulta de contratos'!$K$1),OR('Consulta de contratos'!$K$2="",I13='Consulta de contratos'!$K$2),OR('Consulta de contratos'!$K$3="",C13='Consulta de contratos'!$K$3),OR('Consulta de contratos'!$K$4="",D13='Consulta de contratos'!$K$4),OR('Consulta de contratos'!$K$5="",E13='Consulta de contratos'!$K$5),OR('Consulta de contratos'!$K$6="",IFERROR(ISNUMBER(SEARCH("|"&'Consulta de contratos'!$K$6&"|",AF13)),FALSE))),1,0) -> 0 | W13: =IF(V13=1,SUM($V$2:V13),0) -> 0 | X13: ADJUDICACIÓN PUBLICADA EN DATOS PLACSP · FORMALIZACIÓN POR CONTRASTAR | Y13: CLECE | Z13: Grupo de empresa contrastado en fuente corporativa: https://clece.es/es/listado-clece-filiales/ | AA13: 16/10/2026 | AF13: |CLECE|
A14: Retiro | B14: Residuos | C14: Área de Gobierno de Urbanismo, Medio Ambiente y Movilidad | D14: Dirección General de Servicios de Limpieza y Residuos | E14: Subdirección General de Recogida de Residuos | F14: Contenerización, recogida y transporte de residuos | G14: 131/2021/06296 | H14: 2 | I14: UTE Recogida Madrid VAO | J14: Recogida y transporte habitual | K14: Zona territorial del lote | L14: 44866 | M14: 47057 | N14: Víctor Manuel Sarabia Herrero | O14: No acreditado | P14: 010 / 914 800 010 (atencion municipal, no gestor directo) | R14: Concesión vigente; adjudicataria y fin 31/10/2028 contrastados en registro de concesiones municipal (15/10/2026). | FECHAS REVISADAS: Inicio 01/11/2022 acreditado por formalización de los cuatro lotes. | CONTROL DOCUMENTAL 21/10/2026: Adjudicación y fin publicados. Los cuatro lotes se pueden contrastar en el registro municipal de concesiones. Fin publicado: 31/10/2028. No generalizar ámbito de cada lote. [Base de evidencia: Portal municipal / resolución o resultado oficial consultado] | CONTRASTE ADICIONAL 21/10/2026: FUENTE MUNICIPAL: la concesión registra adjudicación diferenciada en los 4 lotes (FCC, UTE VAO, UTE Sur, CONTENUR) y fin contractual 31/10/2028. | S14: https://contratacion.madrid.es/concesiones/ https://contrataciondelestado.es/FileSystem/servlet/GetDocumentByIdServlet?DocumentIdParam=I52CDqtLbsdgHyWk6Tjc%2BH2t2QGKU1Ro9lcaZmb7V5J4T4CLRYtO18fD2fcADXQg90aL83OqQbUADSXvNu02Vt6kOzxNccJdTRf8umMgorI%3D&cifrado=QUC1GjXXSiLkydRHJBmbpw%3D%3D | T14: REL-0013 | U14: 131/2021/06296|2 | V14: =IF(AND(SUM(IF('Consulta de contratos'!$K$1="",0,1),IF('Consulta de contratos'!$K$2="",0,1),IF('Consulta de contratos'!$K$3="",0,1),IF('Consulta de contratos'!$K$4="",0,1),IF('Consulta de contratos'!$K$5="",0,1),IF('Consulta de contratos'!$K$6="",0,1))>0,OR('Consulta de contratos'!$K$1="",A14='Consulta de contratos'!$K$1),OR('Consulta de contratos'!$K$2="",I14='Consulta de contratos'!$K$2),OR('Consulta de contratos'!$K$3="",C14='Consulta de contratos'!$K$3),OR('Consulta de contratos'!$K$4="",D14='Consulta de contratos'!$K$4),OR('Consulta de contratos'!$K$5="",E14='Consulta de contratos'!$K$5),OR('Consulta de contratos'!$K$6="",IFERROR(ISNUMBER(SEARCH("|"&'Consulta de contratos'!$K$6&"|",AF14)),FALSE))),1,0) -> 0 | W14: =IF(V14=1,SUM($V$2:V14),0) -> 0 | X14: FIN REGISTRADO POSTERIOR · EJECUCIÓN A CONFIRMAR | Y14: ACCIONA | VALORIZA | OHL / INGESAN | Z14: UTE: vínculo comercial; no implica propiedad | AA14: 16/10/2026 | AF14: |ACCIONA|VALORIZA|OHL / INGESAN|
A15: Retiro | B15: Residuos | C15: Área de Gobierno de Urbanismo, Medio Ambiente y Movilidad | D15: Dirección General de Servicios de Limpieza y Residuos | E15: Subdirección General de Recogida de Residuos | F15: Contenerización, recogida y transporte de residuos | G15: 131/2021/06296 | H15: 4 | I15: CONTENUR SL | J15: Suministro, mantenimiento y limpieza de contenedores | K15: Toda la ciudad | L15: 44866 | M15: 47057 | N15: Víctor Manuel Sarabia Herrero | O15: No acreditado | P15: 010 / 914 800 010 (atencion municipal, no gestor directo) | Q15: No es vaciado ni recogida habitual | R15: Concesión vigente; adjudicataria y fin 31/10/2028 contrastados en registro de concesiones municipal (15/10/2026). | FECHAS REVISADAS: Inicio 01/11/2022 acreditado por formalización de los cuatro lotes. | CONTROL DOCUMENTAL 21/10/2026: Adjudicación y fin publicados. Los cuatro lotes se pueden contrastar en el registro municipal de concesiones. Fin publicado: 31/10/2028. No generalizar ámbito de cada lote. [Base de evidencia: Portal municipal / resolución o resultado oficial consultado] | CONTRASTE ADICIONAL 21/10/2026: FUENTE MUNICIPAL: la concesión registra adjudicación diferenciada en los 4 lotes (FCC, UTE VAO, UTE Sur, CONTENUR) y fin contractual 31/10/2028. | S15: https://contratacion.madrid.es/concesiones/ https://contrataciondelestado.es/FileSystem/servlet/GetDocumentByIdServlet?DocumentIdParam=I52CDqtLbsdgHyWk6Tjc%2BH2t2QGKU1Ro9lcaZmb7V5J4T4CLRYtO18fD2fcADXQg90aL83OqQbUADSXvNu02Vt6kOzxNccJdTRf8umMgorI%3D&cifrado=QUC1GjXXSiLkydRHJBmbpw%3D%3D | T15: REL-0014 | U15: 131/2021/06296|4 | V15: =IF(AND(SUM(IF('Consulta de contratos'!$K$1="",0,1),IF('Consulta de contratos'!$K$2="",0,1),IF('Consulta de contratos'!$K$3="",0,1),IF('Consulta de contratos'!$K$4="",0,1),IF('Consulta de contratos'!$K$5="",0,1),IF('Consulta de contratos'!$K$6="",0,1))>0,OR('Consulta de contratos'!$K$1="",A15='Consulta de contratos'!$K$1),OR('Consulta de contratos'!$K$2="",I15='Consulta de contratos'!$K$2),OR('Consulta de contratos'!$K$3="",C15='Consulta de contratos'!$K$3),OR('Consulta de contratos'!$K$4="",D15='Consulta de contratos'!$K$4),OR('Consulta de contratos'!$K$5="",E15='Consulta de contratos'!$K$5),OR('Consulta de contratos'!$K$6="",IFERROR(ISNUMBER(SEARCH("|"&'Consulta de contratos'!$K$6&"|",AF15)),FALSE))),1,0) -> 0 | W15: =IF(V15=1,SUM($V$2:V15),0) -> 0 | X15: FIN REGISTRADO POSTERIOR · EJECUCIÓN A CONFIRMAR | Y15: CONTENUR SL | Z15: Agrupación de consulta por nombre de adjudicataria; no consta matriz contrastada. | AA15: 16/10/2026 | AF15: |CONTENUR SL|
A16: Retiro | B16: Residuos | C16: Área de Gobierno de Urbanismo, Medio Ambiente y Movilidad | D16: Dirección General de Servicios de Limpieza y Residuos | E16: Subdirección General de Recogida de Residuos | F16: Contenerización, recogida y transporte de residuos | G16: 131/2021/06296 | H16: 3 | I16: UTE 2022 Recogida Madrid Sur | J16: Recogida de pilas y baterias usadas | K16: Toda la ciudad | L16: 44866 | M16: 47057 | N16: Víctor Manuel Sarabia Herrero | O16: No acreditado | P16: 010 / 914 800 010 (atencion municipal, no gestor directo) | Q16: Tarea especial del lote 3 fuera de su zona habitual | R16: Concesión vigente; adjudicataria y fin 31/10/2028 contrastados en registro de concesiones municipal (15/10/2026). | FECHAS REVISADAS: Inicio 01/11/2022 acreditado por formalización de los cuatro lotes. | CONTROL DOCUMENTAL 21/10/2026: Adjudicación y fin publicados. Los cuatro lotes se pueden contrastar en el registro municipal de concesiones. Fin publicado: 31/10/2028. No generalizar ámbito de cada lote. [Base de evidencia: Portal municipal / resolución o resultado oficial consultado] | CONTRASTE ADICIONAL 21/10/2026: FUENTE MUNICIPAL: la concesión registra adjudicación diferenciada en los 4 lotes (FCC, UTE VAO, UTE Sur, CONTENUR) y fin contractual 31/10/2028. | S16: https://contratacion.madrid.es/concesiones/ https://contrataciondelestado.es/FileSystem/servlet/GetDocumentByIdServlet?DocumentIdParam=I52CDqtLbsdgHyWk6Tjc%2BH2t2QGKU1Ro9lcaZmb7V5J4T4CLRYtO18fD2fcADXQg90aL83OqQbUADSXvNu02Vt6kOzxNccJdTRf8umMgorI%3D&cifrado=QUC1GjXXSiLkydRHJBmbpw%3D%3D | T16: REL-0015 | U16: 131/2021/06296|3 | V16: =IF(AND(SUM(IF('Consulta de contratos'!$K$1="",0,1),IF('Consulta de contratos'!$K$2="",0,1),IF('Consulta de contratos'!$K$3="",0,1),IF('Consulta de contratos'!$K$4="",0,1),IF('Consulta de contratos'!$K$5="",0,1),IF('Consulta de contratos'!$K$6="",0,1))>0,OR('Consulta de contratos'!$K$1="",A16='Consulta de contratos'!$K$1),OR('Consulta de contratos'!$K$2="",I16='Consulta de contratos'!$K$2),OR('Consulta de contratos'!$K$3="",C16='Consulta de contratos'!$K$3),OR('Consulta de contratos'!$K$4="",D16='Consulta de contratos'!$K$4),OR('Consulta de contratos'!$K$5="",E16='Consulta de contratos'!$K$5),OR('Consulta de contratos'!$K$6="",IFERROR(ISNUMBER(SEARCH("|"&'Consulta de contratos'!$K$6&"|",AF16)),FALSE))),1,0) -> 0 | W16: =IF(V16=1,SUM($V$2:V16),0) -> 0 | X16: FIN REGISTRADO POSTERIOR · EJECUCIÓN A CONFIRMAR | Y16: PREZERO | URBASER | Z16: UTE: vínculo comercial; no implica propiedad | AA16: 16/10/2026 | AF16: |PREZERO|URBASER|
A17: Retiro | B17: Residuos | C17: Área de Gobierno de Urbanismo, Medio Ambiente y Movilidad | D17: Dirección General de Servicios de Limpieza y Residuos | E17: Subdirección General de Recogida de Residuos | F17: Asistencia técnica para el mantenimiento, ampliación y mejora continua del sistema de gestión de la información de limpieza urbana, recogida de residuos y equipamientos urbanos | G17: 300/2025/00411 | H17: Sin lotes | I17: APORTA PLATAFORMA COOPERATIVA SCCL | J17: Mantenimiento y mejora del sistema de informacion | K17: Ambito municipal; no contrato propio del distrito | M17: 46850 | N17: Víctor Manuel Sarabia Herrero | O17: No acreditado | P17: 010 / 914 800 010 (atencion municipal, no gestor directo) | R17: Adjudicado 27/01/2026 y formalizado 08/04/2026. Fin publicado 07/04/2028 (posible prórroga 12 meses). Inicio de prestación no acreditado. | FECHAS SIN ACREDITAR: Formalización 08/04/2026 y fin en agregador 07/04/2028; no consta fecha independiente de inicio de prestación. La formalización no se convierte en inicio automático. | FUENTES REVISADAS 21/10/2026: Ayuntamiento publica objeto y pliegos; registro TED del contrato identifica formalización el 08/04/2026 y adjudicataria Aporta. No equivale a fecha de inicio operativo. | CONTROL DOCUMENTAL 21/10/2026: Adjudicataria identificada. APORTA PLATAFORMA COOPERATIVA figura en la base y en fichas de licitación; comprobar firma e hitos en el expediente. [Base de evidencia: Datos confrontados con referencias aportadas; no hay resolución individual corroborada] | CONTRASTE ADICIONAL 21/10/2026: ADJUDICACIÓN: APORTA PLATAFORMA COOPERATIVA SCCL, resolución de 27/01/2026, contrastada con publicación de licitación. | S17: https://contratos.gobierto.es/adjudicatarios/aporta-plataforma-cooperativa-sccl?locale=es https://www.madrid.es/portales/munimadrid/es/Inicio/Medio-ambiente/Limpieza-urbana/Contrato-de-servicio-de-asistencia-tecnica/?vgnextchannel=ddd2a694fde40910VgnVCM2000001f4a900aRCRD&vgnextfmt=default&vgnextoid=7c07475398a4e910VgnVCM200000f921e388RCRD https://contratos.gobierto.es/licitaciones/4668721?locale=es | T17: REL-0016 | U17: 300/2025/00411|Sin lotes | V17: =IF(AND(SUM(IF('Consulta de contratos'!$K$1="",0,1),IF('Consulta de contratos'!$K$2="",0,1),IF('Consulta de contratos'!$K$3="",0,1),IF('Consulta de contratos'!$K$4="",0,1),IF('Consulta de contratos'!$K$5="",0,1),IF('Consulta de contratos'!$K$6="",0,1))>0,OR('Consulta de contratos'!$K$1="",A17='Consulta de contratos'!$K$1),OR('Consulta de contratos'!$K$2="",I17='Consulta de contratos'!$K$2),OR('Consulta de contratos'!$K$3="",C17='Consulta de contratos'!$K$3),OR('Consulta de contratos'!$K$4="",D17='Consulta de contratos'!$K$4),OR('Consulta de contratos'!$K$5="",E17='Consulta de contratos'!$K$5),OR('Consulta de contratos'!$K$6="",IFERROR(ISNUMBER(SEARCH("|"&'Consulta de contratos'!$K$6&"|",AF17)),FALSE))),1,0) -> 0 | W17: =IF(V17=1,SUM($V$2:V17),0) -> 0 | X17: FIN REGISTRADO POSTERIOR · EJECUCIÓN A CONFIRMAR | Y17: APORTA PLATAFORMA COOPERATIVA SCCL | Z17: Agrupación de consulta por nombre de adjudicataria; no consta matriz contrastada. | AA17: 16/10/2026 | AF17: |APORTA PLATAFORMA COOPERATIVA SCCL|
A18: Retiro | B18: Residuos | C18: Área de Gobierno de Urbanismo, Medio Ambiente y Movilidad | D18: Dirección General de Servicios de Limpieza y Residuos | E18: Subdirección General de Recogida de Residuos | F18: Gestión del servicio de explotación de puntos limpios, centros de reutilización de residuos y saneamiento de viviendas | G18: 300/2023/00593 | H18: Sin lotes | I18: PREZERO ESPAÑA SAU | J18: Gestión de puntos limpios y centros de reutilización; saneamientos por requerimiento. | K18: Ambito municipal; ubicaciones concretas no incluidas | L18: 45622 | M18: 47447 | N18: Víctor Manuel Sarabia Herrero | O18: No acreditado | P18: 010 / 914 800 010 (atencion municipal, no gestor directo) | Q18: Saneamiento no es limpieza domestica ordinaria | R18: Vigente según Ayuntamiento; adjudicataria PREZERO acreditada (24/10/2024). Inicio contractual y fecha fin exacta sin acreditar. | FECHAS REVISADAS: Vigencia: 26/11/2024–25/11/2029. Inicio oficial; fin ordinario calculado por cinco años contractuales sin prórroga. | CONTROL DOCUMENTAL 21/10/2026: Adjudicataria identificada. PREZERO ESPAÑA figura adjudicataria de puntos limpios. El contrato es municipal; no son 21 concesiones independientes. [Base de evidencia: Datos confrontados con referencias aportadas; no hay resolución individual corroborada] | CONTRASTE ADICIONAL 21/10/2026: ADJUDICACIÓN: PREZERO ESPAÑA SA, 24/10/2024. El Ayuntamiento dispone de ficha oficial del contrato; compruébese formalización para fechas exactas. | S18: https://contratos.gobierto.es/licitaciones/4336157 https://contrataciondelestado.es/FileSystem/servlet/GetDocumentByIdServlet?DocumentIdParam=DX1ZAvwzaIUStPoibgXBVeTGIJOgffe86rdC19dt4dT5lTaSGg5Vq9cT4fT6Jv75jYAipcFv6g1zHenSv4lINo4IQyA7QON0MW%2BNRBCDa6cZyAJWGsSt0OzTSTyw9JAs&cifrado=QUC1GjXXSiLkydRHJBmbpw%3D%3D https://www.madrid.es/UnidadesDescentralizadas/LimpiezaUrbanaYResiduos/CONTRATOS_DG/CONTRATO-RES_PuntosLimpios/DocumentoPliegos_ContratoPuntosLimpios.pdf https://www.madrid.es/portales/munimadrid/es/Inicio/Medio-ambiente/Recogida-de-residuos/Contrato-de-servicios-de-explotacion-de-puntos-limpios-centros-de-reutilizacion-de-residuos-y-saneamiento-de-viviendas-en-la-ciudad-de-Madrid/?vgnextchannel=f81379ed268fe410VgnVCM1000000b205a0aRCRD&vgnextfmt=default&vgnextoid=8177150aabc46710VgnVCM2000001f4a900aRCRD | T18: REL-0017 | U18: 300/2023/00593|Sin lotes | V18: =IF(AND(SUM(IF('Consulta de contratos'!$K$1="",0,1),IF('Consulta de contratos'!$K$2="",0,1),IF('Consulta de contratos'!$K$3="",0,1),IF('Consulta de contratos'!$K$4="",0,1),IF('Consulta de contratos'!$K$5="",0,1),IF('Consulta de contratos'!$K$6="",0,1))>0,OR('Consulta de contratos'!$K$1="",A18='Consulta de contratos'!$K$1),OR('Consulta de contratos'!$K$2="",I18='Consulta de contratos'!$K$2),OR('Consulta de contratos'!$K$3="",C18='Consulta de contratos'!$K$3),OR('Consulta de contratos'!$K$4="",D18='Consulta de contratos'!$K$4),OR('Consulta de contratos'!$K$5="",E18='Consulta de contratos'!$K$5),OR('Consulta de contratos'!$K$6="",IFERROR(ISNUMBER(SEARCH("|"&'Consulta de contratos'!$K$6&"|",AF18)),FALSE))),1,0) -> 0 | W18: =IF(V18=1,SUM($V$2:V18),0) -> 0 | X18: FIN REGISTRADO POSTERIOR · EJECUCIÓN A CONFIRMAR | Y18: PREZERO | Z18: Grupo/familia pendiente de confirmar legalmente | AA18: 16/10/2026 | AF18: |PREZERO|
A19: Retiro | B19: Residuos | C19: Área de Gobierno de Urbanismo, Medio Ambiente y Movilidad | D19: Dirección General de Servicios de Limpieza y Residuos | E19: Subdirección General de Recogida de Residuos | F19: Programa de actividades de sensibilización sobre separación de residuos y limpieza del espacio público | G19: 300/2026/00024 | H19: Sin lotes | I19: TALHER, S.A. | J19: Actividades educativas y de sensibilizacion | K19: Ambito municipal; no acredita actividad en cada distrito | N19: Víctor Manuel Sarabia Herrero | O19: No acreditado | P19: 010 / 914 800 010 (atencion municipal, no gestor directo) | Q19: Adjudicación publicada en datos de PLACSP; formalización e inicio efectivos sin contrastar. | ATENCIÓN · CONTRASTE 23/10/2026: el portal municipal incluye este expediente entre los contratos en vigor, mientras un agregador lo presenta como «Desistida». La resolución de adjudicación, la formalización y el inicio efectivo requieren comprobación directa. | R19: ADJUDICACIÓN 30/09/2026 A TALHER, S.A. (1.432.107 € sin IVA) recogida en LicitaLens a partir de PLACSP. Pendiente de verificar resolución y fecha de formalización en documento oficial; no certificar inicio efectivo. | CONTROL DOCUMENTAL 21/10/2026: Adjudicación localizada. Adjudicación a TALHER encontrada en plataformas que reproducen PLACSP; la resolución y la fecha de ejecución requieren lectura directa. [Base de evidencia: Ficha individual de publicación / agregador contrastada] | CONTRASTE DE FUENTES 23/10/2026: ficha municipal lo relaciona entre contratos en vigor; Gobierto muestra estado «Desistida», pese a reflejar datos de adjudicación del 30/09/2026. No tratar la formalización, la entrada en servicio ni la vigencia como acreditadas sin resolución. | S19: https://www.madrid.es/portales/munimadrid/es/Inicio/El-Ayuntamiento/Publicaciones/Listado-de-Publicaciones/Contratos-de-Recogida-de-Residuos/?vgnextchannel=f1aebadb6b997010VgnVCM100000dc0ca8c0RCRD&vgnextfmt=default&vgnextoid=429f71adf3d56910VgnVCM2000001f4a900aRCRD https://contratos.gobierto.es/licitaciones/5108890 https://licitalens.com/empresa/A08602815 https://www.madrid.es/portales/munimadrid/es/Inicio/Medio-ambiente/Recogida-de-residuos/Actividades-y-eventos/Contrato-de-servicio-de-actividades-de-sensibilizacion/?vgnextchannel=d04bbb21278fe410VgnVCM1000000b205a0aRCRD&vgnextfmt=default&vgnextoid=1d1f49ec5caef910VgnVCM200000f921e388RCRD | T19: REL-0018 | U19: 300/2026/00024|Sin lotes | V19: =IF(AND(SUM(IF('Consulta de contratos'!$K$1="",0,1),IF('Consulta de contratos'!$K$2="",0,1),IF('Consulta de contratos'!$K$3="",0,1),IF('Consulta de contratos'!$K$4="",0,1),IF('Consulta de contratos'!$K$5="",0,1),IF('Consulta de contratos'!$K$6="",0,1))>0,OR('Consulta de contratos'!$K$1="",A19='Consulta de contratos'!$K$1),OR('Consulta de contratos'!$K$2="",I19='Consulta de contratos'!$K$2),OR('Consulta de contratos'!$K$3="",C19='Consulta de contratos'!$K$3),OR('Consulta de contratos'!$K$4="",D19='Consulta de contratos'!$K$4),OR('Consulta de contratos'!$K$5="",E19='Consulta de contratos'!$K$5),OR('Consulta de contratos'!$K$6="",IFERROR(ISNUMBER(SEARCH("|"&'Consulta de contratos'!$K$6&"|",AF19)),FALSE))),1,0) -> 0 | W19: =IF(V19=1,SUM($V$2:V19),0) -> 0 | X19: ADJUDICACIÓN PUBLICADA EN DATOS PLACSP · FORMALIZACIÓN POR CONTRASTAR | Y19: CLECE | Z19: Grupo de empresa contrastado en fuente corporativa: https://clece.es/es/listado-clece-filiales/ | AA19: 16/10/2026 | AF19: |CLECE|
A20: Salamanca | B20: Residuos | C20: Área de Gobierno de Urbanismo, Medio Ambiente y Movilidad | D20: Dirección General de Servicios de Limpieza y Residuos | E20: Subdirección General de Recogida de Residuos | F20: Contenerización, recogida y transporte de residuos | G20: 131/2021/06296 | H20: 2 | I20: UTE Recogida Madrid VAO | J20: Recogida y transporte habitual | K20: Zona territorial del lote | L20: 44866 | M20: 47057 | N20: Víctor Manuel Sarabia Herrero | O20: No acreditado | P20: 010 / 914 800 010 (atencion municipal, no gestor directo) | R20: Concesión vigente; adjudicataria y fin 31/10/2028 contrastados en registro de concesiones municipal (15/10/2026). | FECHAS REVISADAS: Inicio 01/11/2022 acreditado por formalización de los cuatro lotes. | CONTROL DOCUMENTAL 21/10/2026: Adjudicación y fin publicados. Los cuatro lotes se pueden contrastar en el registro municipal de concesiones. Fin publicado: 31/10/2028. No generalizar ámbito de cada lote. [Base de evidencia: Portal municipal / resolución o resultado oficial consultado] | CONTRASTE ADICIONAL 21/10/2026: FUENTE MUNICIPAL: la concesión registra adjudicación diferenciada en los 4 lotes (FCC, UTE VAO, UTE Sur, CONTENUR) y fin contractual 31/10/2028. | S20: https://contratacion.madrid.es/concesiones/ https://contrataciondelestado.es/FileSystem/servlet/GetDocumentByIdServlet?DocumentIdParam=I52CDqtLbsdgHyWk6Tjc%2BH2t2QGKU1Ro9lcaZmb7V5J4T4CLRYtO18fD2fcADXQg90aL83OqQbUADSXvNu02Vt6kOzxNccJdTRf8umMgorI%3D&cifrado=QUC1GjXXSiLkydRHJBmbpw%3D%3D | T20: REL-0019 | U20: 131/2021/06296|2 | V20: =IF(AND(SUM(IF('Consulta de contratos'!$K$1="",0,1),IF('Consulta de contratos'!$K$2="",0,1),IF('Consulta de contratos'!$K$3="",0,1),IF('Consulta de contratos'!$K$4="",0,1),IF('Consulta de contratos'!$K$5="",0,1),IF('Consulta de contratos'!$K$6="",0,1))>0,OR('Consulta de contratos'!$K$1="",A20='Consulta de contratos'!$K$1),OR('Consulta de contratos'!$K$2="",I20='Consulta de contratos'!$K$2),OR('Consulta de contratos'!$K$3="",C20='Consulta de contratos'!$K$3),OR('Consulta de contratos'!$K$4="",D20='Consulta de contratos'!$K$4),OR('Consulta de contratos'!$K$5="",E20='Consulta de contratos'!$K$5),OR('Consulta de contratos'!$K$6="",IFERROR(ISNUMBER(SEARCH("|"&'Consulta de contratos'!$K$6&"|",AF20)),FALSE))),1,0) -> 0 | W20: =IF(V20=1,SUM($V$2:V20),0) -> 0 | X20: FIN REGISTRADO POSTERIOR · EJECUCIÓN A CONFIRMAR | Y20: ACCIONA | VALORIZA | OHL / INGESAN | Z20: UTE: vínculo comercial; no implica propiedad | AA20: 16/10/2026 | AF20: |ACCIONA|VALORIZA|OHL / INGESAN|
A21: Salamanca | B21: Residuos | C21: Área de Gobierno de Urbanismo, Medio Ambiente y Movilidad | D21: Dirección General de Servicios de Limpieza y Residuos | E21: Subdirección General de Recogida de Residuos | F21: Contenerización, recogida y transporte de residuos | G21: 131/2021/06296 | H21: 4 | I21: CONTENUR SL | J21: Suministro, mantenimiento y limpieza de contenedores | K21: Toda la ciudad | L21: 44866 | M21: 47057 | N21: Víctor Manuel Sarabia Herrero | O21: No acreditado | P21: 010 / 914 800 010 (atencion municipal, no gestor directo) | Q21: No es vaciado ni recogida habitual | R21: Concesión vigente; adjudicataria y fin 31/10/2028 contrastados en registro de concesiones municipal (15/10/2026). | FECHAS REVISADAS: Inicio 01/11/2022 acreditado por formalización de los cuatro lotes. | CONTROL DOCUMENTAL 21/10/2026: Adjudicación y fin publicados. Los cuatro lotes se pueden contrastar en el registro municipal de concesiones. Fin publicado: 31/10/2028. No generalizar ámbito de cada lote. [Base de evidencia: Portal municipal / resolución o resultado oficial consultado] | CONTRASTE ADICIONAL 21/10/2026: FUENTE MUNICIPAL: la concesión registra adjudicación diferenciada en los 4 lotes (FCC, UTE VAO, UTE Sur, CONTENUR) y fin contractual 31/10/2028. | S21: https://contratacion.madrid.es/concesiones/ https://contrataciondelestado.es/FileSystem/servlet/GetDocumentByIdServlet?DocumentIdParam=I52CDqtLbsdgHyWk6Tjc%2BH2t2QGKU1Ro9lcaZmb7V5J4T4CLRYtO18fD2fcADXQg90aL83OqQbUADSXvNu02Vt6kOzxNccJdTRf8umMgorI%3D&cifrado=QUC1GjXXSiLkydRHJBmbpw%3D%3D | T21: REL-0020 | U21: 131/2021/06296|4 | V21: =IF(AND(SUM(IF('Consulta de contratos'!$K$1="",0,1),IF('Consulta de contratos'!$K$2="",0,1),IF('Consulta de contratos'!$K$3="",0,1),IF('Consulta de contratos'!$K$4="",0,1),IF('Consulta de contratos'!$K$5="",0,1),IF('Consulta de contratos'!$K$6="",0,1))>0,OR('Consulta de contratos'!$K$1="",A21='Consulta de contratos'!$K$1),OR('Consulta de contratos'!$K$2="",I21='Consulta de contratos'!$K$2),OR('Consulta de contratos'!$K$3="",C21='Consulta de contratos'!$K$3),OR('Consulta de contratos'!$K$4="",D21='Consulta de contratos'!$K$4),OR('Consulta de contratos'!$K$5="",E21='Consulta de contratos'!$K$5),OR('Consulta de contratos'!$K$6="",IFERROR(ISNUMBER(SEARCH("|"&'Consulta de contratos'!$K$6&"|",AF21)),FALSE))),1,0) -> 0 | W21: =IF(V21=1,SUM($V$2:V21),0) -> 0 | X21: FIN REGISTRADO POSTERIOR · EJECUCIÓN A CONFIRMAR | Y21: CONTENUR SL | Z21: Agrupación de consulta por nombre de adjudicataria; no consta matriz contrastada. | AA21: 16/10/2026 | AF21: |CONTENUR SL|
A22: Salamanca | B22: Residuos | C22: Área de Gobierno de Urbanismo, Medio Ambiente y Movilidad | D22: Dirección General de Servicios de Limpieza y Residuos | E22: Subdirección General de Recogida de Residuos | F22: Contenerización, recogida y transporte de residuos | G22: 131/2021/06296 | H22: 3 | I22: UTE 2022 Recogida Madrid Sur | J22: Recogida de pilas y baterias usadas | K22: Toda la ciudad | L22: 44866 | M22: 47057 | N22: Víctor Manuel Sarabia Herrero | O22: No acreditado | P22: 010 / 914 800 010 (atencion municipal, no gestor directo) | Q22: Tarea especial del lote 3 fuera de su zona habitual | R22: Concesión vigente; adjudicataria y fin 31/10/2028 contrastados en registro de concesiones municipal (15/10/2026). | FECHAS REVISADAS: Inicio 01/11/2022 acreditado por formalización de los cuatro lotes. | CONTROL DOCUMENTAL 21/10/2026: Adjudicación y fin publicados. Los cuatro lotes se pueden contrastar en el registro municipal de concesiones. Fin publicado: 31/10/2028. No generalizar ámbito de cada lote. [Base de evidencia: Portal municipal / resolución o resultado oficial consultado] | CONTRASTE ADICIONAL 21/10/2026: FUENTE MUNICIPAL: la concesión registra adjudicación diferenciada en los 4 lotes (FCC, UTE VAO, UTE Sur, CONTENUR) y fin contractual 31/10/2028. | S22: https://contratacion.madrid.es/concesiones/ https://contrataciondelestado.es/FileSystem/servlet/GetDocumentByIdServlet?DocumentIdParam=I52CDqtLbsdgHyWk6Tjc%2BH2t2QGKU1Ro9lcaZmb7V5J4T4CLRYtO18fD2fcADXQg90aL83OqQbUADSXvNu02Vt6kOzxNccJdTRf8umMgorI%3D&cifrado=QUC1GjXXSiLkydRHJBmbpw%3D%3D | T22: REL-0021 | U22: 131/2021/06296|3 | V22: =IF(AND(SUM(IF('Consulta de contratos'!$K$1="",0,1),IF('Consulta de contratos'!$K$2="",0,1),IF('Consulta de contratos'!$K$3="",0,1),IF('Consulta de contratos'!$K$4="",0,1),IF('Consulta de contratos'!$K$5="",0,1),IF('Consulta de contratos'!$K$6="",0,1))>0,OR('Consulta de contratos'!$K$1="",A22='Consulta de contratos'!$K$1),OR('Consulta de contratos'!$K$2="",I22='Consulta de contratos'!$K$2),OR('Consulta de contratos'!$K$3="",C22='Consulta de contratos'!$K$3),OR('Consulta de contratos'!$K$4="",D22='Consulta de contratos'!$K$4),OR('Consulta de contratos'!$K$5="",E22='Consulta de contratos'!$K$5),OR('Consulta de contratos'!$K$6="",IFERROR(ISNUMBER(SEARCH("|"&'Consulta de contratos'!$K$6&"|",AF22)),FALSE))),1,0) -> 0 | W22: =IF(V22=1,SUM($V$2:V22),0) -> 0 | X22: FIN REGISTRADO POSTERIOR · EJECUCIÓN A CONFIRMAR | Y22: PREZERO | URBASER | Z22: UTE: vínculo comercial; no implica propiedad | AA22: 16/10/2026 | AF22: |PREZERO|URBASER|
A23: Salamanca | B23: Residuos | C23: Área de Gobierno de Urbanismo, Medio Ambiente y Movilidad | D23: Dirección General de Servicios de Limpieza y Residuos | E23: Subdirección General de Recogida de Residuos | F23: Asistencia técnica para el mantenimiento, ampliación y mejora continua del sistema de gestión de la información de limpieza urbana, recogida de residuos y equipamientos urbanos | G23: 300/2025/00411 | H23: Sin lotes | I23: APORTA PLATAFORMA COOPERATIVA SCCL | J23: Mantenimiento y mejora del sistema de informacion | K23: Ambito municipal; no contrato propio del distrito | M23: 46850 | N23: Víctor Manuel Sarabia Herrero | O23: No acreditado | P23: 010 / 914 800 010 (atencion municipal, no gestor directo) | R23: Adjudicado 27/01/2026 y formalizado 08/04/2026. Fin publicado 07/04/2028 (posible prórroga 12 meses). Inicio de prestación no acreditado. | FECHAS SIN ACREDITAR: Formalización 08/04/2026 y fin en agregador 07/04/2028; no consta fecha independiente de inicio de prestación. La formalización no se convierte en inicio automático. | FUENTES REVISADAS 21/10/2026: Ayuntamiento publica objeto y pliegos; registro TED del contrato identifica formalización el 08/04/2026 y adjudicataria Aporta. No equivale a fecha de inicio operativo. | CONTROL DOCUMENTAL 21/10/2026: Adjudicataria identificada. APORTA PLATAFORMA COOPERATIVA figura en la base y en fichas de licitación; comprobar firma e hitos en el expediente. [Base de evidencia: Datos confrontados con referencias aportadas; no hay resolución individual corroborada] | CONTRASTE ADICIONAL 21/10/2026: ADJUDICACIÓN: APORTA PLATAFORMA COOPERATIVA SCCL, resolución de 27/01/2026, contrastada con publicación de licitación. | S23: https://contratos.gobierto.es/adjudicatarios/aporta-plataforma-cooperativa-sccl?locale=es https://www.madrid.es/portales/munimadrid/es/Inicio/Medio-ambiente/Limpieza-urbana/Contrato-de-servicio-de-asistencia-tecnica/?vgnextchannel=ddd2a694fde40910VgnVCM2000001f4a900aRCRD&vgnextfmt=default&vgnextoid=7c07475398a4e910VgnVCM200000f921e388RCRD https://contratos.gobierto.es/licitaciones/4668721?locale=es | T23: REL-0022 | U23: 300/2025/00411|Sin lotes | V23: =IF(AND(SUM(IF('Consulta de contratos'!$K$1="",0,1),IF('Consulta de contratos'!$K$2="",0,1),IF('Consulta de contratos'!$K$3="",0,1),IF('Consulta de contratos'!$K$4="",0,1),IF('Consulta de contratos'!$K$5="",0,1),IF('Consulta de contratos'!$K$6="",0,1))>0,OR('Consulta de contratos'!$K$1="",A23='Consulta de contratos'!$K$1),OR('Consulta de contratos'!$K$2="",I23='Consulta de contratos'!$K$2),OR('Consulta de contratos'!$K$3="",C23='Consulta de contratos'!$K$3),OR('Consulta de contratos'!$K$4="",D23='Consulta de contratos'!$K$4),OR('Consulta de contratos'!$K$5="",E23='Consulta de contratos'!$K$5),OR('Consulta de contratos'!$K$6="",IFERROR(ISNUMBER(SEARCH("|"&'Consulta de contratos'!$K$6&"|",AF23)),FALSE))),1,0) -> 0 | W23: =IF(V23=1,SUM($V$2:V23),0) -> 0 | X23: FIN REGISTRADO POSTERIOR · EJECUCIÓN A CONFIRMAR | Y23: APORTA PLATAFORMA COOPERATIVA SCCL | Z23: Agrupación de consulta por nombre de adjudicataria; no consta matriz contrastada. | AA23: 16/10/2026 | AF23: |APORTA PLATAFORMA COOPERATIVA SCCL|
A24: Salamanca | B24: Residuos | C24: Área de Gobierno de Urbanismo, Medio Ambiente y Movilidad | D24: Dirección General de Servicios de Limpieza y Residuos | E24: Subdirección General de Recogida de Residuos | F24: Gestión del servicio de explotación de puntos limpios, centros de reutilización de residuos y saneamiento de viviendas | G24: 300/2023/00593 | H24: Sin lotes | I24: PREZERO ESPAÑA SAU | J24: Gestión de puntos limpios y centros de reutilización; saneamientos por requerimiento. | K24: Ambito municipal; ubicaciones concretas no incluidas | L24: 45622 | M24: 47447 | N24: Víctor Manuel Sarabia Herrero | O24: No acreditado | P24: 010 / 914 800 010 (atencion municipal, no gestor directo) | Q24: Saneamiento no es limpieza domestica ordinaria | R24: Vigente según Ayuntamiento; adjudicataria PREZERO acreditada (24/10/2024). Inicio contractual y fecha fin exacta sin acreditar. | FECHAS REVISADAS: Vigencia: 26/11/2024–25/11/2029. Inicio oficial; fin ordinario calculado por cinco años contractuales sin prórroga. | CONTROL DOCUMENTAL 21/10/2026: Adjudicataria identificada. PREZERO ESPAÑA figura adjudicataria de puntos limpios. El contrato es municipal; no son 21 concesiones independientes. [Base de evidencia: Datos confrontados con referencias aportadas; no hay resolución individual corroborada] | CONTRASTE ADICIONAL 21/10/2026: ADJUDICACIÓN: PREZERO ESPAÑA SA, 24/10/2024. El Ayuntamiento dispone de ficha oficial del contrato; compruébese formalización para fechas exactas. | S24: https://contratos.gobierto.es/licitaciones/4336157 https://contrataciondelestado.es/FileSystem/servlet/GetDocumentByIdServlet?DocumentIdParam=DX1ZAvwzaIUStPoibgXBVeTGIJOgffe86rdC19dt4dT5lTaSGg5Vq9cT4fT6Jv75jYAipcFv6g1zHenSv4lINo4IQyA7QON0MW%2BNRBCDa6cZyAJWGsSt0OzTSTyw9JAs&cifrado=QUC1GjXXSiLkydRHJBmbpw%3D%3D https://www.madrid.es/UnidadesDescentralizadas/LimpiezaUrbanaYResiduos/CONTRATOS_DG/CONTRATO-RES_PuntosLimpios/DocumentoPliegos_ContratoPuntosLimpios.pdf https://www.madrid.es/portales/munimadrid/es/Inicio/Medio-ambiente/Recogida-de-residuos/Contrato-de-servicios-de-explotacion-de-puntos-limpios-centros-de-reutilizacion-de-residuos-y-saneamiento-de-viviendas-en-la-ciudad-de-Madrid/?vgnextchannel=f81379ed268fe410VgnVCM1000000b205a0aRCRD&vgnextfmt=default&vgnextoid=8177150aabc46710VgnVCM2000001f4a900aRCRD | T24: REL-0023 | U24: 300/2023/00593|Sin lotes | V24: =IF(AND(SUM(IF('Consulta de contratos'!$K$1="",0,1),IF('Consulta de contratos'!$K$2="",0,1),IF('Consulta de contratos'!$K$3="",0,1),IF('Consulta de contratos'!$K$4="",0,1),IF('Consulta de contratos'!$K$5="",0,1),IF('Consulta de contratos'!$K$6="",0,1))>0,OR('Consulta de contratos'!$K$1="",A24='Consulta de contratos'!$K$1),OR('Consulta de contratos'!$K$2="",I24='Consulta de contratos'!$K$2),OR('Consulta de contratos'!$K$3="",C24='Consulta de contratos'!$K$3),OR('Consulta de contratos'!$K$4="",D24='Consulta de contratos'!$K$4),OR('Consulta de contratos'!$K$5="",E24='Consulta de contratos'!$K$5),OR('Consulta de contratos'!$K$6="",IFERROR(ISNUMBER(SEARCH("|"&'Consulta de contratos'!$K$6&"|",AF24)),FALSE))),1,0) -> 0 | W24: =IF(V24=1,SUM($V$2:V24),0) -> 0 | X24: FIN REGISTRADO POSTERIOR · EJECUCIÓN A CONFIRMAR | Y24: PREZERO | Z24: Grupo/familia pendiente de confirmar legalmente | AA24: 16/10/2026 | AF24: |PREZERO|
A25: Salamanca | B25: Residuos | C25: Área de Gobierno de Urbanismo, Medio Ambiente y Movilidad | D25: Dirección General de Servicios de Limpieza y Residuos | E25: Subdirección General de Recogida de Residuos | F25: Programa de actividades de sensibilización sobre separación de residuos y limpieza del espacio público | G25: 300/2026/00024 | H25: Sin lotes | I25: TALHER, S.A. | J25: Actividades educativas y de sensibilizacion | K25: Ambito municipal; no acredita actividad en cada distrito | N25: Víctor Manuel Sarabia Herrero | O25: No acreditado | P25: 010 / 914 800 010 (atencion municipal, no gestor directo) | Q25: Adjudicación publicada en datos de PLACSP; formalización e inicio efectivos sin contrastar. | ATENCIÓN · CONTRASTE 23/10/2026: el portal municipal incluye este expediente entre los contratos en vigor, mientras un agregador lo presenta como «Desistida». La resolución de adjudicación, la formalización y el inicio efectivo requieren comprobación directa. | R25: ADJUDICACIÓN 30/09/2026 A TALHER, S.A. (1.432.107 € sin IVA) recogida en LicitaLens a partir de PLACSP. Pendiente de verificar resolución y fecha de formalización en documento oficial; no certificar inicio efectivo. | CONTROL DOCUMENTAL 21/10/2026: Adjudicación localizada. Adjudicación a TALHER encontrada en plataformas que reproducen PLACSP; la resolución y la fecha de ejecución requieren lectura directa. [Base de evidencia: Ficha individual de publicación / agregador contrastada] | CONTRASTE DE FUENTES 23/10/2026: ficha municipal lo relaciona entre contratos en vigor; Gobierto muestra estado «Desistida», pese a reflejar datos de adjudicación del 30/09/2026. No tratar la formalización, la entrada en servicio ni la vigencia como acreditadas sin resolución. | S25: https://www.madrid.es/portales/munimadrid/es/Inicio/El-Ayuntamiento/Publicaciones/Listado-de-Publicaciones/Contratos-de-Recogida-de-Residuos/?vgnextchannel=f1aebadb6b997010VgnVCM100000dc0ca8c0RCRD&vgnextfmt=default&vgnextoid=429f71adf3d56910VgnVCM2000001f4a900aRCRD https://contratos.gobierto.es/licitaciones/5108890 https://licitalens.com/empresa/A08602815 https://www.madrid.es/portales/munimadrid/es/Inicio/Medio-ambiente/Recogida-de-residuos/Actividades-y-eventos/Contrato-de-servicio-de-actividades-de-sensibilizacion/?vgnextchannel=d04bbb21278fe410VgnVCM1000000b205a0aRCRD&vgnextfmt=default&vgnextoid=1d1f49ec5caef910VgnVCM200000f921e388RCRD | T25: REL-0024 | U25: 300/2026/00024|Sin lotes | V25: =IF(AND(SUM(IF('Consulta de contratos'!$K$1="",0,1),IF('Consulta de contratos'!$K$2="",0,1),IF('Consulta de contratos'!$K$3="",0,1),IF('Consulta de contratos'!$K$4="",0,1),IF('Consulta de contratos'!$K$5="",0,1),IF('Consulta de contratos'!$K$6="",0,1))>0,OR('Consulta de contratos'!$K$1="",A25='Consulta de contratos'!$K$1),OR('Consulta de contratos'!$K$2="",I25='Consulta de contratos'!$K$2),OR('Consulta de contratos'!$K$3="",C25='Consulta de contratos'!$K$3),OR('Consulta de contratos'!$K$4="",D25='Consulta de contratos'!$K$4),OR('Consulta de contratos'!$K$5="",E25='Consulta de contratos'!$K$5),OR('Consulta de contratos'!$K$6="",IFERROR(ISNUMBER(SEARCH("|"&'Consulta de contratos'!$K$6&"|",AF25)),FALSE))),1,0) -> 0 | W25: =IF(V25=1,SUM($V$2:V25),0) -> 0 | X25: ADJUDICACIÓN PUBLICADA EN DATOS PLACSP · FORMALIZACIÓN POR CONTRASTAR | Y25: CLECE | Z25: Grupo de empresa contrastado en fuente corporativa: https://clece.es/es/listado-clece-filiales/ | AA25: 16/10/2026 | AF25: |CLECE|
A26: Chamartín | B26: Residuos | C26: Área de Gobierno de Urbanismo, Medio Ambiente y Movilidad | D26: Dirección General de Servicios de Limpieza y Residuos | E26: Subdirección General de Recogida de Residuos | F26: Contenerización, recogida y transporte de residuos | G26: 131/2021/06296 | H26: 2 | I26: UTE Recogida Madrid VAO | J26: Recogida y transporte habitual | K26: Zona territorial del lote | L26: 44866 | M26: 47057 | N26: Víctor Manuel Sarabia Herrero | O26: No acreditado | P26: 010 / 914 800 010 (atencion municipal, no gestor directo) | R26: Concesión vigente; adjudicataria y fin 31/10/2028 contrastados en registro de concesiones municipal (15/10/2026). | FECHAS REVISADAS: Inicio 01/11/2022 acreditado por formalización de los cuatro lotes. | CONTROL DOCUMENTAL 21/10/2026: Adjudicación y fin publicados. Los cuatro lotes se pueden contrastar en el registro municipal de concesiones. Fin publicado: 31/10/2028. No generalizar ámbito de cada lote. [Base de evidencia: Portal municipal / resolución o resultado oficial consultado] | CONTRASTE ADICIONAL 21/10/2026: FUENTE MUNICIPAL: la concesión registra adjudicación diferenciada en los 4 lotes (FCC, UTE VAO, UTE Sur, CONTENUR) y fin contractual 31/10/2028. | S26: https://contratacion.madrid.es/concesiones/ https://contrataciondelestado.es/FileSystem/servlet/GetDocumentByIdServlet?DocumentIdParam=I52CDqtLbsdgHyWk6Tjc%2BH2t2QGKU1Ro9lcaZmb7V5J4T4CLRYtO18fD2fcADXQg90aL83OqQbUADSXvNu02Vt6kOzxNccJdTRf8umMgorI%3D&cifrado=QUC1GjXXSiLkydRHJBmbpw%3D%3D | T26: REL-0025 | U26: 131/2021/06296|2 | V26: =IF(AND(SUM(IF('Consulta de contratos'!$K$1="",0,1),IF('Consulta de contratos'!$K$2="",0,1),IF('Consulta de contratos'!$K$3="",0,1),IF('Consulta de contratos'!$K$4="",0,1),IF('Consulta de contratos'!$K$5="",0,1),IF('Consulta de contratos'!$K$6="",0,1))>0,OR('Consulta de contratos'!$K$1="",A26='Consulta de contratos'!$K$1),OR('Consulta de contratos'!$K$2="",I26='Consulta de contratos'!$K$2),OR('Consulta de contratos'!$K$3="",C26='Consulta de contratos'!$K$3),OR('Consulta de contratos'!$K$4="",D26='Consulta de contratos'!$K$4),OR('Consulta de contratos'!$K$5="",E26='Consulta de contratos'!$K$5),OR('Consulta de contratos'!$K$6="",IFERROR(ISNUMBER(SEARCH("|"&'Consulta de contratos'!$K$6&"|",AF26)),FALSE))),1,0) -> 0 | W26: =IF(V26=1,SUM($V$2:V26),0) -> 0 | X26: FIN REGISTRADO POSTERIOR · EJECUCIÓN A CONFIRMAR | Y26: ACCIONA | VALORIZA | OHL / INGESAN | Z26: UTE: vínculo comercial; no implica propiedad | AA26: 16/10/2026 | AF26: |ACCIONA|VALORIZA|OHL / INGESAN|
A27: Chamartín | B27: Residuos | C27: Área de Gobierno de Urbanismo, Medio Ambiente y Movilidad | D27: Dirección General de Servicios de Limpieza y Residuos | E27: Subdirección General de Recogida de Residuos | F27: Contenerización, recogida y transporte de residuos | G27: 131/2021/06296 | H27: 4 | I27: CONTENUR SL | J27: Suministro, mantenimiento y limpieza de contenedores | K27: Toda la ciudad | L27: 44866 | M27: 47057 | N27: Víctor Manuel Sarabia Herrero | O27: No acreditado | P27: 010 / 914 800 010 (atencion municipal, no gestor directo) | Q27: No es vaciado ni recogida habitual | R27: Concesión vigente; adjudicataria y fin 31/10/2028 contrastados en registro de concesiones municipal (15/10/2026). | FECHAS REVISADAS: Inicio 01/11/2022 acreditado por formalización de los cuatro lotes. | CONTROL DOCUMENTAL 21/10/2026: Adjudicación y fin publicados. Los cuatro lotes se pueden contrastar en el registro municipal de concesiones. Fin publicado: 31/10/2028. No generalizar ámbito de cada lote. [Base de evidencia: Portal municipal / resolución o resultado oficial consultado] | CONTRASTE ADICIONAL 21/10/2026: FUENTE MUNICIPAL: la concesión registra adjudicación diferenciada en los 4 lotes (FCC, UTE VAO, UTE Sur, CONTENUR) y fin contractual 31/10/2028. | S27: https://contratacion.madrid.es/concesiones/ https://contrataciondelestado.es/FileSystem/servlet/GetDocumentByIdServlet?DocumentIdParam=I52CDqtLbsdgHyWk6Tjc%2BH2t2QGKU1Ro9lcaZmb7V5J4T4CLRYtO18fD2fcADXQg90aL83OqQbUADSXvNu02Vt6kOzxNccJdTRf8umMgorI%3D&cifrado=QUC1GjXXSiLkydRHJBmbpw%3D%3D | T27: REL-0026 | U27: 131/2021/06296|4 | V27: =IF(AND(SUM(IF('Consulta de contratos'!$K$1="",0,1),IF('Consulta de contratos'!$K$2="",0,1),IF('Consulta de contratos'!$K$3="",0,1),IF('Consulta de contratos'!$K$4="",0,1),IF('Consulta de contratos'!$K$5="",0,1),IF('Consulta de contratos'!$K$6="",0,1))>0,OR('Consulta de contratos'!$K$1="",A27='Consulta de contratos'!$K$1),OR('Consulta de contratos'!$K$2="",I27='Consulta de contratos'!$K$2),OR('Consulta de contratos'!$K$3="",C27='Consulta de contratos'!$K$3),OR('Consulta de contratos'!$K$4="",D27='Consulta de contratos'!$K$4),OR('Consulta de contratos'!$K$5="",E27='Consulta de contratos'!$K$5),OR('Consulta de contratos'!$K$6="",IFERROR(ISNUMBER(SEARCH("|"&'Consulta de contratos'!$K$6&"|",AF27)),FALSE))),1,0) -> 0 | W27: =IF(V27=1,SUM($V$2:V27),0) -> 0 | X27: FIN REGISTRADO POSTERIOR · EJECUCIÓN A CONFIRMAR | Y27: CONTENUR SL | Z27: Agrupación de consulta por nombre de adjudicataria; no consta matriz contrastada. | AA27: 16/10/2026 | AF27: |CONTENUR SL|
A28: Chamartín | B28: Residuos | C28: Área de Gobierno de Urbanismo, Medio Ambiente y Movilidad | D28: Dirección General de Servicios de Limpieza y Residuos | E28: Subdirección General de Recogida de Residuos | F28: Contenerización, recogida y transporte de residuos | G28: 131/2021/06296 | H28: 3 | I28: UTE 2022 Recogida Madrid Sur | J28: Recogida de pilas y baterias usadas | K28: Toda la ciudad | L28: 44866 | M28: 47057 | N28: Víctor Manuel Sarabia Herrero | O28: No acreditado | P28: 010 / 914 800 010 (atencion municipal, no gestor directo) | Q28: Tarea especial del lote 3 fuera de su zona habitual | R28: Concesión vigente; adjudicataria y fin 31/10/2028 contrastados en registro de concesiones municipal (15/10/2026). | FECHAS REVISADAS: Inicio 01/11/2022 acreditado por formalización de los cuatro lotes. | CONTROL DOCUMENTAL 21/10/2026: Adjudicación y fin publicados. Los cuatro lotes se pueden contrastar en el registro municipal de concesiones. Fin publicado: 31/10/2028. No generalizar ámbito de cada lote. [Base de evidencia: Portal municipal / resolución o resultado oficial consultado] | CONTRASTE ADICIONAL 21/10/2026: FUENTE MUNICIPAL: la concesión registra adjudicación diferenciada en los 4 lotes (FCC, UTE VAO, UTE Sur, CONTENUR) y fin contractual 31/10/2028. | S28: https://contratacion.madrid.es/concesiones/ https://contrataciondelestado.es/FileSystem/servlet/GetDocumentByIdServlet?DocumentIdParam=I52CDqtLbsdgHyWk6Tjc%2BH2t2QGKU1Ro9lcaZmb7V5J4T4CLRYtO18fD2fcADXQg90aL83OqQbUADSXvNu02Vt6kOzxNccJdTRf8umMgorI%3D&cifrado=QUC1GjXXSiLkydRHJBmbpw%3D%3D | T28: REL-0027 | U28: 131/2021/06296|3 | V28: =IF(AND(SUM(IF('Consulta de contratos'!$K$1="",0,1),IF('Consulta de contratos'!$K$2="",0,1),IF('Consulta de contratos'!$K$3="",0,1),IF('Consulta de contratos'!$K$4="",0,1),IF('Consulta de contratos'!$K$5="",0,1),IF('Consulta de contratos'!$K$6="",0,1))>0,OR('Consulta de contratos'!$K$1="",A28='Consulta de contratos'!$K$1),OR('Consulta de contratos'!$K$2="",I28='Consulta de contratos'!$K$2),OR('Consulta de contratos'!$K$3="",C28='Consulta de contratos'!$K$3),OR('Consulta de contratos'!$K$4="",D28='Consulta de contratos'!$K$4),OR('Consulta de contratos'!$K$5="",E28='Consulta de contratos'!$K$5),OR('Consulta de contratos'!$K$6="",IFERROR(ISNUMBER(SEARCH("|"&'Consulta de contratos'!$K$6&"|",AF28)),FALSE))),1,0) -> 0 | W28: =IF(V28=1,SUM($V$2:V28),0) -> 0 | X28: FIN REGISTRADO POSTERIOR · EJECUCIÓN A CONFIRMAR | Y28: PREZERO | URBASER | Z28: UTE: vínculo comercial; no implica propiedad | AA28: 16/10/2026 | AF28: |PREZERO|URBASER|
A29: Chamartín | B29: Residuos | C29: Área de Gobierno de Urbanismo, Medio Ambiente y Movilidad | D29: Dirección General de Servicios de Limpieza y Residuos | E29: Subdirección General de Recogida de Residuos | F29: Asistencia técnica para el mantenimiento, ampliación y mejora continua del sistema de gestión de la información de limpieza urbana, recogida de residuos y equipamientos urbanos | G29: 300/2025/00411 | H29: Sin lotes | I29: APORTA PLATAFORMA COOPERATIVA SCCL | J29: Mantenimiento y mejora del sistema de informacion | K29: Ambito municipal; no contrato propio del distrito | M29: 46850 | N29: Víctor Manuel Sarabia Herrero | O29: No acreditado | P29: 010 / 914 800 010 (atencion municipal, no gestor directo) | R29: Adjudicado 27/01/2026 y formalizado 08/04/2026. Fin publicado 07/04/2028 (posible prórroga 12 meses). Inicio de prestación no acreditado. | FECHAS SIN ACREDITAR: Formalización 08/04/2026 y fin en agregador 07/04/2028; no consta fecha independiente de inicio de prestación. La formalización no se convierte en inicio automático. | FUENTES REVISADAS 21/10/2026: Ayuntamiento publica objeto y pliegos; registro TED del contrato identifica formalización el 08/04/2026 y adjudicataria Aporta. No equivale a fecha de inicio operativo. | CONTROL DOCUMENTAL 21/10/2026: Adjudicataria identificada. APORTA PLATAFORMA COOPERATIVA figura en la base y en fichas de licitación; comprobar firma e hitos en el expediente. [Base de evidencia: Datos confrontados con referencias aportadas; no hay resolución individual corroborada] | CONTRASTE ADICIONAL 21/10/2026: ADJUDICACIÓN: APORTA PLATAFORMA COOPERATIVA SCCL, resolución de 27/01/2026, contrastada con publicación de licitación. | S29: https://contratos.gobierto.es/adjudicatarios/aporta-plataforma-cooperativa-sccl?locale=es https://www.madrid.es/portales/munimadrid/es/Inicio/Medio-ambiente/Limpieza-urbana/Contrato-de-servicio-de-asistencia-tecnica/?vgnextchannel=ddd2a694fde40910VgnVCM2000001f4a900aRCRD&vgnextfmt=default&vgnextoid=7c07475398a4e910VgnVCM200000f921e388RCRD https://contratos.gobierto.es/licitaciones/4668721?locale=es | T29: REL-0028 | U29: 300/2025/00411|Sin lotes | V29: =IF(AND(SUM(IF('Consulta de contratos'!$K$1="",0,1),IF('Consulta de contratos'!$K$2="",0,1),IF('Consulta de contratos'!$K$3="",0,1),IF('Consulta de contratos'!$K$4="",0,1),IF('Consulta de contratos'!$K$5="",0,1),IF('Consulta de contratos'!$K$6="",0,1))>0,OR('Consulta de contratos'!$K$1="",A29='Consulta de contratos'!$K$1),OR('Consulta de contratos'!$K$2="",I29='Consulta de contratos'!$K$2),OR('Consulta de contratos'!$K$3="",C29='Consulta de contratos'!$K$3),OR('Consulta de contratos'!$K$4="",D29='Consulta de contratos'!$K$4),OR('Consulta de contratos'!$K$5="",E29='Consulta de contratos'!$K$5),OR('Consulta de contratos'!$K$6="",IFERROR(ISNUMBER(SEARCH("|"&'Consulta de contratos'!$K$6&"|",AF29)),FALSE))),1,0) -> 0 | W29: =IF(V29=1,SUM($V$2:V29),0) -> 0 | X29: FIN REGISTRADO POSTERIOR · EJECUCIÓN A CONFIRMAR | Y29: APORTA PLATAFORMA COOPERATIVA SCCL | Z29: Agrupación de consulta por nombre de adjudicataria; no consta matriz contrastada. | AA29: 16/10/2026 | AF29: |APORTA PLATAFORMA COOPERATIVA SCCL|
A30: Chamartín | B30: Residuos | C30: Área de Gobierno de Urbanismo, Medio Ambiente y Movilidad | D30: Dirección General de Servicios de Limpieza y Residuos | E30: Subdirección General de Recogida de Residuos | F30: Gestión del servicio de explotación de puntos limpios, centros de reutilización de residuos y saneamiento de viviendas | G30: 300/2023/00593 | H30: Sin lotes | I30: PREZERO ESPAÑA SAU | J30: Gestión de puntos limpios y centros de reutilización; saneamientos por requerimiento. | K30: Ambito municipal; ubicaciones concretas no incluidas | L30: 45622 | M30: 47447 | N30: Víctor Manuel Sarabia Herrero | O30: No acreditado | P30: 010 / 914 800 010 (atencion municipal, no gestor directo) | Q30: Saneamiento no es limpieza domestica ordinaria | R30: Vigente según Ayuntamiento; adjudicataria PREZERO acreditada (24/10/2024). Inicio contractual y fecha fin exacta sin acreditar. | FECHAS REVISADAS: Vigencia: 26/11/2024–25/11/2029. Inicio oficial; fin ordinario calculado por cinco años contractuales sin prórroga. | CONTROL DOCUMENTAL 21/10/2026: Adjudicataria identificada. PREZERO ESPAÑA figura adjudicataria de puntos limpios. El contrato es municipal; no son 21 concesiones independientes. [Base de evidencia: Datos confrontados con referencias aportadas; no hay resolución individual corroborada] | CONTRASTE ADICIONAL 21/10/2026: ADJUDICACIÓN: PREZERO ESPAÑA SA, 24/10/2024. El Ayuntamiento dispone de ficha oficial del contrato; compruébese formalización para fechas exactas. | S30: https://contratos.gobierto.es/licitaciones/4336157 https://contrataciondelestado.es/FileSystem/servlet/GetDocumentByIdServlet?DocumentIdParam=DX1ZAvwzaIUStPoibgXBVeTGIJOgffe86rdC19dt4dT5lTaSGg5Vq9cT4fT6Jv75jYAipcFv6g1zHenSv4lINo4IQyA7QON0MW%2BNRBCDa6cZyAJWGsSt0OzTSTyw9JAs&cifrado=QUC1GjXXSiLkydRHJBmbpw%3D%3D https://www.madrid.es/UnidadesDescentralizadas/LimpiezaUrbanaYResiduos/CONTRATOS_DG/CONTRATO-RES_PuntosLimpios/DocumentoPliegos_ContratoPuntosLimpios.pdf https://www.madrid.es/portales/munimadrid/es/Inicio/Medio-ambiente/Recogida-de-residuos/Contrato-de-servicios-de-explotacion-de-puntos-limpios-centros-de-reutilizacion-de-residuos-y-saneamiento-de-viviendas-en-la-ciudad-de-Madrid/?vgnextchannel=f81379ed268fe410VgnVCM1000000b205a0aRCRD&vgnextfmt=default&vgnextoid=8177150aabc46710VgnVCM2000001f4a900aRCRD | T30: REL-0029 | U30: 300/2023/00593|Sin lotes | V30: =IF(AND(SUM(IF('Consulta de contratos'!$K$1="",0,1),IF('Consulta de contratos'!$K$2="",0,1),IF('Consulta de contratos'!$K$3="",0,1),IF('Consulta de contratos'!$K$4="",0,1),IF('Consulta de contratos'!$K$5="",0,1),IF('Consulta de contratos'!$K$6="",0,1))>0,OR('Consulta de contratos'!$K$1="",A30='Consulta de contratos'!$K$1),OR('Consulta de contratos'!$K$2="",I30='Consulta de contratos'!$K$2),OR('Consulta de contratos'!$K$3="",C30='Consulta de contratos'!$K$3),OR('Consulta de contratos'!$K$4="",D30='Consulta de contratos'!$K$4),OR('Consulta de contratos'!$K$5="",E30='Consulta de contratos'!$K$5),OR('Consulta de contratos'!$K$6="",IFERROR(ISNUMBER(SEARCH("|"&'Consulta de contratos'!$K$6&"|",AF30)),FALSE))),1,0) -> 0 | W30: =IF(V30=1,SUM($V$2:V30),0) -> 0 | X30: FIN REGISTRADO POSTERIOR · EJECUCIÓN A CONFIRMAR | Y30: PREZERO | Z30: Grupo/familia pendiente de confirmar legalmente | AA30: 16/10/2026 | AF30: |PREZERO|
A31: Chamartín | B31: Residuos | C31: Área de Gobierno de Urbanismo, Medio Ambiente y Movilidad | D31: Dirección General de Servicios de Limpieza y Residuos | E31: Subdirección General de Recogida de Residuos | F31: Programa de actividades de sensibilización sobre separación de residuos y limpieza del espacio público | G31: 300/2026/00024 | H31: Sin lotes | I31: TALHER, S.A. | J31: Actividades educativas y de sensibilizacion | K31: Ambito municipal; no acredita actividad en cada distrito | N31: Víctor Manuel Sarabia Herrero | O31: No acreditado | P31: 010 / 914 800 010 (atencion municipal, no gestor directo) | Q31: Adjudicación publicada en datos de PLACSP; formalización e inicio efectivos sin contrastar. | ATENCIÓN · CONTRASTE 23/10/2026: el portal municipal incluye este expediente entre los contratos en vigor, mientras un agregador lo presenta como «Desistida». La resolución de adjudicación, la formalización y el inicio efectivo requieren comprobación directa. | R31: ADJUDICACIÓN 30/09/2026 A TALHER, S.A. (1.432.107 € sin IVA) recogida en LicitaLens a partir de PLACSP. Pendiente de verificar resolución y fecha de formalización en documento oficial; no certificar inicio efectivo. | CONTROL DOCUMENTAL 21/10/2026: Adjudicación localizada. Adjudicación a TALHER encontrada en plataformas que reproducen PLACSP; la resolución y la fecha de ejecución requieren lectura directa. [Base de evidencia: Ficha individual de publicación / agregador contrastada] | CONTRASTE DE FUENTES 23/10/2026: ficha municipal lo relaciona entre contratos en vigor; Gobierto muestra estado «Desistida», pese a reflejar datos de adjudicación del 30/09/2026. No tratar la formalización, la entrada en servicio ni la vigencia como acreditadas sin resolución. | S31: https://www.madrid.es/portales/munimadrid/es/Inicio/El-Ayuntamiento/Publicaciones/Listado-de-Publicaciones/Contratos-de-Recogida-de-Residuos/?vgnextchannel=f1aebadb6b997010VgnVCM100000dc0ca8c0RCRD&vgnextfmt=default&vgnextoid=429f71adf3d56910VgnVCM2000001f4a900aRCRD https://contratos.gobierto.es/licitaciones/5108890 https://licitalens.com/empresa/A08602815 https://www.madrid.es/portales/munimadrid/es/Inicio/Medio-ambiente/Recogida-de-residuos/Actividades-y-eventos/Contrato-de-servicio-de-actividades-de-sensibilizacion/?vgnextchannel=d04bbb21278fe410VgnVCM1000000b205a0aRCRD&vgnextfmt=default&vgnextoid=1d1f49ec5caef910VgnVCM200000f921e388RCRD | T31: REL-0030 | U31: 300/2026/00024|Sin lotes | V31: =IF(AND(SUM(IF('Consulta de contratos'!$K$1="",0,1),IF('Consulta de contratos'!$K$2="",0,1),IF('Consulta de contratos'!$K$3="",0,1),IF('Consulta de contratos'!$K$4="",0,1),IF('Consulta de contratos'!$K$5="",0,1),IF('Consulta de contratos'!$K$6="",0,1))>0,OR('Consulta de contratos'!$K$1="",A31='Consulta de contratos'!$K$1),OR('Consulta de contratos'!$K$2="",I31='Consulta de contratos'!$K$2),OR('Consulta de contratos'!$K$3="",C31='Consulta de contratos'!$K$3),OR('Consulta de contratos'!$K$4="",D31='Consulta de contratos'!$K$4),OR('Consulta de contratos'!$K$5="",E31='Consulta de contratos'!$K$5),OR('Consulta de contratos'!$K$6="",IFERROR(ISNUMBER(SEARCH("|"&'Consulta de contratos'!$K$6&"|",AF31)),FALSE))),1,0) -> 0 | W31: =IF(V31=1,SUM($V$2:V31),0) -> 0 | X31: ADJUDICACIÓN PUBLICADA EN DATOS PLACSP · FORMALIZACIÓN POR CONTRASTAR | Y31: CLECE | Z31: Grupo de empresa contrastado en fuente corporativa: https://clece.es/es/listado-clece-filiales/ | AA31: 16/10/2026 | AF31: |CLECE|
A32: Tetuán | B32: Residuos | C32: Área de Gobierno de Urbanismo, Medio Ambiente y Movilidad | D32: Dirección General de Servicios de Limpieza y Residuos | E32: Subdirección General de Recogida de Residuos | F32: Contenerización, recogida y transporte de residuos | G32: 131/2021/06296 | H32: 1 | I32: FCC MEDIO AMBIENTE, SA | J32: Recogida y transporte habitual | K32: Zona territorial del lote | L32: 44866 | M32: 47057 | N32: Víctor Manuel Sarabia Herrero | O32: No acreditado | P32: 010 / 914 800 010 (atencion municipal, no gestor directo) | Q32: Lote 1: eventos eje Castellana-Prado-Recoletos | R32: Concesión vigente; adjudicataria y fin 31/10/2028 contrastados en registro de concesiones municipal (15/10/2026). | FECHAS REVISADAS: Inicio 01/11/2022 acreditado por formalización de los cuatro lotes. | CONTROL DOCUMENTAL 21/10/2026: Adjudicación y fin publicados. Los cuatro lotes se pueden contrastar en el registro municipal de concesiones. Fin publicado: 31/10/2028. No generalizar ámbito de cada lote. [Base de evidencia: Portal municipal / resolución o resultado oficial consultado] | CONTRASTE ADICIONAL 21/10/2026: FUENTE MUNICIPAL: la concesión registra adjudicación diferenciada en los 4 lotes (FCC, UTE VAO, UTE Sur, CONTENUR) y fin contractual 31/10/2028. | S32: https://contratacion.madrid.es/concesiones/ https://contrataciondelestado.es/FileSystem/servlet/GetDocumentByIdServlet?DocumentIdParam=I52CDqtLbsdgHyWk6Tjc%2BH2t2QGKU1Ro9lcaZmb7V5J4T4CLRYtO18fD2fcADXQg90aL83OqQbUADSXvNu02Vt6kOzxNccJdTRf8umMgorI%3D&cifrado=QUC1GjXXSiLkydRHJBmbpw%3D%3D | T32: REL-0031 | U32: 131/2021/06296|1 | V32: =IF(AND(SUM(IF('Consulta de contratos'!$K$1="",0,1),IF('Consulta de contratos'!$K$2="",0,1),IF('Consulta de contratos'!$K$3="",0,1),IF('Consulta de contratos'!$K$4="",0,1),IF('Consulta de contratos'!$K$5="",0,1),IF('Consulta de contratos'!$K$6="",0,1))>0,OR('Consulta de contratos'!$K$1="",A32='Consulta de contratos'!$K$1),OR('Consulta de contratos'!$K$2="",I32='Consulta de contratos'!$K$2),OR('Consulta de contratos'!$K$3="",C32='Consulta de contratos'!$K$3),OR('Consulta de contratos'!$K$4="",D32='Consulta de contratos'!$K$4),OR('Consulta de contratos'!$K$5="",E32='Consulta de contratos'!$K$5),OR('Consulta de contratos'!$K$6="",IFERROR(ISNUMBER(SEARCH("|"&'Consulta de contratos'!$K$6&"|",AF32)),FALSE))),1,0) -> 0 | W32: =IF(V32=1,SUM($V$2:V32),0) -> 0 | X32: FIN REGISTRADO POSTERIOR · EJECUCIÓN A CONFIRMAR | Y32: FCC | Z32: Grupo/familia pendiente de confirmar legalmente | AA32: 16/10/2026 | AF32: |FCC|
A33: Tetuán | B33: Residuos | C33: Área de Gobierno de Urbanismo, Medio Ambiente y Movilidad | D33: Dirección General de Servicios de Limpieza y Residuos | E33: Subdirección General de Recogida de Residuos | F33: Contenerización, recogida y transporte de residuos | G33: 131/2021/06296 | H33: 4 | I33: CONTENUR SL | J33: Suministro, mantenimiento y limpieza de contenedores | K33: Toda la ciudad | L33: 44866 | M33: 47057 | N33: Víctor Manuel Sarabia Herrero | O33: No acreditado | P33: 010 / 914 800 010 (atencion municipal, no gestor directo) | Q33: No es vaciado ni recogida habitual | R33: Concesión vigente; adjudicataria y fin 31/10/2028 contrastados en registro de concesiones municipal (15/10/2026). | FECHAS REVISADAS: Inicio 01/11/2022 acreditado por formalización de los cuatro lotes. | CONTROL DOCUMENTAL 21/10/2026: Adjudicación y fin publicados. Los cuatro lotes se pueden contrastar en el registro municipal de concesiones. Fin publicado: 31/10/2028. No generalizar ámbito de cada lote. [Base de evidencia: Portal municipal / resolución o resultado oficial consultado] | CONTRASTE ADICIONAL 21/10/2026: FUENTE MUNICIPAL: la concesión registra adjudicación diferenciada en los 4 lotes (FCC, UTE VAO, UTE Sur, CONTENUR) y fin contractual 31/10/2028. | S33: https://contratacion.madrid.es/concesiones/ https://contrataciondelestado.es/FileSystem/servlet/GetDocumentByIdServlet?DocumentIdParam=I52CDqtLbsdgHyWk6Tjc%2BH2t2QGKU1Ro9lcaZmb7V5J4T4CLRYtO18fD2fcADXQg90aL83OqQbUADSXvNu02Vt6kOzxNccJdTRf8umMgorI%3D&cifrado=QUC1GjXXSiLkydRHJBmbpw%3D%3D | T33: REL-0032 | U33: 131/2021/06296|4 | V33: =IF(AND(SUM(IF('Consulta de contratos'!$K$1="",0,1),IF('Consulta de contratos'!$K$2="",0,1),IF('Consulta de contratos'!$K$3="",0,1),IF('Consulta de contratos'!$K$4="",0,1),IF('Consulta de contratos'!$K$5="",0,1),IF('Consulta de contratos'!$K$6="",0,1))>0,OR('Consulta de contratos'!$K$1="",A33='Consulta de contratos'!$K$1),OR('Consulta de contratos'!$K$2="",I33='Consulta de contratos'!$K$2),OR('Consulta de contratos'!$K$3="",C33='Consulta de contratos'!$K$3),OR('Consulta de contratos'!$K$4="",D33='Consulta de contratos'!$K$4),OR('Consulta de contratos'!$K$5="",E33='Consulta de contratos'!$K$5),OR('Consulta de contratos'!$K$6="",IFERROR(ISNUMBER(SEARCH("|"&'Consulta de contratos'!$K$6&"|",AF33)),FALSE))),1,0) -> 0 | W33: =IF(V33=1,SUM($V$2:V33),0) -> 0 | X33: FIN REGISTRADO POSTERIOR · EJECUCIÓN A CONFIRMAR | Y33: CONTENUR SL | Z33: Agrupación de consulta por nombre de adjudicataria; no consta matriz contrastada. | AA33: 16/10/2026 | AF33: |CONTENUR SL|
A34: Tetuán | B34: Residuos | C34: Área de Gobierno de Urbanismo, Medio Ambiente y Movilidad | D34: Dirección General de Servicios de Limpieza y Residuos | E34: Subdirección General de Recogida de Residuos | F34: Contenerización, recogida y transporte de residuos | G34: 131/2021/06296 | H34: 3 | I34: UTE 2022 Recogida Madrid Sur | J34: Recogida de pilas y baterias usadas | K34: Toda la ciudad | L34: 44866 | M34: 47057 | N34: Víctor Manuel Sarabia Herrero | O34: No acreditado | P34: 010 / 914 800 010 (atencion municipal, no gestor directo) | Q34: Tarea especial del lote 3 fuera de su zona habitual | R34: Concesión vigente; adjudicataria y fin 31/10/2028 contrastados en registro de concesiones municipal (15/10/2026). | FECHAS REVISADAS: Inicio 01/11/2022 acreditado por formalización de los cuatro lotes. | CONTROL DOCUMENTAL 21/10/2026: Adjudicación y fin publicados. Los cuatro lotes se pueden contrastar en el registro municipal de concesiones. Fin publicado: 31/10/2028. No generalizar ámbito de cada lote. [Base de evidencia: Portal municipal / resolución o resultado oficial consultado] | CONTRASTE ADICIONAL 21/10/2026: FUENTE MUNICIPAL: la concesión registra adjudicación diferenciada en los 4 lotes (FCC, UTE VAO, UTE Sur, CONTENUR) y fin contractual 31/10/2028. | S34: https://contratacion.madrid.es/concesiones/ https://contrataciondelestado.es/FileSystem/servlet/GetDocumentByIdServlet?DocumentIdParam=I52CDqtLbsdgHyWk6Tjc%2BH2t2QGKU1Ro9lcaZmb7V5J4T4CLRYtO18fD2fcADXQg90aL83OqQbUADSXvNu02Vt6kOzxNccJdTRf8umMgorI%3D&cifrado=QUC1GjXXSiLkydRHJBmbpw%3D%3D | T34: REL-0033 | U34: 131/2021/06296|3 | V34: =IF(AND(SUM(IF('Consulta de contratos'!$K$1="",0,1),IF('Consulta de contratos'!$K$2="",0,1),IF('Consulta de contratos'!$K$3="",0,1),IF('Consulta de contratos'!$K$4="",0,1),IF('Consulta de contratos'!$K$5="",0,1),IF('Consulta de contratos'!$K$6="",0,1))>0,OR('Consulta de contratos'!$K$1="",A34='Consulta de contratos'!$K$1),OR('Consulta de contratos'!$K$2="",I34='Consulta de contratos'!$K$2),OR('Consulta de contratos'!$K$3="",C34='Consulta de contratos'!$K$3),OR('Consulta de contratos'!$K$4="",D34='Consulta de contratos'!$K$4),OR('Consulta de contratos'!$K$5="",E34='Consulta de contratos'!$K$5),OR('Consulta de contratos'!$K$6="",IFERROR(ISNUMBER(SEARCH("|"&'Consulta de contratos'!$K$6&"|",AF34)),FALSE))),1,0) -> 0 | W34: =IF(V34=1,SUM($V$2:V34),0) -> 0 | X34: FIN REGISTRADO POSTERIOR · EJECUCIÓN A CONFIRMAR | Y34: PREZERO | URBASER | Z34: UTE: vínculo comercial; no implica propiedad | AA34: 16/10/2026 | AF34: |PREZERO|URBASER|
A35: Tetuán | B35: Residuos | C35: Área de Gobierno de Urbanismo, Medio Ambiente y Movilidad | D35: Dirección General de Servicios de Limpieza y Residuos | E35: Subdirección General de Recogida de Residuos | F35: Asistencia técnica para el mantenimiento, ampliación y mejora continua del sistema de gestión de la información de limpieza urbana, recogida de residuos y equipamientos urbanos | G35: 300/2025/00411 | H35: Sin lotes | I35: APORTA PLATAFORMA COOPERATIVA SCCL | J35: Mantenimiento y mejora del sistema de informacion | K35: Ambito municipal; no contrato propio del distrito | M35: 46850 | N35: Víctor Manuel Sarabia Herrero | O35: No acreditado | P35: 010 / 914 800 010 (atencion municipal, no gestor directo) | R35: Adjudicado 27/01/2026 y formalizado 08/04/2026. Fin publicado 07/04/2028 (posible prórroga 12 meses). Inicio de prestación no acreditado. | FECHAS SIN ACREDITAR: Formalización 08/04/2026 y fin en agregador 07/04/2028; no consta fecha independiente de inicio de prestación. La formalización no se convierte en inicio automático. | FUENTES REVISADAS 21/10/2026: Ayuntamiento publica objeto y pliegos; registro TED del contrato identifica formalización el 08/04/2026 y adjudicataria Aporta. No equivale a fecha de inicio operativo. | CONTROL DOCUMENTAL 21/10/2026: Adjudicataria identificada. APORTA PLATAFORMA COOPERATIVA figura en la base y en fichas de licitación; comprobar firma e hitos en el expediente. [Base de evidencia: Datos confrontados con referencias aportadas; no hay resolución individual corroborada] | CONTRASTE ADICIONAL 21/10/2026: ADJUDICACIÓN: APORTA PLATAFORMA COOPERATIVA SCCL, resolución de 27/01/2026, contrastada con publicación de licitación. | S35: https://contratos.gobierto.es/adjudicatarios/aporta-plataforma-cooperativa-sccl?locale=es https://www.madrid.es/portales/munimadrid/es/Inicio/Medio-ambiente/Limpieza-urbana/Contrato-de-servicio-de-asistencia-tecnica/?vgnextchannel=ddd2a694fde40910VgnVCM2000001f4a900aRCRD&vgnextfmt=default&vgnextoid=7c07475398a4e910VgnVCM200000f921e388RCRD https://contratos.gobierto.es/licitaciones/4668721?locale=es | T35: REL-0034 | U35: 300/2025/00411|Sin lotes | V35: =IF(AND(SUM(IF('Consulta de contratos'!$K$1="",0,1),IF('Consulta de contratos'!$K$2="",0,1),IF('Consulta de contratos'!$K$3="",0,1),IF('Consulta de contratos'!$K$4="",0,1),IF('Consulta de contratos'!$K$5="",0,1),IF('Consulta de contratos'!$K$6="",0,1))>0,OR('Consulta de contratos'!$K$1="",A35='Consulta de contratos'!$K$1),OR('Consulta de contratos'!$K$2="",I35='Consulta de contratos'!$K$2),OR('Consulta de contratos'!$K$3="",C35='Consulta de contratos'!$K$3),OR('Consulta de contratos'!$K$4="",D35='Consulta de contratos'!$K$4),OR('Consulta de contratos'!$K$5="",E35='Consulta de contratos'!$K$5),OR('Consulta de contratos'!$K$6="",IFERROR(ISNUMBER(SEARCH("|"&'Consulta de contratos'!$K$6&"|",AF35)),FALSE))),1,0) -> 0 | W35: =IF(V35=1,SUM($V$2:V35),0) -> 0 | X35: FIN REGISTRADO POSTERIOR · EJECUCIÓN A CONFIRMAR | Y35: APORTA PLATAFORMA COOPERATIVA SCCL | Z35: Agrupación de consulta por nombre de adjudicataria; no consta matriz contrastada. | AA35: 16/10/2026 | AF35: |APORTA PLATAFORMA COOPERATIVA SCCL|
A36: Tetuán | B36: Residuos | C36: Área de Gobierno de Urbanismo, Medio Ambiente y Movilidad | D36: Dirección General de Servicios de Limpieza y Residuos | E36: Subdirección General de Recogida de Residuos | F36: Gestión del servicio de explotación de puntos limpios, centros de reutilización de residuos y saneamiento de viviendas | G36: 300/2023/00593 | H36: Sin lotes | I36: PREZERO ESPAÑA SAU | J36: Gestión de puntos limpios y centros de reutilización; saneamientos por requerimiento. | K36: Ambito municipal; ubicaciones concretas no incluidas | L36: 45622 | M36: 47447 | N36: Víctor Manuel Sarabia Herrero | O36: No acreditado | P36: 010 / 914 800 010 (atencion municipal, no gestor directo) | Q36: Saneamiento no es limpieza domestica ordinaria | R36: Vigente según Ayuntamiento; adjudicataria PREZERO acreditada (24/10/2024). Inicio contractual y fecha fin exacta sin acreditar. | FECHAS REVISADAS: Vigencia: 26/11/2024–25/11/2029. Inicio oficial; fin ordinario calculado por cinco años contractuales sin prórroga. | CONTROL DOCUMENTAL 21/10/2026: Adjudicataria identificada. PREZERO ESPAÑA figura adjudicataria de puntos limpios. El contrato es municipal; no son 21 concesiones independientes. [Base de evidencia: Datos confrontados con referencias aportadas; no hay resolución individual corroborada] | CONTRASTE ADICIONAL 21/10/2026: ADJUDICACIÓN: PREZERO ESPAÑA SA, 24/10/2024. El Ayuntamiento dispone de ficha oficial del contrato; compruébese formalización para fechas exactas. | S36: https://contratos.gobierto.es/licitaciones/4336157 https://contrataciondelestado.es/FileSystem/servlet/GetDocumentByIdServlet?DocumentIdParam=DX1ZAvwzaIUStPoibgXBVeTGIJOgffe86rdC19dt4dT5lTaSGg5Vq9cT4fT6Jv75jYAipcFv6g1zHenSv4lINo4IQyA7QON0MW%2BNRBCDa6cZyAJWGsSt0OzTSTyw9JAs&cifrado=QUC1GjXXSiLkydRHJBmbpw%3D%3D https://www.madrid.es/UnidadesDescentralizadas/LimpiezaUrbanaYResiduos/CONTRATOS_DG/CONTRATO-RES_PuntosLimpios/DocumentoPliegos_ContratoPuntosLimpios.pdf https://www.madrid.es/portales/munimadrid/es/Inicio/Medio-ambiente/Recogida-de-residuos/Contrato-de-servicios-de-explotacion-de-puntos-limpios-centros-de-reutilizacion-de-residuos-y-saneamiento-de-viviendas-en-la-ciudad-de-Madrid/?vgnextchannel=f81379ed268fe410VgnVCM1000000b205a0aRCRD&vgnextfmt=default&vgnextoid=8177150aabc46710VgnVCM2000001f4a900aRCRD | T36: REL-0035 | U36: 300/2023/00593|Sin lotes | V36: =IF(AND(SUM(IF('Consulta de contratos'!$K$1="",0,1),IF('Consulta de contratos'!$K$2="",0,1),IF('Consulta de contratos'!$K$3="",0,1),IF('Consulta de contratos'!$K$4="",0,1),IF('Consulta de contratos'!$K$5="",0,1),IF('Consulta de contratos'!$K$6="",0,1))>0,OR('Consulta de contratos'!$K$1="",A36='Consulta de contratos'!$K$1),OR('Consulta de contratos'!$K$2="",I36='Consulta de contratos'!$K$2),OR('Consulta de contratos'!$K$3="",C36='Consulta de contratos'!$K$3),OR('Consulta de contratos'!$K$4="",D36='Consulta de contratos'!$K$4),OR('Consulta de contratos'!$K$5="",E36='Consulta de contratos'!$K$5),OR('Consulta de contratos'!$K$6="",IFERROR(ISNUMBER(SEARCH("|"&'Consulta de contratos'!$K$6&"|",AF36)),FALSE))),1,0) -> 0 | W36: =IF(V36=1,SUM($V$2:V36),0) -> 0 | X36: FIN REGISTRADO POSTERIOR · EJECUCIÓN A CONFIRMAR | Y36: PREZERO | Z36: Grupo/familia pendiente de confirmar legalmente | AA36: 16/10/2026 | AF36: |PREZERO|
A37: Tetuán | B37: Residuos | C37: Área de Gobierno de Urbanismo, Medio Ambiente y Movilidad | D37: Dirección General de Servicios de Limpieza y Residuos | E37: Subdirección General de Recogida de Residuos | F37: Programa de actividades de sensibilización sobre separación de residuos y limpieza del espacio público | G37: 300/2026/00024 | H37: Sin lotes | I37: TALHER, S.A. | J37: Actividades educativas y de sensibilizacion | K37: Ambito municipal; no acredita actividad en cada distrito | N37: Víctor Manuel Sarabia Herrero | O37: No acreditado | P37: 010 / 914 800 010 (atencion municipal, no gestor directo) | Q37: Adjudicación publicada en datos de PLACSP; formalización e inicio efectivos sin contrastar. | ATENCIÓN · CONTRASTE 23/10/2026: el portal municipal incluye este expediente entre los contratos en vigor, mientras un agregador lo presenta como «Desistida». La resolución de adjudicación, la formalización y el inicio efectivo requieren comprobación directa. | R37: ADJUDICACIÓN 30/09/2026 A TALHER, S.A. (1.432.107 € sin IVA) recogida en LicitaLens a partir de PLACSP. Pendiente de verificar resolución y fecha de formalización en documento oficial; no certificar inicio efectivo. | CONTROL DOCUMENTAL 21/10/2026: Adjudicación localizada. Adjudicación a TALHER encontrada en plataformas que reproducen PLACSP; la resolución y la fecha de ejecución requieren lectura directa. [Base de evidencia: Ficha individual de publicación / agregador contrastada] | CONTRASTE DE FUENTES 23/10/2026: ficha municipal lo relaciona entre contratos en vigor; Gobierto muestra estado «Desistida», pese a reflejar datos de adjudicación del 30/09/2026. No tratar la formalización, la entrada en servicio ni la vigencia como acreditadas sin resolución. | S37: https://www.madrid.es/portales/munimadrid/es/Inicio/El-Ayuntamiento/Publicaciones/Listado-de-Publicaciones/Contratos-de-Recogida-de-Residuos/?vgnextchannel=f1aebadb6b997010VgnVCM100000dc0ca8c0RCRD&vgnextfmt=default&vgnextoid=429f71adf3d56910VgnVCM2000001f4a900aRCRD https://contratos.gobierto.es/licitaciones/5108890 https://licitalens.com/empresa/A08602815 https://www.madrid.es/portales/munimadrid/es/Inicio/Medio-ambiente/Recogida-de-residuos/Actividades-y-eventos/Contrato-de-servicio-de-actividades-de-sensibilizacion/?vgnextchannel=d04bbb21278fe410VgnVCM1000000b205a0aRCRD&vgnextfmt=default&vgnextoid=1d1f49ec5caef910VgnVCM200000f921e388RCRD | T37: REL-0036 | U37: 300/2026/00024|Sin lotes | V37: =IF(AND(SUM(IF('Consulta de contratos'!$K$1="",0,1),IF('Consulta de contratos'!$K$2="",0,1),IF('Consulta de contratos'!$K$3="",0,1),IF('Consulta de contratos'!$K$4="",0,1),IF('Consulta de contratos'!$K$5="",0,1),IF('Consulta de contratos'!$K$6="",0,1))>0,OR('Consulta de contratos'!$K$1="",A37='Consulta de contratos'!$K$1),OR('Consulta de contratos'!$K$2="",I37='Consulta de contratos'!$K$2),OR('Consulta de contratos'!$K$3="",C37='Consulta de contratos'!$K$3),OR('Consulta de contratos'!$K$4="",D37='Consulta de contratos'!$K$4),OR('Consulta de contratos'!$K$5="",E37='Consulta de contratos'!$K$5),OR('Consulta de contratos'!$K$6="",IFERROR(ISNUMBER(SEARCH("|"&'Consulta de contratos'!$K$6&"|",AF37)),FALSE))),1,0) -> 0 | W37: =IF(V37=1,SUM($V$2:V37),0) -> 0 | X37: ADJUDICACIÓN PUBLICADA EN DATOS PLACSP · FORMALIZACIÓN POR CONTRASTAR | Y37: CLECE | Z37: Grupo de empresa contrastado en fuente corporativa: https://clece.es/es/listado-clece-filiales/ | AA37: 16/10/2026 | AF37: |CLECE|
A38: Chamberí | B38: Residuos | C38: Área de Gobierno de Urbanismo, Medio Ambiente y Movilidad | D38: Dirección General de Servicios de Limpieza y Residuos | E38: Subdirección General de Recogida de Residuos | F38: Contenerización, recogida y transporte de residuos | G38: 131/2021/06296 | H38: 1 | I38: FCC MEDIO AMBIENTE, SA | J38: Recogida y transporte habitual | K38: Zona territorial del lote | L38: 44866 | M38: 47057 | N38: Víctor Manuel Sarabia Herrero | O38: No acreditado | P38: 010 / 914 800 010 (atencion municipal, no gestor directo) | Q38: Lote 1: eventos eje Castellana-Prado-Recoletos | R38: Concesión vigente; adjudicataria y fin 31/10/2028 contrastados en registro de concesiones municipal (15/10/2026). | FECHAS REVISADAS: Inicio 01/11/2022 acreditado por formalización de los cuatro lotes. | CONTROL DOCUMENTAL 21/10/2026: Adjudicación y fin publicados. Los cuatro lotes se pueden contrastar en el registro municipal de concesiones. Fin publicado: 31/10/2028. No generalizar ámbito de cada lote. [Base de evidencia: Portal municipal / resolución o resultado oficial consultado] | CONTRASTE ADICIONAL 21/10/2026: FUENTE MUNICIPAL: la concesión registra adjudicación diferenciada en los 4 lotes (FCC, UTE VAO, UTE Sur, CONTENUR) y fin contractual 31/10/2028. | S38: https://contratacion.madrid.es/concesiones/ https://contrataciondelestado.es/FileSystem/servlet/GetDocumentByIdServlet?DocumentIdParam=I52CDqtLbsdgHyWk6Tjc%2BH2t2QGKU1Ro9lcaZmb7V5J4T4CLRYtO18fD2fcADXQg90aL83OqQbUADSXvNu02Vt6kOzxNccJdTRf8umMgorI%3D&cifrado=QUC1GjXXSiLkydRHJBmbpw%3D%3D | T38: REL-0037 | U38: 131/2021/06296|1 | V38: =IF(AND(SUM(IF('Consulta de contratos'!$K$1="",0,1),IF('Consulta de contratos'!$K$2="",0,1),IF('Consulta de contratos'!$K$3="",0,1),IF('Consulta de contratos'!$K$4="",0,1),IF('Consulta de contratos'!$K$5="",0,1),IF('Consulta de contratos'!$K$6="",0,1))>0,OR('Consulta de contratos'!$K$1="",A38='Consulta de contratos'!$K$1),OR('Consulta de contratos'!$K$2="",I38='Consulta de contratos'!$K$2),OR('Consulta de contratos'!$K$3="",C38='Consulta de contratos'!$K$3),OR('Consulta de contratos'!$K$4="",D38='Consulta de contratos'!$K$4),OR('Consulta de contratos'!$K$5="",E38='Consulta de contratos'!$K$5),OR('Consulta de contratos'!$K$6="",IFERROR(ISNUMBER(SEARCH("|"&'Consulta de contratos'!$K$6&"|",AF38)),FALSE))),1,0) -> 0 | W38: =IF(V38=1,SUM($V$2:V38),0) -> 0 | X38: FIN REGISTRADO POSTERIOR · EJECUCIÓN A CONFIRMAR | Y38: FCC | Z38: Grupo/familia pendiente de confirmar legalmente | AA38: 16/10/2026 | AF38: |FCC|
A39: Chamberí | B39: Residuos | C39: Área de Gobierno de Urbanismo, Medio Ambiente y Movilidad | D39: Dirección General de Servicios de Limpieza y Residuos | E39: Subdirección General de Recogida de Residuos | F39: Contenerización, recogida y transporte de residuos | G39: 131/2021/06296 | H39: 4 | I39: CONTENUR SL | J39: Suministro, mantenimiento y limpieza de contenedores | K39: Toda la ciudad | L39: 44866 | M39: 47057 | N39: Víctor Manuel Sarabia Herrero | O39: No acreditado | P39: 010 / 914 800 010 (atencion municipal, no gestor directo) | Q39: No es vaciado ni recogida habitual | R39: Concesión vigente; adjudicataria y fin 31/10/2028 contrastados en registro de concesiones municipal (15/10/2026). | FECHAS REVISADAS: Inicio 01/11/2022 acreditado por formalización de los cuatro lotes. | CONTROL DOCUMENTAL 21/10/2026: Adjudicación y fin publicados. Los cuatro lotes se pueden contrastar en el registro municipal de concesiones. Fin publicado: 31/10/2028. No generalizar ámbito de cada lote. [Base de evidencia: Portal municipal / resolución o resultado oficial consultado] | CONTRASTE ADICIONAL 21/10/2026: FUENTE MUNICIPAL: la concesión registra adjudicación diferenciada en los 4 lotes (FCC, UTE VAO, UTE Sur, CONTENUR) y fin contractual 31/10/2028. | S39: https://contratacion.madrid.es/concesiones/ https://contrataciondelestado.es/FileSystem/servlet/GetDocumentByIdServlet?DocumentIdParam=I52CDqtLbsdgHyWk6Tjc%2BH2t2QGKU1Ro9lcaZmb7V5J4T4CLRYtO18fD2fcADXQg90aL83OqQbUADSXvNu02Vt6kOzxNccJdTRf8umMgorI%3D&cifrado=QUC1GjXXSiLkydRHJBmbpw%3D%3D | T39: REL-0038 | U39: 131/2021/06296|4 | V39: =IF(AND(SUM(IF('Consulta de contratos'!$K$1="",0,1),IF('Consulta de contratos'!$K$2="",0,1),IF('Consulta de contratos'!$K$3="",0,1),IF('Consulta de contratos'!$K$4="",0,1),IF('Consulta de contratos'!$K$5="",0,1),IF('Consulta de contratos'!$K$6="",0,1))>0,OR('Consulta de contratos'!$K$1="",A39='Consulta de contratos'!$K$1),OR('Consulta de contratos'!$K$2="",I39='Consulta de contratos'!$K$2),OR('Consulta de contratos'!$K$3="",C39='Consulta de contratos'!$K$3),OR('Consulta de contratos'!$K$4="",D39='Consulta de contratos'!$K$4),OR('Consulta de contratos'!$K$5="",E39='Consulta de contratos'!$K$5),OR('Consulta de contratos'!$K$6="",IFERROR(ISNUMBER(SEARCH("|"&'Consulta de contratos'!$K$6&"|",AF39)),FALSE))),1,0) -> 0 | W39: =IF(V39=1,SUM($V$2:V39),0) -> 0 | X39: FIN REGISTRADO POSTERIOR · EJECUCIÓN A CONFIRMAR | Y39: CONTENUR SL | Z39: Agrupación de consulta por nombre de adjudicataria; no consta matriz contrastada. | AA39: 16/10/2026 | AF39: |CONTENUR SL|
A40: Chamberí | B40: Residuos | C40: Área de Gobierno de Urbanismo, Medio Ambiente y Movilidad | D40: Dirección General de Servicios de Limpieza y Residuos | E40: Subdirección General de Recogida de Residuos | F40: Contenerización, recogida y transporte de residuos | G40: 131/2021/06296 | H40: 3 | I40: UTE 2022 Recogida Madrid Sur | J40: Recogida de pilas y baterias usadas | K40: Toda la ciudad | L40: 44866 | M40: 47057 | N40: Víctor Manuel Sarabia Herrero | O40: No acreditado | P40: 010 / 914 800 010 (atencion municipal, no gestor directo) | Q40: Tarea especial del lote 3 fuera de su zona habitual | R40: Concesión vigente; adjudicataria y fin 31/10/2028 contrastados en registro de concesiones municipal (15/10/2026). | FECHAS REVISADAS: Inicio 01/11/2022 acreditado por formalización de los cuatro lotes. | CONTROL DOCUMENTAL 21/10/2026: Adjudicación y fin publicados. Los cuatro lotes se pueden contrastar en el registro municipal de concesiones. Fin publicado: 31/10/2028. No generalizar ámbito de cada lote. [Base de evidencia: Portal municipal / resolución o resultado oficial consultado] | CONTRASTE ADICIONAL 21/10/2026: FUENTE MUNICIPAL: la concesión registra adjudicación diferenciada en los 4 lotes (FCC, UTE VAO, UTE Sur, CONTENUR) y fin contractual 31/10/2028. | S40: https://contratacion.madrid.es/concesiones/ https://contrataciondelestado.es/FileSystem/servlet/GetDocumentByIdServlet?DocumentIdParam=I52CDqtLbsdgHyWk6Tjc%2BH2t2QGKU1Ro9lcaZmb7V5J4T4CLRYtO18fD2fcADXQg90aL83OqQbUADSXvNu02Vt6kOzxNccJdTRf8umMgorI%3D&cifrado=QUC1GjXXSiLkydRHJBmbpw%3D%3D | T40: REL-0039 | U40: 131/2021/06296|3 | V40: =IF(AND(SUM(IF('Consulta de contratos'!$K$1="",0,1),IF('Consulta de contratos'!$K$2="",0,1),IF('Consulta de contratos'!$K$3="",0,1),IF('Consulta de contratos'!$K$4="",0,1),IF('Consulta de contratos'!$K$5="",0,1),IF('Consulta de contratos'!$K$6="",0,1))>0,OR('Consulta de contratos'!$K$1="",A40='Consulta de contratos'!$K$1),OR('Consulta de contratos'!$K$2="",I40='Consulta de contratos'!$K$2),OR('Consulta de contratos'!$K$3="",C40='Consulta de contratos'!$K$3),OR('Consulta de contratos'!$K$4="",D40='Consulta de contratos'!$K$4),OR('Consulta de contratos'!$K$5="",E40='Consulta de contratos'!$K$5),OR('Consulta de contratos'!$K$6="",IFERROR(ISNUMBER(SEARCH("|"&'Consulta de contratos'!$K$6&"|",AF40)),FALSE))),1,0) -> 0 | W40: =IF(V40=1,SUM($V$2:V40),0) -> 0 | X40: FIN REGISTRADO POSTERIOR · EJECUCIÓN A CONFIRMAR | Y40: PREZERO | URBASER | Z40: UTE: vínculo comercial; no implica propiedad | AA40: 16/10/2026 | AF40: |PREZERO|URBASER|
A41: Chamberí | B41: Residuos | C41: Área de Gobierno de Urbanismo, Medio Ambiente y Movilidad | D41: Dirección General de Servicios de Limpieza y Residuos | E41: Subdirección General de Recogida de Residuos | F41: Asistencia técnica para el mantenimiento, ampliación y mejora continua del sistema de gestión de la información de limpieza urbana, recogida de residuos y equipamientos urbanos | G41: 300/2025/00411 | H41: Sin lotes | I41: APORTA PLATAFORMA COOPERATIVA SCCL | J41: Mantenimiento y mejora del sistema de informacion | K41: Ambito municipal; no contrato propio del distrito | M41: 46850 | N41: Víctor Manuel Sarabia Herrero | O41: No acreditado | P41: 010 / 914 800 010 (atencion municipal, no gestor directo) | R41: Adjudicado 27/01/2026 y formalizado 08/04/2026. Fin publicado 07/04/2028 (posible prórroga 12 meses). Inicio de prestación no acreditado. | FECHAS SIN ACREDITAR: Formalización 08/04/2026 y fin en agregador 07/04/2028; no consta fecha independiente de inicio de prestación. La formalización no se convierte en inicio automático. | FUENTES REVISADAS 21/10/2026: Ayuntamiento publica objeto y pliegos; registro TED del contrato identifica formalización el 08/04/2026 y adjudicataria Aporta. No equivale a fecha de inicio operativo. | CONTROL DOCUMENTAL 21/10/2026: Adjudicataria identificada. APORTA PLATAFORMA COOPERATIVA figura en la base y en fichas de licitación; comprobar firma e hitos en el expediente. [Base de evidencia: Datos confrontados con referencias aportadas; no hay resolución individual corroborada] | CONTRASTE ADICIONAL 21/10/2026: ADJUDICACIÓN: APORTA PLATAFORMA COOPERATIVA SCCL, resolución de 27/01/2026, contrastada con publicación de licitación. | S41: https://contratos.gobierto.es/adjudicatarios/aporta-plataforma-cooperativa-sccl?locale=es https://www.madrid.es/portales/munimadrid/es/Inicio/Medio-ambiente/Limpieza-urbana/Contrato-de-servicio-de-asistencia-tecnica/?vgnextchannel=ddd2a694fde40910VgnVCM2000001f4a900aRCRD&vgnextfmt=default&vgnextoid=7c07475398a4e910VgnVCM200000f921e388RCRD https://contratos.gobierto.es/licitaciones/4668721?locale=es | T41: REL-0040 | U41: 300/2025/00411|Sin lotes | V41: =IF(AND(SUM(IF('Consulta de contratos'!$K$1="",0,1),IF('Consulta de contratos'!$K$2="",0,1),IF('Consulta de contratos'!$K$3="",0,1),IF('Consulta de contratos'!$K$4="",0,1),IF('Consulta de contratos'!$K$5="",0,1),IF('Consulta de contratos'!$K$6="",0,1))>0,OR('Consulta de contratos'!$K$1="",A41='Consulta de contratos'!$K$1),OR('Consulta de contratos'!$K$2="",I41='Consulta de contratos'!$K$2),OR('Consulta de contratos'!$K$3="",C41='Consulta de contratos'!$K$3),OR('Consulta de contratos'!$K$4="",D41='Consulta de contratos'!$K$4),OR('Consulta de contratos'!$K$5="",E41='Consulta de contratos'!$K$5),OR('Consulta de contratos'!$K$6="",IFERROR(ISNUMBER(SEARCH("|"&'Consulta de contratos'!$K$6&"|",AF41)),FALSE))),1,0) -> 0 | W41: =IF(V41=1,SUM($V$2:V41),0) -> 0 | X41: FIN REGISTRADO POSTERIOR · EJECUCIÓN A CONFIRMAR | Y41: APORTA PLATAFORMA COOPERATIVA SCCL | Z41: Agrupación de consulta por nombre de adjudicataria; no consta matriz contrastada. | AA41: 16/10/2026 | AF41: |APORTA PLATAFORMA COOPERATIVA SCCL|
A42: Chamberí | B42: Residuos | C42: Área de Gobierno de Urbanismo, Medio Ambiente y Movilidad | D42: Dirección General de Servicios de Limpieza y Residuos | E42: Subdirección General de Recogida de Residuos | F42: Gestión del servicio de explotación de puntos limpios, centros de reutilización de residuos y saneamiento de viviendas | G42: 300/2023/00593 | H42: Sin lotes | I42: PREZERO ESPAÑA SAU | J42: Gestión de puntos limpios y centros de reutilización; saneamientos por requerimiento. | K42: Ambito municipal; ubicaciones concretas no incluidas | L42: 45622 | M42: 47447 | N42: Víctor Manuel Sarabia Herrero | O42: No acreditado | P42: 010 / 914 800 010 (atencion municipal, no gestor directo) | Q42: Saneamiento no es limpieza domestica ordinaria | R42: Vigente según Ayuntamiento; adjudicataria PREZERO acreditada (24/10/2024). Inicio contractual y fecha fin exacta sin acreditar. | FECHAS REVISADAS: Vigencia: 26/11/2024–25/11/2029. Inicio oficial; fin ordinario calculado por cinco años contractuales sin prórroga. | CONTROL DOCUMENTAL 21/10/2026: Adjudicataria identificada. PREZERO ESPAÑA figura adjudicataria de puntos limpios. El contrato es municipal; no son 21 concesiones independientes. [Base de evidencia: Datos confrontados con referencias aportadas; no hay resolución individual corroborada] | CONTRASTE ADICIONAL 21/10/2026: ADJUDICACIÓN: PREZERO ESPAÑA SA, 24/10/2024. El Ayuntamiento dispone de ficha oficial del contrato; compruébese formalización para fechas exactas. | S42: https://contratos.gobierto.es/licitaciones/4336157 https://contrataciondelestado.es/FileSystem/servlet/GetDocumentByIdServlet?DocumentIdParam=DX1ZAvwzaIUStPoibgXBVeTGIJOgffe86rdC19dt4dT5lTaSGg5Vq9cT4fT6Jv75jYAipcFv6g1zHenSv4lINo4IQyA7QON0MW%2BNRBCDa6cZyAJWGsSt0OzTSTyw9JAs&cifrado=QUC1GjXXSiLkydRHJBmbpw%3D%3D https://www.madrid.es/UnidadesDescentralizadas/LimpiezaUrbanaYResiduos/CONTRATOS_DG/CONTRATO-RES_PuntosLimpios/DocumentoPliegos_ContratoPuntosLimpios.pdf https://www.madrid.es/portales/munimadrid/es/Inicio/Medio-ambiente/Recogida-de-residuos/Contrato-de-servicios-de-explotacion-de-puntos-limpios-centros-de-reutilizacion-de-residuos-y-saneamiento-de-viviendas-en-la-ciudad-de-Madrid/?vgnextchannel=f81379ed268fe410VgnVCM1000000b205a0aRCRD&vgnextfmt=default&vgnextoid=8177150aabc46710VgnVCM2000001f4a900aRCRD | T42: REL-0041 | U42: 300/2023/00593|Sin lotes | V42: =IF(AND(SUM(IF('Consulta de contratos'!$K$1="",0,1),IF('Consulta de contratos'!$K$2="",0,1),IF('Consulta de contratos'!$K$3="",0,1),IF('Consulta de contratos'!$K$4="",0,1),IF('Consulta de contratos'!$K$5="",0,1),IF('Consulta de contratos'!$K$6="",0,1))>0,OR('Consulta de contratos'!$K$1="",A42='Consulta de contratos'!$K$1),OR('Consulta de contratos'!$K$2="",I42='Consulta de contratos'!$K$2),OR('Consulta de contratos'!$K$3="",C42='Consulta de contratos'!$K$3),OR('Consulta de contratos'!$K$4="",D42='Consulta de contratos'!$K$4),OR('Consulta de contratos'!$K$5="",E42='Consulta de contratos'!$K$5),OR('Consulta de contratos'!$K$6="",IFERROR(ISNUMBER(SEARCH("|"&'Consulta de contratos'!$K$6&"|",AF42)),FALSE))),1,0) -> 0 | W42: =IF(V42=1,SUM($V$2:V42),0) -> 0 | X42: FIN REGISTRADO POSTERIOR · EJECUCIÓN A CONFIRMAR | Y42: PREZERO | Z42: Grupo/familia pendiente de confirmar legalmente | AA42: 16/10/2026 | AF42: |PREZERO|
A43: Chamberí | B43: Residuos | C43: Área de Gobierno de Urbanismo, Medio Ambiente y Movilidad | D43: Dirección General de Servicios de Limpieza y Residuos | E43: Subdirección General de Recogida de Residuos | F43: Programa de actividades de sensibilización sobre separación de residuos y limpieza del espacio público | G43: 300/2026/00024 | H43: Sin lotes | I43: TALHER, S.A. | J43: Actividades educativas y de sensibilizacion | K43: Ambito municipal; no acredita actividad en cada distrito | N43: Víctor Manuel Sarabia Herrero | O43: No acreditado | P43: 010 / 914 800 010 (atencion municipal, no gestor directo) | Q43: Adjudicación publicada en datos de PLACSP; formalización e inicio efectivos sin contrastar. | ATENCIÓN · CONTRASTE 23/10/2026: el portal municipal incluye este expediente entre los contratos en vigor, mientras un agregador lo presenta como «Desistida». La resolución de adjudicación, la formalización y el inicio efectivo requieren comprobación directa. | R43: ADJUDICACIÓN 30/09/2026 A TALHER, S.A. (1.432.107 € sin IVA) recogida en LicitaLens a partir de PLACSP. Pendiente de verificar resolución y fecha de formalización en documento oficial; no certificar inicio efectivo. | CONTROL DOCUMENTAL 21/10/2026: Adjudicación localizada. Adjudicación a TALHER encontrada en plataformas que reproducen PLACSP; la resolución y la fecha de ejecución requieren lectura directa. [Base de evidencia: Ficha individual de publicación / agregador contrastada] | CONTRASTE DE FUENTES 23/10/2026: ficha municipal lo relaciona entre contratos en vigor; Gobierto muestra estado «Desistida», pese a reflejar datos de adjudicación del 30/09/2026. No tratar la formalización, la entrada en servicio ni la vigencia como acreditadas sin resolución. | S43: https://www.madrid.es/portales/munimadrid/es/Inicio/El-Ayuntamiento/Publicaciones/Listado-de-Publicaciones/Contratos-de-Recogida-de-Residuos/?vgnextchannel=f1aebadb6b997010VgnVCM100000dc0ca8c0RCRD&vgnextfmt=default&vgnextoid=429f71adf3d56910VgnVCM2000001f4a900aRCRD https://contratos.gobierto.es/licitaciones/5108890 https://licitalens.com/empresa/A08602815 https://www.madrid.es/portales/munimadrid/es/Inicio/Medio-ambiente/Recogida-de-residuos/Actividades-y-eventos/Contrato-de-servicio-de-actividades-de-sensibilizacion/?vgnextchannel=d04bbb21278fe410VgnVCM1000000b205a0aRCRD&vgnextfmt=default&vgnextoid=1d1f49ec5caef910VgnVCM200000f921e388RCRD | T43: REL-0042 | U43: 300/2026/00024|Sin lotes | V43: =IF(AND(SUM(IF('Consulta de contratos'!$K$1="",0,1),IF('Consulta de contratos'!$K$2="",0,1),IF('Consulta de contratos'!$K$3="",0,1),IF('Consulta de contratos'!$K$4="",0,1),IF('Consulta de contratos'!$K$5="",0,1),IF('Consulta de contratos'!$K$6="",0,1))>0,OR('Consulta de contratos'!$K$1="",A43='Consulta de contratos'!$K$1),OR('Consulta de contratos'!$K$2="",I43='Consulta de contratos'!$K$2),OR('Consulta de contratos'!$K$3="",C43='Consulta de contratos'!$K$3),OR('Consulta de contratos'!$K$4="",D43='Consulta de contratos'!$K$4),OR('Consulta de contratos'!$K$5="",E43='Consulta de contratos'!$K$5),OR('Consulta de contratos'!$K$6="",IFERROR(ISNUMBER(SEARCH("|"&'Consulta de contratos'!$K$6&"|",AF43)),FALSE))),1,0) -> 0 | W43: =IF(V43=1,SUM($V$2:V43),0) -> 0 | X43: ADJUDICACIÓN PUBLICADA EN DATOS PLACSP · FORMALIZACIÓN POR CONTRASTAR | Y43: CLECE | Z43: Grupo de empresa contrastado en fuente corporativa: https://clece.es/es/listado-clece-filiales/ | AA43: 16/10/2026 | AF43: |CLECE|
A44: Fuencarral-El Pardo | B44: Residuos | C44: Área de Gobierno de Urbanismo, Medio Ambiente y Movilidad | D44: Dirección General de Servicios de Limpieza y Residuos | E44: Subdirección General de Recogida de Residuos | F44: Contenerización, recogida y transporte de residuos | G44: 131/2021/06296 | H44: 1 | I44: FCC MEDIO AMBIENTE, SA | J44: Recogida y transporte habitual | K44: Zona territorial del lote | L44: 44866 | M44: 47057 | N44: Víctor Manuel Sarabia Herrero | O44: No acreditado | P44: 010 / 914 800 010 (atencion municipal, no gestor directo) | Q44: Lote 1: eventos eje Castellana-Prado-Recoletos | R44: Concesión vigente; adjudicataria y fin 31/10/2028 contrastados en registro de concesiones municipal (15/10/2026). | FECHAS REVISADAS: Inicio 01/11/2022 acreditado por formalización de los cuatro lotes. | CONTROL DOCUMENTAL 21/10/2026: Adjudicación y fin publicados. Los cuatro lotes se pueden contrastar en el registro municipal de concesiones. Fin publicado: 31/10/2028. No generalizar ámbito de cada lote. [Base de evidencia: Portal municipal / resolución o resultado oficial consultado] | CONTRASTE ADICIONAL 21/10/2026: FUENTE MUNICIPAL: la concesión registra adjudicación diferenciada en los 4 lotes (FCC, UTE VAO, UTE Sur, CONTENUR) y fin contractual 31/10/2028. | S44: https://contratacion.madrid.es/concesiones/ https://contrataciondelestado.es/FileSystem/servlet/GetDocumentByIdServlet?DocumentIdParam=I52CDqtLbsdgHyWk6Tjc%2BH2t2QGKU1Ro9lcaZmb7V5J4T4CLRYtO18fD2fcADXQg90aL83OqQbUADSXvNu02Vt6kOzxNccJdTRf8umMgorI%3D&cifrado=QUC1GjXXSiLkydRHJBmbpw%3D%3D | T44: REL-0043 | U44: 131/2021/06296|1 | V44: =IF(AND(SUM(IF('Consulta de contratos'!$K$1="",0,1),IF('Consulta de contratos'!$K$2="",0,1),IF('Consulta de contratos'!$K$3="",0,1),IF('Consulta de contratos'!$K$4="",0,1),IF('Consulta de contratos'!$K$5="",0,1),IF('Consulta de contratos'!$K$6="",0,1))>0,OR('Consulta de contratos'!$K$1="",A44='Consulta de contratos'!$K$1),OR('Consulta de contratos'!$K$2="",I44='Consulta de contratos'!$K$2),OR('Consulta de contratos'!$K$3="",C44='Consulta de contratos'!$K$3),OR('Consulta de contratos'!$K$4="",D44='Consulta de contratos'!$K$4),OR('Consulta de contratos'!$K$5="",E44='Consulta de contratos'!$K$5),OR('Consulta de contratos'!$K$6="",IFERROR(ISNUMBER(SEARCH("|"&'Consulta de contratos'!$K$6&"|",AF44)),FALSE))),1,0) -> 0 | W44: =IF(V44=1,SUM($V$2:V44),0) -> 0 | X44: FIN REGISTRADO POSTERIOR · EJECUCIÓN A CONFIRMAR | Y44: FCC | Z44: Grupo/familia pendiente de confirmar legalmente | AA44: 16/10/2026 | AF44: |FCC|
A45: Fuencarral-El Pardo | B45: Residuos | C45: Área de Gobierno de Urbanismo, Medio Ambiente y Movilidad | D45: Dirección General de Servicios de Limpieza y Residuos | E45: Subdirección General de Recogida de Residuos | F45: Contenerización, recogida y transporte de residuos | G45: 131/2021/06296 | H45: 4 | I45: CONTENUR SL | J45: Suministro, mantenimiento y limpieza de contenedores | K45: Toda la ciudad | L45: 44866 | M45: 47057 | N45: Víctor Manuel Sarabia Herrero | O45: No acreditado | P45: 010 / 914 800 010 (atencion municipal, no gestor directo) | Q45: No es vaciado ni recogida habitual | R45: Concesión vigente; adjudicataria y fin 31/10/2028 contrastados en registro de concesiones municipal (15/10/2026). | FECHAS REVISADAS: Inicio 01/11/2022 acreditado por formalización de los cuatro lotes. | CONTROL DOCUMENTAL 21/10/2026: Adjudicación y fin publicados. Los cuatro lotes se pueden contrastar en el registro municipal de concesiones. Fin publicado: 31/10/2028. No generalizar ámbito de cada lote. [Base de evidencia: Portal municipal / resolución o resultado oficial consultado] | CONTRASTE ADICIONAL 21/10/2026: FUENTE MUNICIPAL: la concesión registra adjudicación diferenciada en los 4 lotes (FCC, UTE VAO, UTE Sur, CONTENUR) y fin contractual 31/10/2028. | S45: https://contratacion.madrid.es/concesiones/ https://contrataciondelestado.es/FileSystem/servlet/GetDocumentByIdServlet?DocumentIdParam=I52CDqtLbsdgHyWk6Tjc%2BH2t2QGKU1Ro9lcaZmb7V5J4T4CLRYtO18fD2fcADXQg90aL83OqQbUADSXvNu02Vt6kOzxNccJdTRf8umMgorI%3D&cifrado=QUC1GjXXSiLkydRHJBmbpw%3D%3D | T45: REL-0044 | U45: 131/2021/06296|4 | V45: =IF(AND(SUM(IF('Consulta de contratos'!$K$1="",0,1),IF('Consulta de contratos'!$K$2="",0,1),IF('Consulta de contratos'!$K$3="",0,1),IF('Consulta de contratos'!$K$4="",0,1),IF('Consulta de contratos'!$K$5="",0,1),IF('Consulta de contratos'!$K$6="",0,1))>0,OR('Consulta de contratos'!$K$1="",A45='Consulta de contratos'!$K$1),OR('Consulta de contratos'!$K$2="",I45='Consulta de contratos'!$K$2),OR('Consulta de contratos'!$K$3="",C45='Consulta de contratos'!$K$3),OR('Consulta de contratos'!$K$4="",D45='Consulta de contratos'!$K$4),OR('Consulta de contratos'!$K$5="",E45='Consulta de contratos'!$K$5),OR('Consulta de contratos'!$K$6="",IFERROR(ISNUMBER(SEARCH("|"&'Consulta de contratos'!$K$6&"|",AF45)),FALSE))),1,0) -> 0 | W45: =IF(V45=1,SUM($V$2:V45),0) -> 0 | X45: FIN REGISTRADO POSTERIOR · EJECUCIÓN A CONFIRMAR | Y45: CONTENUR SL | Z45: Agrupación de consulta por nombre de adjudicataria; no consta matriz contrastada. | AA45: 16/10/2026 | AF45: |CONTENUR SL|
A46: Fuencarral-El Pardo | B46: Residuos | C46: Área de Gobierno de Urbanismo, Medio Ambiente y Movilidad | D46: Dirección General de Servicios de Limpieza y Residuos | E46: Subdirección General de Recogida de Residuos | F46: Contenerización, recogida y transporte de residuos | G46: 131/2021/06296 | H46: 3 | I46: UTE 2022 Recogida Madrid Sur | J46: Recogida de pilas y baterias usadas | K46: Toda la ciudad | L46: 44866 | M46: 47057 | N46: Víctor Manuel Sarabia Herrero | O46: No acreditado | P46: 010 / 914 800 010 (atencion municipal, no gestor directo) | Q46: Tarea especial del lote 3 fuera de su zona habitual | R46: Concesión vigente; adjudicataria y fin 31/10/2028 contrastados en registro de concesiones municipal (15/10/2026). | FECHAS REVISADAS: Inicio 01/11/2022 acreditado por formalización de los cuatro lotes. | CONTROL DOCUMENTAL 21/10/2026: Adjudicación y fin publicados. Los cuatro lotes se pueden contrastar en el registro municipal de concesiones. Fin publicado: 31/10/2028. No generalizar ámbito de cada lote. [Base de evidencia: Portal municipal / resolución o resultado oficial consultado] | CONTRASTE ADICIONAL 21/10/2026: FUENTE MUNICIPAL: la concesión registra adjudicación diferenciada en los 4 lotes (FCC, UTE VAO, UTE Sur, CONTENUR) y fin contractual 31/10/2028. | S46: https://contratacion.madrid.es/concesiones/ https://contrataciondelestado.es/FileSystem/servlet/GetDocumentByIdServlet?DocumentIdParam=I52CDqtLbsdgHyWk6Tjc%2BH2t2QGKU1Ro9lcaZmb7V5J4T4CLRYtO18fD2fcADXQg90aL83OqQbUADSXvNu02Vt6kOzxNccJdTRf8umMgorI%3D&cifrado=QUC1GjXXSiLkydRHJBmbpw%3D%3D | T46: REL-0045 | U46: 131/2021/06296|3 | V46: =IF(AND(SUM(IF('Consulta de contratos'!$K$1="",0,1),IF('Consulta de contratos'!$K$2="",0,1),IF('Consulta de contratos'!$K$3="",0,1),IF('Consulta de contratos'!$K$4="",0,1),IF('Consulta de contratos'!$K$5="",0,1),IF('Consulta de contratos'!$K$6="",0,1))>0,OR('Consulta de contratos'!$K$1="",A46='Consulta de contratos'!$K$1),OR('Consulta de contratos'!$K$2="",I46='Consulta de contratos'!$K$2),OR('Consulta de contratos'!$K$3="",C46='Consulta de contratos'!$K$3),OR('Consulta de contratos'!$K$4="",D46='Consulta de contratos'!$K$4),OR('Consulta de contratos'!$K$5="",E46='Consulta de contratos'!$K$5),OR('Consulta de contratos'!$K$6="",IFERROR(ISNUMBER(SEARCH("|"&'Consulta de contratos'!$K$6&"|",AF46)),FALSE))),1,0) -> 0 | W46: =IF(V46=1,SUM($V$2:V46),0) -> 0 | X46: FIN REGISTRADO POSTERIOR · EJECUCIÓN A CONFIRMAR | Y46: PREZERO | URBASER | Z46: UTE: vínculo comercial; no implica propiedad | AA46: 16/10/2026 | AF46: |PREZERO|URBASER|
A47: Fuencarral-El Pardo | B47: Residuos | C47: Área de Gobierno de Urbanismo, Medio Ambiente y Movilidad | D47: Dirección General de Servicios de Limpieza y Residuos | E47: Subdirección General de Recogida de Residuos | F47: Asistencia técnica para el mantenimiento, ampliación y mejora continua del sistema de gestión de la información de limpieza urbana, recogida de residuos y equipamientos urbanos | G47: 300/2025/00411 | H47: Sin lotes | I47: APORTA PLATAFORMA COOPERATIVA SCCL | J47: Mantenimiento y mejora del sistema de informacion | K47: Ambito municipal; no contrato propio del distrito | M47: 46850 | N47: Víctor Manuel Sarabia Herrero | O47: No acreditado | P47: 010 / 914 800 010 (atencion municipal, no gestor directo) | R47: Adjudicado 27/01/2026 y formalizado 08/04/2026. Fin publicado 07/04/2028 (posible prórroga 12 meses). Inicio de prestación no acreditado. | FECHAS SIN ACREDITAR: Formalización 08/04/2026 y fin en agregador 07/04/2028; no consta fecha independiente de inicio de prestación. La formalización no se convierte en inicio automático. | FUENTES REVISADAS 21/10/2026: Ayuntamiento publica objeto y pliegos; registro TED del contrato identifica formalización el 08/04/2026 y adjudicataria Aporta. No equivale a fecha de inicio operativo. | CONTROL DOCUMENTAL 21/10/2026: Adjudicataria identificada. APORTA PLATAFORMA COOPERATIVA figura en la base y en fichas de licitación; comprobar firma e hitos en el expediente. [Base de evidencia: Datos confrontados con referencias aportadas; no hay resolución individual corroborada] | CONTRASTE ADICIONAL 21/10/2026: ADJUDICACIÓN: APORTA PLATAFORMA COOPERATIVA SCCL, resolución de 27/01/2026, contrastada con publicación de licitación. | S47: https://contratos.gobierto.es/adjudicatarios/aporta-plataforma-cooperativa-sccl?locale=es https://www.madrid.es/portales/munimadrid/es/Inicio/Medio-ambiente/Limpieza-urbana/Contrato-de-servicio-de-asistencia-tecnica/?vgnextchannel=ddd2a694fde40910VgnVCM2000001f4a900aRCRD&vgnextfmt=default&vgnextoid=7c07475398a4e910VgnVCM200000f921e388RCRD https://contratos.gobierto.es/licitaciones/4668721?locale=es | T47: REL-0046 | U47: 300/2025/00411|Sin lotes | V47: =IF(AND(SUM(IF('Consulta de contratos'!$K$1="",0,1),IF('Consulta de contratos'!$K$2="",0,1),IF('Consulta de contratos'!$K$3="",0,1),IF('Consulta de contratos'!$K$4="",0,1),IF('Consulta de contratos'!$K$5="",0,1),IF('Consulta de contratos'!$K$6="",0,1))>0,OR('Consulta de contratos'!$K$1="",A47='Consulta de contratos'!$K$1),OR('Consulta de contratos'!$K$2="",I47='Consulta de contratos'!$K$2),OR('Consulta de contratos'!$K$3="",C47='Consulta de contratos'!$K$3),OR('Consulta de contratos'!$K$4="",D47='Consulta de contratos'!$K$4),OR('Consulta de contratos'!$K$5="",E47='Consulta de contratos'!$K$5),OR('Consulta de contratos'!$K$6="",IFERROR(ISNUMBER(SEARCH("|"&'Consulta de contratos'!$K$6&"|",AF47)),FALSE))),1,0) -> 0 | W47: =IF(V47=1,SUM($V$2:V47),0) -> 0 | X47: FIN REGISTRADO POSTERIOR · EJECUCIÓN A CONFIRMAR | Y47: APORTA PLATAFORMA COOPERATIVA SCCL | Z47: Agrupación de consulta por nombre de adjudicataria; no consta matriz contrastada. | AA47: 16/10/2026 | AF47: |APORTA PLATAFORMA COOPERATIVA SCCL|
A48: Fuencarral-El Pardo | B48: Residuos | C48: Área de Gobierno de Urbanismo, Medio Ambiente y Movilidad | D48: Dirección General de Servicios de Limpieza y Residuos | E48: Subdirección General de Recogida de Residuos | F48: Gestión del servicio de explotación de puntos limpios, centros de reutilización de residuos y saneamiento de viviendas | G48: 300/2023/00593 | H48: Sin lotes | I48: PREZERO ESPAÑA SAU | J48: Gestión de puntos limpios y centros de reutilización; saneamientos por requerimiento. | K48: Ambito municipal; ubicaciones concretas no incluidas | L48: 45622 | M48: 47447 | N48: Víctor Manuel Sarabia Herrero | O48: No acreditado | P48: 010 / 914 800 010 (atencion municipal, no gestor directo) | Q48: Saneamiento no es limpieza domestica ordinaria | R48: Vigente según Ayuntamiento; adjudicataria PREZERO acreditada (24/10/2024). Inicio contractual y fecha fin exacta sin acreditar. | FECHAS REVISADAS: Vigencia: 26/11/2024–25/11/2029. Inicio oficial; fin ordinario calculado por cinco años contractuales sin prórroga. | CONTROL DOCUMENTAL 21/10/2026: Adjudicataria identificada. PREZERO ESPAÑA figura adjudicataria de puntos limpios. El contrato es municipal; no son 21 concesiones independientes. [Base de evidencia: Datos confrontados con referencias aportadas; no hay resolución individual corroborada] | CONTRASTE ADICIONAL 21/10/2026: ADJUDICACIÓN: PREZERO ESPAÑA SA, 24/10/2024. El Ayuntamiento dispone de ficha oficial del contrato; compruébese formalización para fechas exactas. | S48: https://contratos.gobierto.es/licitaciones/4336157 https://contrataciondelestado.es/FileSystem/servlet/GetDocumentByIdServlet?DocumentIdParam=DX1ZAvwzaIUStPoibgXBVeTGIJOgffe86rdC19dt4dT5lTaSGg5Vq9cT4fT6Jv75jYAipcFv6g1zHenSv4lINo4IQyA7QON0MW%2BNRBCDa6cZyAJWGsSt0OzTSTyw9JAs&cifrado=QUC1GjXXSiLkydRHJBmbpw%3D%3D https://www.madrid.es/UnidadesDescentralizadas/LimpiezaUrbanaYResiduos/CONTRATOS_DG/CONTRATO-RES_PuntosLimpios/DocumentoPliegos_ContratoPuntosLimpios.pdf https://www.madrid.es/portales/munimadrid/es/Inicio/Medio-ambiente/Recogida-de-residuos/Contrato-de-servicios-de-explotacion-de-puntos-limpios-centros-de-reutilizacion-de-residuos-y-saneamiento-de-viviendas-en-la-ciudad-de-Madrid/?vgnextchannel=f81379ed268fe410VgnVCM1000000b205a0aRCRD&vgnextfmt=default&vgnextoid=8177150aabc46710VgnVCM2000001f4a900aRCRD | T48: REL-0047 | U48: 300/2023/00593|Sin lotes | V48: =IF(AND(SUM(IF('Consulta de contratos'!$K$1="",0,1),IF('Consulta de contratos'!$K$2="",0,1),IF('Consulta de contratos'!$K$3="",0,1),IF('Consulta de contratos'!$K$4="",0,1),IF('Consulta de contratos'!$K$5="",0,1),IF('Consulta de contratos'!$K$6="",0,1))>0,OR('Consulta de contratos'!$K$1="",A48='Consulta de contratos'!$K$1),OR('Consulta de contratos'!$K$2="",I48='Consulta de contratos'!$K$2),OR('Consulta de contratos'!$K$3="",C48='Consulta de contratos'!$K$3),OR('Consulta de contratos'!$K$4="",D48='Consulta de contratos'!$K$4),OR('Consulta de contratos'!$K$5="",E48='Consulta de contratos'!$K$5),OR('Consulta de contratos'!$K$6="",IFERROR(ISNUMBER(SEARCH("|"&'Consulta de contratos'!$K$6&"|",AF48)),FALSE))),1,0) -> 0 | W48: =IF(V48=1,SUM($V$2:V48),0) -> 0 | X48: FIN REGISTRADO POSTERIOR · EJECUCIÓN A CONFIRMAR | Y48: PREZERO | Z48: Grupo/familia pendiente de confirmar legalmente | AA48: 16/10/2026 | AF48: |PREZERO|
A49: Fuencarral-El Pardo | B49: Residuos | C49: Área de Gobierno de Urbanismo, Medio Ambiente y Movilidad | D49: Dirección General de Servicios de Limpieza y Residuos | E49: Subdirección General de Recogida de Residuos | F49: Programa de actividades de sensibilización sobre separación de residuos y limpieza del espacio público | G49: 300/2026/00024 | H49: Sin lotes | I49: TALHER, S.A. | J49: Actividades educativas y de sensibilizacion | K49: Ambito municipal; no acredita actividad en cada distrito | N49: Víctor Manuel Sarabia Herrero | O49: No acreditado | P49: 010 / 914 800 010 (atencion municipal, no gestor directo) | Q49: Adjudicación publicada en datos de PLACSP; formalización e inicio efectivos sin contrastar. | ATENCIÓN · CONTRASTE 23/10/2026: el portal municipal incluye este expediente entre los contratos en vigor, mientras un agregador lo presenta como «Desistida». La resolución de adjudicación, la formalización y el inicio efectivo requieren comprobación directa. | R49: ADJUDICACIÓN 30/09/2026 A TALHER, S.A. (1.432.107 € sin IVA) recogida en LicitaLens a partir de PLACSP. Pendiente de verificar resolución y fecha de formalización en documento oficial; no certificar inicio efectivo. | CONTROL DOCUMENTAL 21/10/2026: Adjudicación localizada. Adjudicación a TALHER encontrada en plataformas que reproducen PLACSP; la resolución y la fecha de ejecución requieren lectura directa. [Base de evidencia: Ficha individual de publicación / agregador contrastada] | CONTRASTE DE FUENTES 23/10/2026: ficha municipal lo relaciona entre contratos en vigor; Gobierto muestra estado «Desistida», pese a reflejar datos de adjudicación del 30/09/2026. No tratar la formalización, la entrada en servicio ni la vigencia como acreditadas sin resolución. | S49: https://www.madrid.es/portales/munimadrid/es/Inicio/El-Ayuntamiento/Publicaciones/Listado-de-Publicaciones/Contratos-de-Recogida-de-Residuos/?vgnextchannel=f1aebadb6b997010VgnVCM100000dc0ca8c0RCRD&vgnextfmt=default&vgnextoid=429f71adf3d56910VgnVCM2000001f4a900aRCRD https://contratos.gobierto.es/licitaciones/5108890 https://licitalens.com/empresa/A08602815 https://www.madrid.es/portales/munimadrid/es/Inicio/Medio-ambiente/Recogida-de-residuos/Actividades-y-eventos/Contrato-de-servicio-de-actividades-de-sensibilizacion/?vgnextchannel=d04bbb21278fe410VgnVCM1000000b205a0aRCRD&vgnextfmt=default&vgnextoid=1d1f49ec5caef910VgnVCM200000f921e388RCRD | T49: REL-0048 | U49: 300/2026/00024|Sin lotes | V49: =IF(AND(SUM(IF('Consulta de contratos'!$K$1="",0,1),IF('Consulta de contratos'!$K$2="",0,1),IF('Consulta de contratos'!$K$3="",0,1),IF('Consulta de contratos'!$K$4="",0,1),IF('Consulta de contratos'!$K$5="",0,1),IF('Consulta de contratos'!$K$6="",0,1))>0,OR('Consulta de contratos'!$K$1="",A49='Consulta de contratos'!$K$1),OR('Consulta de contratos'!$K$2="",I49='Consulta de contratos'!$K$2),OR('Consulta de contratos'!$K$3="",C49='Consulta de contratos'!$K$3),OR('Consulta de contratos'!$K$4="",D49='Consulta de contratos'!$K$4),OR('Consulta de contratos'!$K$5="",E49='Consulta de contratos'!$K$5),OR('Consulta de contratos'!$K$6="",IFERROR(ISNUMBER(SEARCH("|"&'Consulta de contratos'!$K$6&"|",AF49)),FALSE))),1,0) -> 0 | W49: =IF(V49=1,SUM($V$2:V49),0) -> 0 | X49: ADJUDICACIÓN PUBLICADA EN DATOS PLACSP · FORMALIZACIÓN POR CONTRASTAR | Y49: CLECE | Z49: Grupo de empresa contrastado en fuente corporativa: https://clece.es/es/listado-clece-filiales/ | AA49: 16/10/2026 | AF49: |CLECE|
A50: Moncloa-Aravaca | B50: Residuos | C50: Área de Gobierno de Urbanismo, Medio Ambiente y Movilidad | D50: Dirección General de Servicios de Limpieza y Residuos | E50: Subdirección General de Recogida de Residuos | F50: Contenerización, recogida y transporte de residuos | G50: 131/2021/06296 | H50: 1 | I50: FCC MEDIO AMBIENTE, SA | J50: Recogida y transporte habitual | K50: Zona territorial del lote | L50: 44866 | M50: 47057 | N50: Víctor Manuel Sarabia Herrero | O50: No acreditado | P50: 010 / 914 800 010 (atencion municipal, no gestor directo) | Q50: Lote 1: eventos eje Castellana-Prado-Recoletos | R50: Concesión vigente; adjudicataria y fin 31/10/2028 contrastados en registro de concesiones municipal (15/10/2026). | FECHAS REVISADAS: Inicio 01/11/2022 acreditado por formalización de los cuatro lotes. | CONTROL DOCUMENTAL 21/10/2026: Adjudicación y fin publicados. Los cuatro lotes se pueden contrastar en el registro municipal de concesiones. Fin publicado: 31/10/2028. No generalizar ámbito de cada lote. [Base de evidencia: Portal municipal / resolución o resultado oficial consultado] | CONTRASTE ADICIONAL 21/10/2026: FUENTE MUNICIPAL: la concesión registra adjudicación diferenciada en los 4 lotes (FCC, UTE VAO, UTE Sur, CONTENUR) y fin contractual 31/10/2028. | S50: https://contratacion.madrid.es/concesiones/ https://contrataciondelestado.es/FileSystem/servlet/GetDocumentByIdServlet?DocumentIdParam=I52CDqtLbsdgHyWk6Tjc%2BH2t2QGKU1Ro9lcaZmb7V5J4T4CLRYtO18fD2fcADXQg90aL83OqQbUADSXvNu02Vt6kOzxNccJdTRf8umMgorI%3D&cifrado=QUC1GjXXSiLkydRHJBmbpw%3D%3D | T50: REL-0049 | U50: 131/2021/06296|1 | V50: =IF(AND(SUM(IF('Consulta de contratos'!$K$1="",0,1),IF('Consulta de contratos'!$K$2="",0,1),IF('Consulta de contratos'!$K$3="",0,1),IF('Consulta de contratos'!$K$4="",0,1),IF('Consulta de contratos'!$K$5="",0,1),IF('Consulta de contratos'!$K$6="",0,1))>0,OR('Consulta de contratos'!$K$1="",A50='Consulta de contratos'!$K$1),OR('Consulta de contratos'!$K$2="",I50='Consulta de contratos'!$K$2),OR('Consulta de contratos'!$K$3="",C50='Consulta de contratos'!$K$3),OR('Consulta de contratos'!$K$4="",D50='Consulta de contratos'!$K$4),OR('Consulta de contratos'!$K$5="",E50='Consulta de contratos'!$K$5),OR('Consulta de contratos'!$K$6="",IFERROR(ISNUMBER(SEARCH("|"&'Consulta de contratos'!$K$6&"|",AF50)),FALSE))),1,0) -> 0 | W50: =IF(V50=1,SUM($V$2:V50),0) -> 0 | X50: FIN REGISTRADO POSTERIOR · EJECUCIÓN A CONFIRMAR | Y50: FCC | Z50: Grupo/familia pendiente de confirmar legalmente | AA50: 16/10/2026 | AF50: |FCC|
A51: Moncloa-Aravaca | B51: Residuos | C51: Área de Gobierno de Urbanismo, Medio Ambiente y Movilidad | D51: Dirección General de Servicios de Limpieza y Residuos | E51: Subdirección General de Recogida de Residuos | F51: Contenerización, recogida y transporte de residuos | G51: 131/2021/06296 | H51: 4 | I51: CONTENUR SL | J51: Suministro, mantenimiento y limpieza de contenedores | K51: Toda la ciudad | L51: 44866 | M51: 47057 | N51: Víctor Manuel Sarabia Herrero | O51: No acreditado | P51: 010 / 914 800 010 (atencion municipal, no gestor directo) | Q51: No es vaciado ni recogida habitual | R51: Concesión vigente; adjudicataria y fin 31/10/2028 contrastados en registro de concesiones municipal (15/10/2026). | FECHAS REVISADAS: Inicio 01/11/2022 acreditado por formalización de los cuatro lotes. | CONTROL DOCUMENTAL 21/10/2026: Adjudicación y fin publicados. Los cuatro lotes se pueden contrastar en el registro municipal de concesiones. Fin publicado: 31/10/2028. No generalizar ámbito de cada lote. [Base de evidencia: Portal municipal / resolución o resultado oficial consultado] | CONTRASTE ADICIONAL 21/10/2026: FUENTE MUNICIPAL: la concesión registra adjudicación diferenciada en los 4 lotes (FCC, UTE VAO, UTE Sur, CONTENUR) y fin contractual 31/10/2028. | S51: https://contratacion.madrid.es/concesiones/ https://contrataciondelestado.es/FileSystem/servlet/GetDocumentByIdServlet?DocumentIdParam=I52CDqtLbsdgHyWk6Tjc%2BH2t2QGKU1Ro9lcaZmb7V5J4T4CLRYtO18fD2fcADXQg90aL83OqQbUADSXvNu02Vt6kOzxNccJdTRf8umMgorI%3D&cifrado=QUC1GjXXSiLkydRHJBmbpw%3D%3D | T51: REL-0050 | U51: 131/2021/06296|4 | V51: =IF(AND(SUM(IF('Consulta de contratos'!$K$1="",0,1),IF('Consulta de contratos'!$K$2="",0,1),IF('Consulta de contratos'!$K$3="",0,1),IF('Consulta de contratos'!$K$4="",0,1),IF('Consulta de contratos'!$K$5="",0,1),IF('Consulta de contratos'!$K$6="",0,1))>0,OR('Consulta de contratos'!$K$1="",A51='Consulta de contratos'!$K$1),OR('Consulta de contratos'!$K$2="",I51='Consulta de contratos'!$K$2),OR('Consulta de contratos'!$K$3="",C51='Consulta de contratos'!$K$3),OR('Consulta de contratos'!$K$4="",D51='Consulta de contratos'!$K$4),OR('Consulta de contratos'!$K$5="",E51='Consulta de contratos'!$K$5),OR('Consulta de contratos'!$K$6="",IFERROR(ISNUMBER(SEARCH("|"&'Consulta de contratos'!$K$6&"|",AF51)),FALSE))),1,0) -> 0 | W51: =IF(V51=1,SUM($V$2:V51),0) -> 0 | X51: FIN REGISTRADO POSTERIOR · EJECUCIÓN A CONFIRMAR | Y51: CONTENUR SL | Z51: Agrupación de consulta por nombre de adjudicataria; no consta matriz contrastada. | AA51: 16/10/2026 | AF51: |CONTENUR SL|
A52: Moncloa-Aravaca | B52: Residuos | C52: Área de Gobierno de Urbanismo, Medio Ambiente y Movilidad | D52: Dirección General de Servicios de Limpieza y Residuos | E52: Subdirección General de Recogida de Residuos | F52: Contenerización, recogida y transporte de residuos | G52: 131/2021/06296 | H52: 3 | I52: UTE 2022 Recogida Madrid Sur | J52: Recogida de pilas y baterias usadas | K52: Toda la ciudad | L52: 44866 | M52: 47057 | N52: Víctor Manuel Sarabia Herrero | O52: No acreditado | P52: 010 / 914 800 010 (atencion municipal, no gestor directo) | Q52: Tarea especial del lote 3 fuera de su zona habitual | R52: Concesión vigente; adjudicataria y fin 31/10/2028 contrastados en registro de concesiones municipal (15/10/2026). | FECHAS REVISADAS: Inicio 01/11/2022 acreditado por formalización de los cuatro lotes. | CONTROL DOCUMENTAL 21/10/2026: Adjudicación y fin publicados. Los cuatro lotes se pueden contrastar en el registro municipal de concesiones. Fin publicado: 31/10/2028. No generalizar ámbito de cada lote. [Base de evidencia: Portal municipal / resolución o resultado oficial consultado] | CONTRASTE ADICIONAL 21/10/2026: FUENTE MUNICIPAL: la concesión registra adjudicación diferenciada en los 4 lotes (FCC, UTE VAO, UTE Sur, CONTENUR) y fin contractual 31/10/2028. | S52: https://contratacion.madrid.es/concesiones/ https://contrataciondelestado.es/FileSystem/servlet/GetDocumentByIdServlet?DocumentIdParam=I52CDqtLbsdgHyWk6Tjc%2BH2t2QGKU1Ro9lcaZmb7V5J4T4CLRYtO18fD2fcADXQg90aL83OqQbUADSXvNu02Vt6kOzxNccJdTRf8umMgorI%3D&cifrado=QUC1GjXXSiLkydRHJBmbpw%3D%3D | T52: REL-0051 | U52: 131/2021/06296|3 | V52: =IF(AND(SUM(IF('Consulta de contratos'!$K$1="",0,1),IF('Consulta de contratos'!$K$2="",0,1),IF('Consulta de contratos'!$K$3="",0,1),IF('Consulta de contratos'!$K$4="",0,1),IF('Consulta de contratos'!$K$5="",0,1),IF('Consulta de contratos'!$K$6="",0,1))>0,OR('Consulta de contratos'!$K$1="",A52='Consulta de contratos'!$K$1),OR('Consulta de contratos'!$K$2="",I52='Consulta de contratos'!$K$2),OR('Consulta de contratos'!$K$3="",C52='Consulta de contratos'!$K$3),OR('Consulta de contratos'!$K$4="",D52='Consulta de contratos'!$K$4),OR('Consulta de contratos'!$K$5="",E52='Consulta de contratos'!$K$5),OR('Consulta de contratos'!$K$6="",IFERROR(ISNUMBER(SEARCH("|"&'Consulta de contratos'!$K$6&"|",AF52)),FALSE))),1,0) -> 0 | W52: =IF(V52=1,SUM($V$2:V52),0) -> 0 | X52: FIN REGISTRADO POSTERIOR · EJECUCIÓN A CONFIRMAR | Y52: PREZERO | URBASER | Z52: UTE: vínculo comercial; no implica propiedad | AA52: 16/10/2026 | AF52: |PREZERO|URBASER|
A53: Moncloa-Aravaca | B53: Residuos | C53: Área de Gobierno de Urbanismo, Medio Ambiente y Movilidad | D53: Dirección General de Servicios de Limpieza y Residuos | E53: Subdirección General de Recogida de Residuos | F53: Asistencia técnica para el mantenimiento, ampliación y mejora continua del sistema de gestión de la información de limpieza urbana, recogida de residuos y equipamientos urbanos | G53: 300/2025/00411 | H53: Sin lotes | I53: APORTA PLATAFORMA COOPERATIVA SCCL | J53: Mantenimiento y mejora del sistema de informacion | K53: Ambito municipal; no contrato propio del distrito | M53: 46850 | N53: Víctor Manuel Sarabia Herrero | O53: No acreditado | P53: 010 / 914 800 010 (atencion municipal, no gestor directo) | R53: Adjudicado 27/01/2026 y formalizado 08/04/2026. Fin publicado 07/04/2028 (posible prórroga 12 meses). Inicio de prestación no acreditado. | FECHAS SIN ACREDITAR: Formalización 08/04/2026 y fin en agregador 07/04/2028; no consta fecha independiente de inicio de prestación. La formalización no se convierte en inicio automático. | FUENTES REVISADAS 21/10/2026: Ayuntamiento publica objeto y pliegos; registro TED del contrato identifica formalización el 08/04/2026 y adjudicataria Aporta. No equivale a fecha de inicio operativo. | CONTROL DOCUMENTAL 21/10/2026: Adjudicataria identificada. APORTA PLATAFORMA COOPERATIVA figura en la base y en fichas de licitación; comprobar firma e hitos en el expediente. [Base de evidencia: Datos confrontados con referencias aportadas; no hay resolución individual corroborada] | CONTRASTE ADICIONAL 21/10/2026: ADJUDICACIÓN: APORTA PLATAFORMA COOPERATIVA SCCL, resolución de 27/01/2026, contrastada con publicación de licitación. | S53: https://contratos.gobierto.es/adjudicatarios/aporta-plataforma-cooperativa-sccl?locale=es https://www.madrid.es/portales/munimadrid/es/Inicio/Medio-ambiente/Limpieza-urbana/Contrato-de-servicio-de-asistencia-tecnica/?vgnextchannel=ddd2a694fde40910VgnVCM2000001f4a900aRCRD&vgnextfmt=default&vgnextoid=7c07475398a4e910VgnVCM200000f921e388RCRD https://contratos.gobierto.es/licitaciones/4668721?locale=es | T53: REL-0052 | U53: 300/2025/00411|Sin lotes | V53: =IF(AND(SUM(IF('Consulta de contratos'!$K$1="",0,1),IF('Consulta de contratos'!$K$2="",0,1),IF('Consulta de contratos'!$K$3="",0,1),IF('Consulta de contratos'!$K$4="",0,1),IF('Consulta de contratos'!$K$5="",0,1),IF('Consulta de contratos'!$K$6="",0,1))>0,OR('Consulta de contratos'!$K$1="",A53='Consulta de contratos'!$K$1),OR('Consulta de contratos'!$K$2="",I53='Consulta de contratos'!$K$2),OR('Consulta de contratos'!$K$3="",C53='Consulta de contratos'!$K$3),OR('Consulta de contratos'!$K$4="",D53='Consulta de contratos'!$K$4),OR('Consulta de contratos'!$K$5="",E53='Consulta de contratos'!$K$5),OR('Consulta de contratos'!$K$6="",IFERROR(ISNUMBER(SEARCH("|"&'Consulta de contratos'!$K$6&"|",AF53)),FALSE))),1,0) -> 0 | W53: =IF(V53=1,SUM($V$2:V53),0) -> 0 | X53: FIN REGISTRADO POSTERIOR · EJECUCIÓN A CONFIRMAR | Y53: APORTA PLATAFORMA COOPERATIVA SCCL | Z53: Agrupación de consulta por nombre de adjudicataria; no consta matriz contrastada. | AA53: 16/10/2026 | AF53: |APORTA PLATAFORMA COOPERATIVA SCCL|
A54: Moncloa-Aravaca | B54: Residuos | C54: Área de Gobierno de Urbanismo, Medio Ambiente y Movilidad | D54: Dirección General de Servicios de Limpieza y Residuos | E54: Subdirección General de Recogida de Residuos | F54: Gestión del servicio de explotación de puntos limpios, centros de reutilización de residuos y saneamiento de viviendas | G54: 300/2023/00593 | H54: Sin lotes | I54: PREZERO ESPAÑA SAU | J54: Gestión de puntos limpios y centros de reutilización; saneamientos por requerimiento. | K54: Ambito municipal; ubicaciones concretas no incluidas | L54: 45622 | M54: 47447 | N54: Víctor Manuel Sarabia Herrero | O54: No acreditado | P54: 010 / 914 800 010 (atencion municipal, no gestor directo) | Q54: Saneamiento no es limpieza domestica ordinaria | R54: Vigente según Ayuntamiento; adjudicataria PREZERO acreditada (24/10/2024). Inicio contractual y fecha fin exacta sin acreditar. | FECHAS REVISADAS: Vigencia: 26/11/2024–25/11/2029. Inicio oficial; fin ordinario calculado por cinco años contractuales sin prórroga. | CONTROL DOCUMENTAL 21/10/2026: Adjudicataria identificada. PREZERO ESPAÑA figura adjudicataria de puntos limpios. El contrato es municipal; no son 21 concesiones independientes. [Base de evidencia: Datos confrontados con referencias aportadas; no hay resolución individual corroborada] | CONTRASTE ADICIONAL 21/10/2026: ADJUDICACIÓN: PREZERO ESPAÑA SA, 24/10/2024. El Ayuntamiento dispone de ficha oficial del contrato; compruébese formalización para fechas exactas. | S54: https://contratos.gobierto.es/licitaciones/4336157 https://contrataciondelestado.es/FileSystem/servlet/GetDocumentByIdServlet?DocumentIdParam=DX1ZAvwzaIUStPoibgXBVeTGIJOgffe86rdC19dt4dT5lTaSGg5Vq9cT4fT6Jv75jYAipcFv6g1zHenSv4lINo4IQyA7QON0MW%2BNRBCDa6cZyAJWGsSt0OzTSTyw9JAs&cifrado=QUC1GjXXSiLkydRHJBmbpw%3D%3D https://www.madrid.es/UnidadesDescentralizadas/LimpiezaUrbanaYResiduos/CONTRATOS_DG/CONTRATO-RES_PuntosLimpios/DocumentoPliegos_ContratoPuntosLimpios.pdf https://www.madrid.es/portales/munimadrid/es/Inicio/Medio-ambiente/Recogida-de-residuos/Contrato-de-servicios-de-explotacion-de-puntos-limpios-centros-de-reutilizacion-de-residuos-y-saneamiento-de-viviendas-en-la-ciudad-de-Madrid/?vgnextchannel=f81379ed268fe410VgnVCM1000000b205a0aRCRD&vgnextfmt=default&vgnextoid=8177150aabc46710VgnVCM2000001f4a900aRCRD | T54: REL-0053 | U54: 300/2023/00593|Sin lotes | V54: =IF(AND(SUM(IF('Consulta de contratos'!$K$1="",0,1),IF('Consulta de contratos'!$K$2="",0,1),IF('Consulta de contratos'!$K$3="",0,1),IF('Consulta de contratos'!$K$4="",0,1),IF('Consulta de contratos'!$K$5="",0,1),IF('Consulta de contratos'!$K$6="",0,1))>0,OR('Consulta de contratos'!$K$1="",A54='Consulta de contratos'!$K$1),OR('Consulta de contratos'!$K$2="",I54='Consulta de contratos'!$K$2),OR('Consulta de contratos'!$K$3="",C54='Consulta de contratos'!$K$3),OR('Consulta de contratos'!$K$4="",D54='Consulta de contratos'!$K$4),OR('Consulta de contratos'!$K$5="",E54='Consulta de contratos'!$K$5),OR('Consulta de contratos'!$K$6="",IFERROR(ISNUMBER(SEARCH("|"&'Consulta de contratos'!$K$6&"|",AF54)),FALSE))),1,0) -> 0 | W54: =IF(V54=1,SUM($V$2:V54),0) -> 0 | X54: FIN REGISTRADO POSTERIOR · EJECUCIÓN A CONFIRMAR | Y54: PREZERO | Z54: Grupo/familia pendiente de confirmar legalmente | AA54: 16/10/2026 | AF54: |PREZERO|
A55: Moncloa-Aravaca | B55: Residuos | C55: Área de Gobierno de Urbanismo, Medio Ambiente y Movilidad | D55: Dirección General de Servicios de Limpieza y Residuos | E55: Subdirección General de Recogida de Residuos | F55: Programa de actividades de sensibilización sobre separación de residuos y limpieza del espacio público | G55: 300/2026/00024 | H55: Sin lotes | I55: TALHER, S.A. | J55: Actividades educativas y de sensibilizacion | K55: Ambito municipal; no acredita actividad en cada distrito | N55: Víctor Manuel Sarabia Herrero | O55: No acreditado | P55: 010 / 914 800 010 (atencion municipal, no gestor directo) | Q55: Adjudicación publicada en datos de PLACSP; formalización e inicio efectivos sin contrastar. | ATENCIÓN · CONTRASTE 23/10/2026: el portal municipal incluye este expediente entre los contratos en vigor, mientras un agregador lo presenta como «Desistida». La resolución de adjudicación, la formalización y el inicio efectivo requieren comprobación directa. | R55: ADJUDICACIÓN 30/09/2026 A TALHER, S.A. (1.432.107 € sin IVA) recogida en LicitaLens a partir de PLACSP. Pendiente de verificar resolución y fecha de formalización en documento oficial; no certificar inicio efectivo. | CONTROL DOCUMENTAL 21/10/2026: Adjudicación localizada. Adjudicación a TALHER encontrada en plataformas que reproducen PLACSP; la resolución y la fecha de ejecución requieren lectura directa. [Base de evidencia: Ficha individual de publicación / agregador contrastada] | CONTRASTE DE FUENTES 23/10/2026: ficha municipal lo relaciona entre contratos en vigor; Gobierto muestra estado «Desistida», pese a reflejar datos de adjudicación del 30/09/2026. No tratar la formalización, la entrada en servicio ni la vigencia como acreditadas sin resolución. | S55: https://www.madrid.es/portales/munimadrid/es/Inicio/El-Ayuntamiento/Publicaciones/Listado-de-Publicaciones/Contratos-de-Recogida-de-Residuos/?vgnextchannel=f1aebadb6b997010VgnVCM100000dc0ca8c0RCRD&vgnextfmt=default&vgnextoid=429f71adf3d56910VgnVCM2000001f4a900aRCRD https://contratos.gobierto.es/licitaciones/5108890 https://licitalens.com/empresa/A08602815 https://www.madrid.es/portales/munimadrid/es/Inicio/Medio-ambiente/Recogida-de-residuos/Actividades-y-eventos/Contrato-de-servicio-de-actividades-de-sensibilizacion/?vgnextchannel=d04bbb21278fe410VgnVCM1000000b205a0aRCRD&vgnextfmt=default&vgnextoid=1d1f49ec5caef910VgnVCM200000f921e388RCRD | T55: REL-0054 | U55: 300/2026/00024|Sin lotes | V55: =IF(AND(SUM(IF('Consulta de contratos'!$K$1="",0,1),IF('Consulta de contratos'!$K$2="",0,1),IF('Consulta de contratos'!$K$3="",0,1),IF('Consulta de contratos'!$K$4="",0,1),IF('Consulta de contratos'!$K$5="",0,1),IF('Consulta de contratos'!$K$6="",0,1))>0,OR('Consulta de contratos'!$K$1="",A55='Consulta de contratos'!$K$1),OR('Consulta de contratos'!$K$2="",I55='Consulta de contratos'!$K$2),OR('Consulta de contratos'!$K$3="",C55='Consulta de contratos'!$K$3),OR('Consulta de contratos'!$K$4="",D55='Consulta de contratos'!$K$4),OR('Consulta de contratos'!$K$5="",E55='Consulta de contratos'!$K$5),OR('Consulta de contratos'!$K$6="",IFERROR(ISNUMBER(SEARCH("|"&'Consulta de contratos'!$K$6&"|",AF55)),FALSE))),1,0) -> 0 | W55: =IF(V55=1,SUM($V$2:V55),0) -> 0 | X55: ADJUDICACIÓN PUBLICADA EN DATOS PLACSP · FORMALIZACIÓN POR CONTRASTAR | Y55: CLECE | Z55: Grupo de empresa contrastado en fuente corporativa: https://clece.es/es/listado-clece-filiales/ | AA55: 16/10/2026 | AF55: |CLECE|
A56: Latina | B56: Residuos | C56: Área de Gobierno de Urbanismo, Medio Ambiente y Movilidad | D56: Dirección General de Servicios de Limpieza y Residuos | E56: Subdirección General de Recogida de Residuos | F56: Contenerización, recogida y transporte de residuos | G56: 131/2021/06296 | H56: 1 | I56: FCC MEDIO AMBIENTE, SA | J56: Recogida y transporte habitual | K56: Zona territorial del lote | L56: 44866 | M56: 47057 | N56: Víctor Manuel Sarabia Herrero | O56: No acreditado | P56: 010 / 914 800 010 (atencion municipal, no gestor directo) | Q56: Lote 1: eventos eje Castellana-Prado-Recoletos | R56: Concesión vigente; adjudicataria y fin 31/10/2028 contrastados en registro de concesiones municipal (15/10/2026). | FECHAS REVISADAS: Inicio 01/11/2022 acreditado por formalización de los cuatro lotes. | CONTROL DOCUMENTAL 21/10/2026: Adjudicación y fin publicados. Los cuatro lotes se pueden contrastar en el registro municipal de concesiones. Fin publicado: 31/10/2028. No generalizar ámbito de cada lote. [Base de evidencia: Portal municipal / resolución o resultado oficial consultado] | CONTRASTE ADICIONAL 21/10/2026: FUENTE MUNICIPAL: la concesión registra adjudicación diferenciada en los 4 lotes (FCC, UTE VAO, UTE Sur, CONTENUR) y fin contractual 31/10/2028. | S56: https://contratacion.madrid.es/concesiones/ https://contrataciondelestado.es/FileSystem/servlet/GetDocumentByIdServlet?DocumentIdParam=I52CDqtLbsdgHyWk6Tjc%2BH2t2QGKU1Ro9lcaZmb7V5J4T4CLRYtO18fD2fcADXQg90aL83OqQbUADSXvNu02Vt6kOzxNccJdTRf8umMgorI%3D&cifrado=QUC1GjXXSiLkydRHJBmbpw%3D%3D | T56: REL-0055 | U56: 131/2021/06296|1 | V56: =IF(AND(SUM(IF('Consulta de contratos'!$K$1="",0,1),IF('Consulta de contratos'!$K$2="",0,1),IF('Consulta de contratos'!$K$3="",0,1),IF('Consulta de contratos'!$K$4="",0,1),IF('Consulta de contratos'!$K$5="",0,1),IF('Consulta de contratos'!$K$6="",0,1))>0,OR('Consulta de contratos'!$K$1="",A56='Consulta de contratos'!$K$1),OR('Consulta de contratos'!$K$2="",I56='Consulta de contratos'!$K$2),OR('Consulta de contratos'!$K$3="",C56='Consulta de contratos'!$K$3),OR('Consulta de contratos'!$K$4="",D56='Consulta de contratos'!$K$4),OR('Consulta de contratos'!$K$5="",E56='Consulta de contratos'!$K$5),OR('Consulta de contratos'!$K$6="",IFERROR(ISNUMBER(SEARCH("|"&'Consulta de contratos'!$K$6&"|",AF56)),FALSE))),1,0) -> 0 | W56: =IF(V56=1,SUM($V$2:V56),0) -> 0 | X56: FIN REGISTRADO POSTERIOR · EJECUCIÓN A CONFIRMAR | Y56: FCC | Z56: Grupo/familia pendiente de confirmar legalmente | AA56: 16/10/2026 | AF56: |FCC|
A57: Latina | B57: Residuos | C57: Área de Gobierno de Urbanismo, Medio Ambiente y Movilidad | D57: Dirección General de Servicios de Limpieza y Residuos | E57: Subdirección General de Recogida de Residuos | F57: Contenerización, recogida y transporte de residuos | G57: 131/2021/06296 | H57: 4 | I57: CONTENUR SL | J57: Suministro, mantenimiento y limpieza de contenedores | K57: Toda la ciudad | L57: 44866 | M57: 47057 | N57: Víctor Manuel Sarabia Herrero | O57: No acreditado | P57: 010 / 914 800 010 (atencion municipal, no gestor directo) | Q57: No es vaciado ni recogida habitual | R57: Concesión vigente; adjudicataria y fin 31/10/2028 contrastados en registro de concesiones municipal (15/10/2026). | FECHAS REVISADAS: Inicio 01/11/2022 acreditado por formalización de los cuatro lotes. | CONTROL DOCUMENTAL 21/10/2026: Adjudicación y fin publicados. Los cuatro lotes se pueden contrastar en el registro municipal de concesiones. Fin publicado: 31/10/2028. No generalizar ámbito de cada lote. [Base de evidencia: Portal municipal / resolución o resultado oficial consultado] | CONTRASTE ADICIONAL 21/10/2026: FUENTE MUNICIPAL: la concesión registra adjudicación diferenciada en los 4 lotes (FCC, UTE VAO, UTE Sur, CONTENUR) y fin contractual 31/10/2028. | S57: https://contratacion.madrid.es/concesiones/ https://contrataciondelestado.es/FileSystem/servlet/GetDocumentByIdServlet?DocumentIdParam=I52CDqtLbsdgHyWk6Tjc%2BH2t2QGKU1Ro9lcaZmb7V5J4T4CLRYtO18fD2fcADXQg90aL83OqQbUADSXvNu02Vt6kOzxNccJdTRf8umMgorI%3D&cifrado=QUC1GjXXSiLkydRHJBmbpw%3D%3D | T57: REL-0056 | U57: 131/2021/06296|4 | V57: =IF(AND(SUM(IF('Consulta de contratos'!$K$1="",0,1),IF('Consulta de contratos'!$K$2="",0,1),IF('Consulta de contratos'!$K$3="",0,1),IF('Consulta de contratos'!$K$4="",0,1),IF('Consulta de contratos'!$K$5="",0,1),IF('Consulta de contratos'!$K$6="",0,1))>0,OR('Consulta de contratos'!$K$1="",A57='Consulta de contratos'!$K$1),OR('Consulta de contratos'!$K$2="",I57='Consulta de contratos'!$K$2),OR('Consulta de contratos'!$K$3="",C57='Consulta de contratos'!$K$3),OR('Consulta de contratos'!$K$4="",D57='Consulta de contratos'!$K$4),OR('Consulta de contratos'!$K$5="",E57='Consulta de contratos'!$K$5),OR('Consulta de contratos'!$K$6="",IFERROR(ISNUMBER(SEARCH("|"&'Consulta de contratos'!$K$6&"|",AF57)),FALSE))),1,0) -> 0 | W57: =IF(V57=1,SUM($V$2:V57),0) -> 0 | X57: FIN REGISTRADO POSTERIOR · EJECUCIÓN A CONFIRMAR | Y57: CONTENUR SL | Z57: Agrupación de consulta por nombre de adjudicataria; no consta matriz contrastada. | AA57: 16/10/2026 | AF57: |CONTENUR SL|
A58: Latina | B58: Residuos | C58: Área de Gobierno de Urbanismo, Medio Ambiente y Movilidad | D58: Dirección General de Servicios de Limpieza y Residuos | E58: Subdirección General de Recogida de Residuos | F58: Contenerización, recogida y transporte de residuos | G58: 131/2021/06296 | H58: 3 | I58: UTE 2022 Recogida Madrid Sur | J58: Recogida de pilas y baterias usadas | K58: Toda la ciudad | L58: 44866 | M58: 47057 | N58: Víctor Manuel Sarabia Herrero | O58: No acreditado | P58: 010 / 914 800 010 (atencion municipal, no gestor directo) | Q58: Tarea especial del lote 3 fuera de su zona habitual | R58: Concesión vigente; adjudicataria y fin 31/10/2028 contrastados en registro de concesiones municipal (15/10/2026). | FECHAS REVISADAS: Inicio 01/11/2022 acreditado por formalización de los cuatro lotes. | CONTROL DOCUMENTAL 21/10/2026: Adjudicación y fin publicados. Los cuatro lotes se pueden contrastar en el registro municipal de concesiones. Fin publicado: 31/10/2028. No generalizar ámbito de cada lote. [Base de evidencia: Portal municipal / resolución o resultado oficial consultado] | CONTRASTE ADICIONAL 21/10/2026: FUENTE MUNICIPAL: la concesión registra adjudicación diferenciada en los 4 lotes (FCC, UTE VAO, UTE Sur, CONTENUR) y fin contractual 31/10/2028. | S58: https://contratacion.madrid.es/concesiones/ https://contrataciondelestado.es/FileSystem/servlet/GetDocumentByIdServlet?DocumentIdParam=I52CDqtLbsdgHyWk6Tjc%2BH2t2QGKU1Ro9lcaZmb7V5J4T4CLRYtO18fD2fcADXQg90aL83OqQbUADSXvNu02Vt6kOzxNccJdTRf8umMgorI%3D&cifrado=QUC1GjXXSiLkydRHJBmbpw%3D%3D | T58: REL-0057 | U58: 131/2021/06296|3 | V58: =IF(AND(SUM(IF('Consulta de contratos'!$K$1="",0,1),IF('Consulta de contratos'!$K$2="",0,1),IF('Consulta de contratos'!$K$3="",0,1),IF('Consulta de contratos'!$K$4="",0,1),IF('Consulta de contratos'!$K$5="",0,1),IF('Consulta de contratos'!$K$6="",0,1))>0,OR('Consulta de contratos'!$K$1="",A58='Consulta de contratos'!$K$1),OR('Consulta de contratos'!$K$2="",I58='Consulta de contratos'!$K$2),OR('Consulta de contratos'!$K$3="",C58='Consulta de contratos'!$K$3),OR('Consulta de contratos'!$K$4="",D58='Consulta de contratos'!$K$4),OR('Consulta de contratos'!$K$5="",E58='Consulta de contratos'!$K$5),OR('Consulta de contratos'!$K$6="",IFERROR(ISNUMBER(SEARCH("|"&'Consulta de contratos'!$K$6&"|",AF58)),FALSE))),1,0) -> 0 | W58: =IF(V58=1,SUM($V$2:V58),0) -> 0 | X58: FIN REGISTRADO POSTERIOR · EJECUCIÓN A CONFIRMAR | Y58: PREZERO | URBASER | Z58: UTE: vínculo comercial; no implica propiedad | AA58: 16/10/2026 | AF58: |PREZERO|URBASER|
A59: Latina | B59: Residuos | C59: Área de Gobierno de Urbanismo, Medio Ambiente y Movilidad | D59: Dirección General de Servicios de Limpieza y Residuos | E59: Subdirección General de Recogida de Residuos | F59: Asistencia técnica para el mantenimiento, ampliación y mejora continua del sistema de gestión de la información de limpieza urbana, recogida de residuos y equipamientos urbanos | G59: 300/2025/00411 | H59: Sin lotes | I59: APORTA PLATAFORMA COOPERATIVA SCCL | J59: Mantenimiento y mejora del sistema de informacion | K59: Ambito municipal; no contrato propio del distrito | M59: 46850 | N59: Víctor Manuel Sarabia Herrero | O59: No acreditado | P59: 010 / 914 800 010 (atencion municipal, no gestor directo) | R59: Adjudicado 27/01/2026 y formalizado 08/04/2026. Fin publicado 07/04/2028 (posible prórroga 12 meses). Inicio de prestación no acreditado. | FECHAS SIN ACREDITAR: Formalización 08/04/2026 y fin en agregador 07/04/2028; no consta fecha independiente de inicio de prestación. La formalización no se convierte en inicio automático. | FUENTES REVISADAS 21/10/2026: Ayuntamiento publica objeto y pliegos; registro TED del contrato identifica formalización el 08/04/2026 y adjudicataria Aporta. No equivale a fecha de inicio operativo. | CONTROL DOCUMENTAL 21/10/2026: Adjudicataria identificada. APORTA PLATAFORMA COOPERATIVA figura en la base y en fichas de licitación; comprobar firma e hitos en el expediente. [Base de evidencia: Datos confrontados con referencias aportadas; no hay resolución individual corroborada] | CONTRASTE ADICIONAL 21/10/2026: ADJUDICACIÓN: APORTA PLATAFORMA COOPERATIVA SCCL, resolución de 27/01/2026, contrastada con publicación de licitación. | S59: https://contratos.gobierto.es/adjudicatarios/aporta-plataforma-cooperativa-sccl?locale=es https://www.madrid.es/portales/munimadrid/es/Inicio/Medio-ambiente/Limpieza-urbana/Contrato-de-servicio-de-asistencia-tecnica/?vgnextchannel=ddd2a694fde40910VgnVCM2000001f4a900aRCRD&vgnextfmt=default&vgnextoid=7c07475398a4e910VgnVCM200000f921e388RCRD https://contratos.gobierto.es/licitaciones/4668721?locale=es | T59: REL-0058 | U59: 300/2025/00411|Sin lotes | V59: =IF(AND(SUM(IF('Consulta de contratos'!$K$1="",0,1),IF('Consulta de contratos'!$K$2="",0,1),IF('Consulta de contratos'!$K$3="",0,1),IF('Consulta de contratos'!$K$4="",0,1),IF('Consulta de contratos'!$K$5="",0,1),IF('Consulta de contratos'!$K$6="",0,1))>0,OR('Consulta de contratos'!$K$1="",A59='Consulta de contratos'!$K$1),OR('Consulta de contratos'!$K$2="",I59='Consulta de contratos'!$K$2),OR('Consulta de contratos'!$K$3="",C59='Consulta de contratos'!$K$3),OR('Consulta de contratos'!$K$4="",D59='Consulta de contratos'!$K$4),OR('Consulta de contratos'!$K$5="",E59='Consulta de contratos'!$K$5),OR('Consulta de contratos'!$K$6="",IFERROR(ISNUMBER(SEARCH("|"&'Consulta de contratos'!$K$6&"|",AF59)),FALSE))),1,0) -> 0 | W59: =IF(V59=1,SUM($V$2:V59),0) -> 0 | X59: FIN REGISTRADO POSTERIOR · EJECUCIÓN A CONFIRMAR | Y59: APORTA PLATAFORMA COOPERATIVA SCCL | Z59: Agrupación de consulta por nombre de adjudicataria; no consta matriz contrastada. | AA59: 16/10/2026 | AF59: |APORTA PLATAFORMA COOPERATIVA SCCL|
A60: Latina | B60: Residuos | C60: Área de Gobierno de Urbanismo, Medio Ambiente y Movilidad | D60: Dirección General de Servicios de Limpieza y Residuos | E60: Subdirección General de Recogida de Residuos | F60: Gestión del servicio de explotación de puntos limpios, centros de reutilización de residuos y saneamiento de viviendas | G60: 300/2023/00593 | H60: Sin lotes | I60: PREZERO ESPAÑA SAU | J60: Gestión de puntos limpios y centros de reutilización; saneamientos por requerimiento. | K60: Ambito municipal; ubicaciones concretas no incluidas | L60: 45622 | M60: 47447 | N60: Víctor Manuel Sarabia Herrero | O60: No acreditado | P60: 010 / 914 800 010 (atencion municipal, no gestor directo) | Q60: Saneamiento no es limpieza domestica ordinaria | R60: Vigente según Ayuntamiento; adjudicataria PREZERO acreditada (24/10/2024). Inicio contractual y fecha fin exacta sin acreditar. | FECHAS REVISADAS: Vigencia: 26/11/2024–25/11/2029. Inicio oficial; fin ordinario calculado por cinco años contractuales sin prórroga. | CONTROL DOCUMENTAL 21/10/2026: Adjudicataria identificada. PREZERO ESPAÑA figura adjudicataria de puntos limpios. El contrato es municipal; no son 21 concesiones independientes. [Base de evidencia: Datos confrontados con referencias aportadas; no hay resolución individual corroborada] | CONTRASTE ADICIONAL 21/10/2026: ADJUDICACIÓN: PREZERO ESPAÑA SA, 24/10/2024. El Ayuntamiento dispone de ficha oficial del contrato; compruébese formalización para fechas exactas. | S60: https://contratos.gobierto.es/licitaciones/4336157 https://contrataciondelestado.es/FileSystem/servlet/GetDocumentByIdServlet?DocumentIdParam=DX1ZAvwzaIUStPoibgXBVeTGIJOgffe86rdC19dt4dT5lTaSGg5Vq9cT4fT6Jv75jYAipcFv6g1zHenSv4lINo4IQyA7QON0MW%2BNRBCDa6cZyAJWGsSt0OzTSTyw9JAs&cifrado=QUC1GjXXSiLkydRHJBmbpw%3D%3D https://www.madrid.es/UnidadesDescentralizadas/LimpiezaUrbanaYResiduos/CONTRATOS_DG/CONTRATO-RES_PuntosLimpios/DocumentoPliegos_ContratoPuntosLimpios.pdf https://www.madrid.es/portales/munimadrid/es/Inicio/Medio-ambiente/Recogida-de-residuos/Contrato-de-servicios-de-explotacion-de-puntos-limpios-centros-de-reutilizacion-de-residuos-y-saneamiento-de-viviendas-en-la-ciudad-de-Madrid/?vgnextchannel=f81379ed268fe410VgnVCM1000000b205a0aRCRD&vgnextfmt=default&vgnextoid=8177150aabc46710VgnVCM2000001f4a900aRCRD | T60: REL-0059 | U60: 300/2023/00593|Sin lotes | V60: =IF(AND(SUM(IF('Consulta de contratos'!$K$1="",0,1),IF('Consulta de contratos'!$K$2="",0,1),IF('Consulta de contratos'!$K$3="",0,1),IF('Consulta de contratos'!$K$4="",0,1),IF('Consulta de contratos'!$K$5="",0,1),IF('Consulta de contratos'!$K$6="",0,1))>0,OR('Consulta de contratos'!$K$1="",A60='Consulta de contratos'!$K$1),OR('Consulta de contratos'!$K$2="",I60='Consulta de contratos'!$K$2),OR('Consulta de contratos'!$K$3="",C60='Consulta de contratos'!$K$3),OR('Consulta de contratos'!$K$4="",D60='Consulta de contratos'!$K$4),OR('Consulta de contratos'!$K$5="",E60='Consulta de contratos'!$K$5),OR('Consulta de contratos'!$K$6="",IFERROR(ISNUMBER(SEARCH("|"&'Consulta de contratos'!$K$6&"|",AF60)),FALSE))),1,0) -> 0 | W60: =IF(V60=1,SUM($V$2:V60),0) -> 0 | X60: FIN REGISTRADO POSTERIOR · EJECUCIÓN A CONFIRMAR | Y60: PREZERO | Z60: Grupo/familia pendiente de confirmar legalmente | AA60: 16/10/2026 | AF60: |PREZERO|
A61: Latina | B61: Residuos | C61: Área de Gobierno de Urbanismo, Medio Ambiente y Movilidad | D61: Dirección General de Servicios de Limpieza y Residuos | E61: Subdirección General de Recogida de Residuos | F61: Programa de actividades de sensibilización sobre separación de residuos y limpieza del espacio público | G61: 300/2026/00024 | H61: Sin lotes | I61: TALHER, S.A. | J61: Actividades educativas y de sensibilizacion | K61: Ambito municipal; no acredita actividad en cada distrito | N61: Víctor Manuel Sarabia Herrero | O61: No acreditado | P61: 010 / 914 800 010 (atencion municipal, no gestor directo) | Q61: Adjudicación publicada en datos de PLACSP; formalización e inicio efectivos sin contrastar. | ATENCIÓN · CONTRASTE 23/10/2026: el portal municipal incluye este expediente entre los contratos en vigor, mientras un agregador lo presenta como «Desistida». La resolución de adjudicación, la formalización y el inicio efectivo requieren comprobación directa. | R61: ADJUDICACIÓN 30/09/2026 A TALHER, S.A. (1.432.107 € sin IVA) recogida en LicitaLens a partir de PLACSP. Pendiente de verificar resolución y fecha de formalización en documento oficial; no certificar inicio efectivo. | CONTROL DOCUMENTAL 21/10/2026: Adjudicación localizada. Adjudicación a TALHER encontrada en plataformas que reproducen PLACSP; la resolución y la fecha de ejecución requieren lectura directa. [Base de evidencia: Ficha individual de publicación / agregador contrastada] | CONTRASTE DE FUENTES 23/10/2026: ficha municipal lo relaciona entre contratos en vigor; Gobierto muestra estado «Desistida», pese a reflejar datos de adjudicación del 30/09/2026. No tratar la formalización, la entrada en servicio ni la vigencia como acreditadas sin resolución. | S61: https://www.madrid.es/portales/munimadrid/es/Inicio/El-Ayuntamiento/Publicaciones/Listado-de-Publicaciones/Contratos-de-Recogida-de-Residuos/?vgnextchannel=f1aebadb6b997010VgnVCM100000dc0ca8c0RCRD&vgnextfmt=default&vgnextoid=429f71adf3d56910VgnVCM2000001f4a900aRCRD https://contratos.gobierto.es/licitaciones/5108890 https://licitalens.com/empresa/A08602815 https://www.madrid.es/portales/munimadrid/es/Inicio/Medio-ambiente/Recogida-de-residuos/Actividades-y-eventos/Contrato-de-servicio-de-actividades-de-sensibilizacion/?vgnextchannel=d04bbb21278fe410VgnVCM1000000b205a0aRCRD&vgnextfmt=default&vgnextoid=1d1f49ec5caef910VgnVCM200000f921e388RCRD | T61: REL-0060 | U61: 300/2026/00024|Sin lotes | V61: =IF(AND(SUM(IF('Consulta de contratos'!$K$1="",0,1),IF('Consulta de contratos'!$K$2="",0,1),IF('Consulta de contratos'!$K$3="",0,1),IF('Consulta de contratos'!$K$4="",0,1),IF('Consulta de contratos'!$K$5="",0,1),IF('Consulta de contratos'!$K$6="",0,1))>0,OR('Consulta de contratos'!$K$1="",A61='Consulta de contratos'!$K$1),OR('Consulta de contratos'!$K$2="",I61='Consulta de contratos'!$K$2),OR('Consulta de contratos'!$K$3="",C61='Consulta de contratos'!$K$3),OR('Consulta de contratos'!$K$4="",D61='Consulta de contratos'!$K$4),OR('Consulta de contratos'!$K$5="",E61='Consulta de contratos'!$K$5),OR('Consulta de contratos'!$K$6="",IFERROR(ISNUMBER(SEARCH("|"&'Consulta de contratos'!$K$6&"|",AF61)),FALSE))),1,0) -> 0 | W61: =IF(V61=1,SUM($V$2:V61),0) -> 0 | X61: ADJUDICACIÓN PUBLICADA EN DATOS PLACSP · FORMALIZACIÓN POR CONTRASTAR | Y61: CLECE | Z61: Grupo de empresa contrastado en fuente corporativa: https://clece.es/es/listado-clece-filiales/ | AA61: 16/10/2026 | AF61: |CLECE|
A62: Carabanchel | B62: Residuos | C62: Área de Gobierno de Urbanismo, Medio Ambiente y Movilidad | D62: Dirección General de Servicios de Limpieza y Residuos | E62: Subdirección General de Recogida de Residuos | F62: Contenerización, recogida y transporte de residuos | G62: 131/2021/06296 | H62: 3 | I62: UTE 2022 Recogida Madrid Sur | J62: Recogida y transporte habitual | K62: Zona territorial del lote | L62: 44866 | M62: 47057 | N62: Víctor Manuel Sarabia Herrero | O62: No acreditado | P62: 010 / 914 800 010 (atencion municipal, no gestor directo) | R62: Concesión vigente; adjudicataria y fin 31/10/2028 contrastados en registro de concesiones municipal (15/10/2026). | FECHAS REVISADAS: Inicio 01/11/2022 acreditado por formalización de los cuatro lotes. | CONTROL DOCUMENTAL 21/10/2026: Adjudicación y fin publicados. Los cuatro lotes se pueden contrastar en el registro municipal de concesiones. Fin publicado: 31/10/2028. No generalizar ámbito de cada lote. [Base de evidencia: Portal municipal / resolución o resultado oficial consultado] | CONTRASTE ADICIONAL 21/10/2026: FUENTE MUNICIPAL: la concesión registra adjudicación diferenciada en los 4 lotes (FCC, UTE VAO, UTE Sur, CONTENUR) y fin contractual 31/10/2028. | S62: https://contratacion.madrid.es/concesiones/ https://contrataciondelestado.es/FileSystem/servlet/GetDocumentByIdServlet?DocumentIdParam=I52CDqtLbsdgHyWk6Tjc%2BH2t2QGKU1Ro9lcaZmb7V5J4T4CLRYtO18fD2fcADXQg90aL83OqQbUADSXvNu02Vt6kOzxNccJdTRf8umMgorI%3D&cifrado=QUC1GjXXSiLkydRHJBmbpw%3D%3D | T62: REL-0061 | U62: 131/2021/06296|3 | V62: =IF(AND(SUM(IF('Consulta de contratos'!$K$1="",0,1),IF('Consulta de contratos'!$K$2="",0,1),IF('Consulta de contratos'!$K$3="",0,1),IF('Consulta de contratos'!$K$4="",0,1),IF('Consulta de contratos'!$K$5="",0,1),IF('Consulta de contratos'!$K$6="",0,1))>0,OR('Consulta de contratos'!$K$1="",A62='Consulta de contratos'!$K$1),OR('Consulta de contratos'!$K$2="",I62='Consulta de contratos'!$K$2),OR('Consulta de contratos'!$K$3="",C62='Consulta de contratos'!$K$3),OR('Consulta de contratos'!$K$4="",D62='Consulta de contratos'!$K$4),OR('Consulta de contratos'!$K$5="",E62='Consulta de contratos'!$K$5),OR('Consulta de contratos'!$K$6="",IFERROR(ISNUMBER(SEARCH("|"&'Consulta de contratos'!$K$6&"|",AF62)),FALSE))),1,0) -> 0 | W62: =IF(V62=1,SUM($V$2:V62),0) -> 0 | X62: FIN REGISTRADO POSTERIOR · EJECUCIÓN A CONFIRMAR | Y62: PREZERO | URBASER | Z62: UTE: vínculo comercial; no implica propiedad | AA62: 16/10/2026 | AF62: |PREZERO|URBASER|
A63: Carabanchel | B63: Residuos | C63: Área de Gobierno de Urbanismo, Medio Ambiente y Movilidad | D63: Dirección General de Servicios de Limpieza y Residuos | E63: Subdirección General de Recogida de Residuos | F63: Contenerización, recogida y transporte de residuos | G63: 131/2021/06296 | H63: 4 | I63: CONTENUR SL | J63: Suministro, mantenimiento y limpieza de contenedores | K63: Toda la ciudad | L63: 44866 | M63: 47057 | N63: Víctor Manuel Sarabia Herrero | O63: No acreditado | P63: 010 / 914 800 010 (atencion municipal, no gestor directo) | Q63: No es vaciado ni recogida habitual | R63: Concesión vigente; adjudicataria y fin 31/10/2028 contrastados en registro de concesiones municipal (15/10/2026). | FECHAS REVISADAS: Inicio 01/11/2022 acreditado por formalización de los cuatro lotes. | CONTROL DOCUMENTAL 21/10/2026: Adjudicación y fin publicados. Los cuatro lotes se pueden contrastar en el registro municipal de concesiones. Fin publicado: 31/10/2028. No generalizar ámbito de cada lote. [Base de evidencia: Portal municipal / resolución o resultado oficial consultado] | CONTRASTE ADICIONAL 21/10/2026: FUENTE MUNICIPAL: la concesión registra adjudicación diferenciada en los 4 lotes (FCC, UTE VAO, UTE Sur, CONTENUR) y fin contractual 31/10/2028. | S63: https://contratacion.madrid.es/concesiones/ https://contrataciondelestado.es/FileSystem/servlet/GetDocumentByIdServlet?DocumentIdParam=I52CDqtLbsdgHyWk6Tjc%2BH2t2QGKU1Ro9lcaZmb7V5J4T4CLRYtO18fD2fcADXQg90aL83OqQbUADSXvNu02Vt6kOzxNccJdTRf8umMgorI%3D&cifrado=QUC1GjXXSiLkydRHJBmbpw%3D%3D | T63: REL-0062 | U63: 131/2021/06296|4 | V63: =IF(AND(SUM(IF('Consulta de contratos'!$K$1="",0,1),IF('Consulta de contratos'!$K$2="",0,1),IF('Consulta de contratos'!$K$3="",0,1),IF('Consulta de contratos'!$K$4="",0,1),IF('Consulta de contratos'!$K$5="",0,1),IF('Consulta de contratos'!$K$6="",0,1))>0,OR('Consulta de contratos'!$K$1="",A63='Consulta de contratos'!$K$1),OR('Consulta de contratos'!$K$2="",I63='Consulta de contratos'!$K$2),OR('Consulta de contratos'!$K$3="",C63='Consulta de contratos'!$K$3),OR('Consulta de contratos'!$K$4="",D63='Consulta de contratos'!$K$4),OR('Consulta de contratos'!$K$5="",E63='Consulta de contratos'!$K$5),OR('Consulta de contratos'!$K$6="",IFERROR(ISNUMBER(SEARCH("|"&'Consulta de contratos'!$K$6&"|",AF63)),FALSE))),1,0) -> 0 | W63: =IF(V63=1,SUM($V$2:V63),0) -> 0 | X63: FIN REGISTRADO POSTERIOR · EJECUCIÓN A CONFIRMAR | Y63: CONTENUR SL | Z63: Agrupación de consulta por nombre de adjudicataria; no consta matriz contrastada. | AA63: 16/10/2026 | AF63: |CONTENUR SL|
A64: Carabanchel | B64: Residuos | C64: Área de Gobierno de Urbanismo, Medio Ambiente y Movilidad | D64: Dirección General de Servicios de Limpieza y Residuos | E64: Subdirección General de Recogida de Residuos | F64: Contenerización, recogida y transporte de residuos | G64: 131/2021/06296 | H64: 3 | I64: UTE 2022 Recogida Madrid Sur | J64: Recogida de pilas y baterias usadas | K64: Toda la ciudad | L64: 44866 | M64: 47057 | N64: Víctor Manuel Sarabia Herrero | O64: No acreditado | P64: 010 / 914 800 010 (atencion municipal, no gestor directo) | Q64: Tarea especial del lote 3 fuera de su zona habitual | R64: Concesión vigente; adjudicataria y fin 31/10/2028 contrastados en registro de concesiones municipal (15/10/2026). | FECHAS REVISADAS: Inicio 01/11/2022 acreditado por formalización de los cuatro lotes. | CONTROL DOCUMENTAL 21/10/2026: Adjudicación y fin publicados. Los cuatro lotes se pueden contrastar en el registro municipal de concesiones. Fin publicado: 31/10/2028. No generalizar ámbito de cada lote. [Base de evidencia: Portal municipal / resolución o resultado oficial consultado] | CONTRASTE ADICIONAL 21/10/2026: FUENTE MUNICIPAL: la concesión registra adjudicación diferenciada en los 4 lotes (FCC, UTE VAO, UTE Sur, CONTENUR) y fin contractual 31/10/2028. | S64: https://contratacion.madrid.es/concesiones/ https://contrataciondelestado.es/FileSystem/servlet/GetDocumentByIdServlet?DocumentIdParam=I52CDqtLbsdgHyWk6Tjc%2BH2t2QGKU1Ro9lcaZmb7V5J4T4CLRYtO18fD2fcADXQg90aL83OqQbUADSXvNu02Vt6kOzxNccJdTRf8umMgorI%3D&cifrado=QUC1GjXXSiLkydRHJBmbpw%3D%3D | T64: REL-0063 | U64: 131/2021/06296|3 | V64: =IF(AND(SUM(IF('Consulta de contratos'!$K$1="",0,1),IF('Consulta de contratos'!$K$2="",0,1),IF('Consulta de contratos'!$K$3="",0,1),IF('Consulta de contratos'!$K$4="",0,1),IF('Consulta de contratos'!$K$5="",0,1),IF('Consulta de contratos'!$K$6="",0,1))>0,OR('Consulta de contratos'!$K$1="",A64='Consulta de contratos'!$K$1),OR('Consulta de contratos'!$K$2="",I64='Consulta de contratos'!$K$2),OR('Consulta de contratos'!$K$3="",C64='Consulta de contratos'!$K$3),OR('Consulta de contratos'!$K$4="",D64='Consulta de contratos'!$K$4),OR('Consulta de contratos'!$K$5="",E64='Consulta de contratos'!$K$5),OR('Consulta de contratos'!$K$6="",IFERROR(ISNUMBER(SEARCH("|"&'Consulta de contratos'!$K$6&"|",AF64)),FALSE))),1,0) -> 0 | W64: =IF(V64=1,SUM($V$2:V64),0) -> 0 | X64: FIN REGISTRADO POSTERIOR · EJECUCIÓN A CONFIRMAR | Y64: PREZERO | URBASER | Z64: UTE: vínculo comercial; no implica propiedad | AA64: 16/10/2026 | AF64: |PREZERO|URBASER|
A65: Carabanchel | B65: Residuos | C65: Área de Gobierno de Urbanismo, Medio Ambiente y Movilidad | D65: Dirección General de Servicios de Limpieza y Residuos | E65: Subdirección General de Recogida de Residuos | F65: Asistencia técnica para el mantenimiento, ampliación y mejora continua del sistema de gestión de la información de limpieza urbana, recogida de residuos y equipamientos urbanos | G65: 300/2025/00411 | H65: Sin lotes | I65: APORTA PLATAFORMA COOPERATIVA SCCL | J65: Mantenimiento y mejora del sistema de informacion | K65: Ambito municipal; no contrato propio del distrito | M65: 46850 | N65: Víctor Manuel Sarabia Herrero | O65: No acreditado | P65: 010 / 914 800 010 (atencion municipal, no gestor directo) | R65: Adjudicado 27/01/2026 y formalizado 08/04/2026. Fin publicado 07/04/2028 (posible prórroga 12 meses). Inicio de prestación no acreditado. | FECHAS SIN ACREDITAR: Formalización 08/04/2026 y fin en agregador 07/04/2028; no consta fecha independiente de inicio de prestación. La formalización no se convierte en inicio automático. | FUENTES REVISADAS 21/10/2026: Ayuntamiento publica objeto y pliegos; registro TED del contrato identifica formalización el 08/04/2026 y adjudicataria Aporta. No equivale a fecha de inicio operativo. | CONTROL DOCUMENTAL 21/10/2026: Adjudicataria identificada. APORTA PLATAFORMA COOPERATIVA figura en la base y en fichas de licitación; comprobar firma e hitos en el expediente. [Base de evidencia: Datos confrontados con referencias aportadas; no hay resolución individual corroborada] | CONTRASTE ADICIONAL 21/10/2026: ADJUDICACIÓN: APORTA PLATAFORMA COOPERATIVA SCCL, resolución de 27/01/2026, contrastada con publicación de licitación. | S65: https://contratos.gobierto.es/adjudicatarios/aporta-plataforma-cooperativa-sccl?locale=es https://www.madrid.es/portales/munimadrid/es/Inicio/Medio-ambiente/Limpieza-urbana/Contrato-de-servicio-de-asistencia-tecnica/?vgnextchannel=ddd2a694fde40910VgnVCM2000001f4a900aRCRD&vgnextfmt=default&vgnextoid=7c07475398a4e910VgnVCM200000f921e388RCRD https://contratos.gobierto.es/licitaciones/4668721?locale=es | T65: REL-0064 | U65: 300/2025/00411|Sin lotes | V65: =IF(AND(SUM(IF('Consulta de contratos'!$K$1="",0,1),IF('Consulta de contratos'!$K$2="",0,1),IF('Consulta de contratos'!$K$3="",0,1),IF('Consulta de contratos'!$K$4="",0,1),IF('Consulta de contratos'!$K$5="",0,1),IF('Consulta de contratos'!$K$6="",0,1))>0,OR('Consulta de contratos'!$K$1="",A65='Consulta de contratos'!$K$1),OR('Consulta de contratos'!$K$2="",I65='Consulta de contratos'!$K$2),OR('Consulta de contratos'!$K$3="",C65='Consulta de contratos'!$K$3),OR('Consulta de contratos'!$K$4="",D65='Consulta de contratos'!$K$4),OR('Consulta de contratos'!$K$5="",E65='Consulta de contratos'!$K$5),OR('Consulta de contratos'!$K$6="",IFERROR(ISNUMBER(SEARCH("|"&'Consulta de contratos'!$K$6&"|",AF65)),FALSE))),1,0) -> 0 | W65: =IF(V65=1,SUM($V$2:V65),0) -> 0 | X65: FIN REGISTRADO POSTERIOR · EJECUCIÓN A CONFIRMAR | Y65: APORTA PLATAFORMA COOPERATIVA SCCL | Z65: Agrupación de consulta por nombre de adjudicataria; no consta matriz contrastada. | AA65: 16/10/2026 | AF65: |APORTA PLATAFORMA COOPERATIVA SCCL|
